Workbook

Sheet C_Outstanding Payment
A2: DAILY PAYMENT SCHEDULE | B2: SBI | C2: IDBI | D2: BOI | E2: PAYABLE AMOUNT (INR) | G2: MONTHLY PAYABLE SUMMARY | H2: AMOUNT (INR)
A3: =WORKDAY(TODAY(), 0) -> 46178 | B3: =SUMIFS('LC-Final List'!$W:$W,'LC-Final List'!$Y:$Y,$A3,'LC-Final List'!$AE:$AE,"*Unpaid*",'LC-Final List'!$E:$E,B$2) -> 103736160 | C3: =SUMIFS('LC-Final List'!$W:$W,'LC-Final List'!$Y:$Y,$A3,'LC-Final List'!$AE:$AE,"*Unpaid*",'LC-Final List'!$E:$E,C$2) -> 0 | D3: =SUMIFS('LC-Final List'!$W:$W,'LC-Final List'!$Y:$Y,$A3,'LC-Final List'!$AE:$AE,"*Unpaid*",'LC-Final List'!$E:$E,D$2) -> 0 | E3: =SUMIFS('LC-Final List'!$W:$W,'LC-Final List'!$Y:$Y,$A3,'LC-Final List'!$AE:$AE,"*Unpaid*") -> 103736160 | G3: January26 | H3: =SUMIFS('LC-Final List'!$W:$W, 'LC-Final List'!$AC:$AC, G3, 'LC-Final List'!$AE:$AE, "*Unpaid*") -> 0
A4: =WORKDAY(TODAY(), 1) -> 46181 | B4: =SUMIFS('LC-Final List'!$W:$W,'LC-Final List'!$Y:$Y,$A4,'LC-Final List'!$AE:$AE,"*Unpaid*",'LC-Final List'!$E:$E,B$2) -> 1.1980314e+08 | C4: =SUMIFS('LC-Final List'!$W:$W,'LC-Final List'!$Y:$Y,$A4,'LC-Final List'!$AE:$AE,"*Unpaid*",'LC-Final List'!$E:$E,C$2) -> 0 | D4: =SUMIFS('LC-Final List'!$W:$W,'LC-Final List'!$Y:$Y,$A4,'LC-Final List'!$AE:$AE,"*Unpaid*",'LC-Final List'!$E:$E,D$2) -> 0 | E4: =SUMIFS('LC-Final List'!$W:$W,'LC-Final List'!$Y:$Y,$A4,'LC-Final List'!$AE:$AE,"*Unpaid*") -> 1.1980314e+08 | G4: February26 | H4: =SUMIFS('LC-Final List'!$W:$W, 'LC-Final List'!$AC:$AC, G4, 'LC-Final List'!$AE:$AE, "*Unpaid*") -> 0
A5: =WORKDAY(TODAY(), 2) -> 46182 | B5: =SUMIFS('LC-Final List'!$W:$W,'LC-Final List'!$Y:$Y,$A5,'LC-Final List'!$AE:$AE,"*Unpaid*",'LC-Final List'!$E:$E,B$2) -> 4.5797035e+08 | C5: =SUMIFS('LC-Final List'!$W:$W,'LC-Final List'!$Y:$Y,$A5,'LC-Final List'!$AE:$AE,"*Unpaid*",'LC-Final List'!$E:$E,C$2) -> 0 | D5: =SUMIFS('LC-Final List'!$W:$W,'LC-Final List'!$Y:$Y,$A5,'LC-Final List'!$AE:$AE,"*Unpaid*",'LC-Final List'!$E:$E,D$2) -> 72808013 | E5: =SUMIFS('LC-Final List'!$W:$W,'LC-Final List'!$Y:$Y,$A5,'LC-Final List'!$AE:$AE,"*Unpaid*") -> 5.3077836e+08 | G5: March26 | H5: =SUMIFS('LC-Final List'!$W:$W, 'LC-Final List'!$AC:$AC, G5, 'LC-Final List'!$AE:$AE, "*Unpaid*") -> 0
A6: =WORKDAY(TODAY(), 3) -> 46183 | B6: =SUMIFS('LC-Final List'!$W:$W,'LC-Final List'!$Y:$Y,$A6,'LC-Final List'!$AE:$AE,"*Unpaid*",'LC-Final List'!$E:$E,B$2) -> 0 | C6: =SUMIFS('LC-Final List'!$W:$W,'LC-Final List'!$Y:$Y,$A6,'LC-Final List'!$AE:$AE,"*Unpaid*",'LC-Final List'!$E:$E,C$2) -> 0 | D6: =SUMIFS('LC-Final List'!$W:$W,'LC-Final List'!$Y:$Y,$A6,'LC-Final List'!$AE:$AE,"*Unpaid*",'LC-Final List'!$E:$E,D$2) -> 0 | E6: =SUMIFS('LC-Final List'!$W:$W,'LC-Final List'!$Y:$Y,$A6,'LC-Final List'!$AE:$AE,"*Unpaid*") -> 0 | G6: April26 | H6: =SUMIFS('LC-Final List'!$W:$W, 'LC-Final List'!$AC:$AC, G6, 'LC-Final List'!$AE:$AE, "*Unpaid*") -> 0
A7: =WORKDAY(TODAY(), 4) -> 46184 | B7: =SUMIFS('LC-Final List'!$W:$W,'LC-Final List'!$Y:$Y,$A7,'LC-Final List'!$AE:$AE,"*Unpaid*",'LC-Final List'!$E:$E,B$2) -> 2.4195292e+08 | C7: =SUMIFS('LC-Final List'!$W:$W,'LC-Final List'!$Y:$Y,$A7,'LC-Final List'!$AE:$AE,"*Unpaid*",'LC-Final List'!$E:$E,C$2) -> 0 | D7: =SUMIFS('LC-Final List'!$W:$W,'LC-Final List'!$Y:$Y,$A7,'LC-Final List'!$AE:$AE,"*Unpaid*",'LC-Final List'!$E:$E,D$2) -> 0 | E7: =SUMIFS('LC-Final List'!$W:$W,'LC-Final List'!$Y:$Y,$A7,'LC-Final List'!$AE:$AE,"*Unpaid*") -> 2.4195292e+08 | G7: May26 | H7: =SUMIFS('LC-Final List'!$W:$W, 'LC-Final List'!$AC:$AC, G7, 'LC-Final List'!$AE:$AE, "*Unpaid*") -> 0
A8: =WORKDAY(TODAY(), 5) -> 46185 | B8: =SUMIFS('LC-Final List'!$W:$W,'LC-Final List'!$Y:$Y,$A8,'LC-Final List'!$AE:$AE,"*Unpaid*",'LC-Final List'!$E:$E,B$2) -> 3.7510745e+08 | C8: =SUMIFS('LC-Final List'!$W:$W,'LC-Final List'!$Y:$Y,$A8,'LC-Final List'!$AE:$AE,"*Unpaid*",'LC-Final List'!$E:$E,C$2) -> 0 | D8: =SUMIFS('LC-Final List'!$W:$W,'LC-Final List'!$Y:$Y,$A8,'LC-Final List'!$AE:$AE,"*Unpaid*",'LC-Final List'!$E:$E,D$2) -> 169992000 | E8: =SUMIFS('LC-Final List'!$W:$W,'LC-Final List'!$Y:$Y,$A8,'LC-Final List'!$AE:$AE,"*Unpaid*") -> 5.4509945e+08 | G8: 46174 | H8: =SUMIFS('LC-Final List'!$W:$W, 'LC-Final List'!$AC:$AC, G8, 'LC-Final List'!$AE:$AE, "*Unpaid*") -> 3.038332e+09
A9: =WORKDAY(TODAY(), 6) -> 46188 | B9: =SUMIFS('LC-Final List'!$W:$W,'LC-Final List'!$Y:$Y,$A9,'LC-Final List'!$AE:$AE,"*Unpaid*",'LC-Final List'!$E:$E,B$2) -> 3.7662287e+08 | C9: =SUMIFS('LC-Final List'!$W:$W,'LC-Final List'!$Y:$Y,$A9,'LC-Final List'!$AE:$AE,"*Unpaid*",'LC-Final List'!$E:$E,C$2) -> 0 | D9: =SUMIFS('LC-Final List'!$W:$W,'LC-Final List'!$Y:$Y,$A9,'LC-Final List'!$AE:$AE,"*Unpaid*",'LC-Final List'!$E:$E,D$2) -> 232502400 | E9: =SUMIFS('LC-Final List'!$W:$W,'LC-Final List'!$Y:$Y,$A9,'LC-Final List'!$AE:$AE,"*Unpaid*") -> 6.0912527e+08 | G9: 46204 | H9: =SUMIFS('LC-Final List'!$W:$W, 'LC-Final List'!$AC:$AC, G9, 'LC-Final List'!$AE:$AE, "*Unpaid*") -> 1.2268206e+09
A10: =WORKDAY(TODAY(), 7) -> 46189 | B10: =SUMIFS('LC-Final List'!$W:$W,'LC-Final List'!$Y:$Y,$A10,'LC-Final List'!$AE:$AE,"*Unpaid*",'LC-Final List'!$E:$E,B$2) -> 76898304 | C10: =SUMIFS('LC-Final List'!$W:$W,'LC-Final List'!$Y:$Y,$A10,'LC-Final List'!$AE:$AE,"*Unpaid*",'LC-Final List'!$E:$E,C$2) -> 0 | D10: =SUMIFS('LC-Final List'!$W:$W,'LC-Final List'!$Y:$Y,$A10,'LC-Final List'!$AE:$AE,"*Unpaid*",'LC-Final List'!$E:$E,D$2) -> 0 | E10: =SUMIFS('LC-Final List'!$W:$W,'LC-Final List'!$Y:$Y,$A10,'LC-Final List'!$AE:$AE,"*Unpaid*") -> 76898304 | G10: 46235 | H10: =SUMIFS('LC-Final List'!$W:$W, 'LC-Final List'!$AC:$AC, G10, 'LC-Final List'!$AE:$AE, "*Unpaid*") -> 28999680
A11: =WORKDAY(TODAY(), 8) -> 46190 | B11: =SUMIFS('LC-Final List'!$W:$W,'LC-Final List'!$Y:$Y,$A11,'LC-Final List'!$AE:$AE,"*Unpaid*",'LC-Final List'!$E:$E,B$2) -> 2.6303468e+08 | C11: =SUMIFS('LC-Final List'!$W:$W,'LC-Final List'!$Y:$Y,$A11,'LC-Final List'!$AE:$AE,"*Unpaid*",'LC-Final List'!$E:$E,C$2) -> 0 | D11: =SUMIFS('LC-Final List'!$W:$W,'LC-Final List'!$Y:$Y,$A11,'LC-Final List'!$AE:$AE,"*Unpaid*",'LC-Final List'!$E:$E,D$2) -> 0 | E11: =SUMIFS('LC-Final List'!$W:$W,'LC-Final List'!$Y:$Y,$A11,'LC-Final List'!$AE:$AE,"*Unpaid*") -> 2.6303468e+08 | G11: 46266 | H11: =SUMIFS('LC-Final List'!$W:$W, 'LC-Final List'!$AC:$AC, G11, 'LC-Final List'!$AE:$AE, "*Unpaid*") -> 122867712
A12: =WORKDAY(TODAY(), 9) -> 46191 | B12: =SUMIFS('LC-Final List'!$W:$W,'LC-Final List'!$Y:$Y,$A12,'LC-Final List'!$AE:$AE,"*Unpaid*",'LC-Final List'!$E:$E,B$2) -> 0 | C12: =SUMIFS('LC-Final List'!$W:$W,'LC-Final List'!$Y:$Y,$A12,'LC-Final List'!$AE:$AE,"*Unpaid*",'LC-Final List'!$E:$E,C$2) -> 0 | D12: =SUMIFS('LC-Final List'!$W:$W,'LC-Final List'!$Y:$Y,$A12,'LC-Final List'!$AE:$AE,"*Unpaid*",'LC-Final List'!$E:$E,D$2) -> 0 | E12: =SUMIFS('LC-Final List'!$W:$W,'LC-Final List'!$Y:$Y,$A12,'LC-Final List'!$AE:$AE,"*Unpaid*") -> 0
A13: =WORKDAY(TODAY(),10) -> 46192 | B13: =SUMIFS('LC-Final List'!$W:$W,'LC-Final List'!$Y:$Y,$A13,'LC-Final List'!$AE:$AE,"*Unpaid*",'LC-Final List'!$E:$E,B$2) -> 0 | C13: =SUMIFS('LC-Final List'!$W:$W,'LC-Final List'!$Y:$Y,$A13,'LC-Final List'!$AE:$AE,"*Unpaid*",'LC-Final List'!$E:$E,C$2) -> 0 | D13: =SUMIFS('LC-Final List'!$W:$W,'LC-Final List'!$Y:$Y,$A13,'LC-Final List'!$AE:$AE,"*Unpaid*",'LC-Final List'!$E:$E,D$2) -> 0 | E13: =SUMIFS('LC-Final List'!$W:$W,'LC-Final List'!$Y:$Y,$A13,'LC-Final List'!$AE:$AE,"*Unpaid*") -> 0
A14: =WORKDAY(TODAY(),11) -> 46195 | B14: =SUMIFS('LC-Final List'!$W:$W,'LC-Final List'!$Y:$Y,$A14,'LC-Final List'!$AE:$AE,"*Unpaid*",'LC-Final List'!$E:$E,B$2) -> 117792000 | C14: =SUMIFS('LC-Final List'!$W:$W,'LC-Final List'!$Y:$Y,$A14,'LC-Final List'!$AE:$AE,"*Unpaid*",'LC-Final List'!$E:$E,C$2) -> 3.5825918e+08 | D14: =SUMIFS('LC-Final List'!$W:$W,'LC-Final List'!$Y:$Y,$A14,'LC-Final List'!$AE:$AE,"*Unpaid*",'LC-Final List'!$E:$E,D$2) -> 0 | E14: =SUMIFS('LC-Final List'!$W:$W,'LC-Final List'!$Y:$Y,$A14,'LC-Final List'!$AE:$AE,"*Unpaid*") -> 4.7605118e+08
A15: =WORKDAY(TODAY(),12) -> 46196 | B15: =SUMIFS('LC-Final List'!$W:$W,'LC-Final List'!$Y:$Y,$A15,'LC-Final List'!$AE:$AE,"*Unpaid*",'LC-Final List'!$E:$E,B$2) -> 6344064 | C15: =SUMIFS('LC-Final List'!$W:$W,'LC-Final List'!$Y:$Y,$A15,'LC-Final List'!$AE:$AE,"*Unpaid*",'LC-Final List'!$E:$E,C$2) -> 0 | D15: =SUMIFS('LC-Final List'!$W:$W,'LC-Final List'!$Y:$Y,$A15,'LC-Final List'!$AE:$AE,"*Unpaid*",'LC-Final List'!$E:$E,D$2) -> 0 | E15: =SUMIFS('LC-Final List'!$W:$W,'LC-Final List'!$Y:$Y,$A15,'LC-Final List'!$AE:$AE,"*Unpaid*") -> 6344064
A16: =WORKDAY(TODAY(),13) -> 46197 | B16: =SUMIFS('LC-Final List'!$W:$W,'LC-Final List'!$Y:$Y,$A16,'LC-Final List'!$AE:$AE,"*Unpaid*",'LC-Final List'!$E:$E,B$2) -> 0 | C16: =SUMIFS('LC-Final List'!$W:$W,'LC-Final List'!$Y:$Y,$A16,'LC-Final List'!$AE:$AE,"*Unpaid*",'LC-Final List'!$E:$E,C$2) -> 0 | D16: =SUMIFS('LC-Final List'!$W:$W,'LC-Final List'!$Y:$Y,$A16,'LC-Final List'!$AE:$AE,"*Unpaid*",'LC-Final List'!$E:$E,D$2) -> 0 | E16: =SUMIFS('LC-Final List'!$W:$W,'LC-Final List'!$Y:$Y,$A16,'LC-Final List'!$AE:$AE,"*Unpaid*") -> 0
A17: =WORKDAY(TODAY(),14) -> 46198 | B17: =SUMIFS('LC-Final List'!$W:$W,'LC-Final List'!$Y:$Y,$A17,'LC-Final List'!$AE:$AE,"*Unpaid*",'LC-Final List'!$E:$E,B$2) -> 0 | C17: =SUMIFS('LC-Final List'!$W:$W,'LC-Final List'!$Y:$Y,$A17,'LC-Final List'!$AE:$AE,"*Unpaid*",'LC-Final List'!$E:$E,C$2) -> 0 | D17: =SUMIFS('LC-Final List'!$W:$W,'LC-Final List'!$Y:$Y,$A17,'LC-Final List'!$AE:$AE,"*Unpaid*",'LC-Final List'!$E:$E,D$2) -> 52310822 | E17: =SUMIFS('LC-Final List'!$W:$W,'LC-Final List'!$Y:$Y,$A17,'LC-Final List'!$AE:$AE,"*Unpaid*") -> 52310822
A18: =WORKDAY(TODAY(),15) -> 46199 | B18: =SUMIFS('LC-Final List'!$W:$W,'LC-Final List'!$Y:$Y,$A18,'LC-Final List'!$AE:$AE,"*Unpaid*",'LC-Final List'!$E:$E,B$2) -> 0 | C18: =SUMIFS('LC-Final List'!$W:$W,'LC-Final List'!$Y:$Y,$A18,'LC-Final List'!$AE:$AE,"*Unpaid*",'LC-Final List'!$E:$E,C$2) -> 0 | D18: =SUMIFS('LC-Final List'!$W:$W,'LC-Final List'!$Y:$Y,$A18,'LC-Final List'!$AE:$AE,"*Unpaid*",'LC-Final List'!$E:$E,D$2) -> 0 | E18: =SUMIFS('LC-Final List'!$W:$W,'LC-Final List'!$Y:$Y,$A18,'LC-Final List'!$AE:$AE,"*Unpaid*") -> 0
A19: =WORKDAY(TODAY(),16) -> 46202 | B19: =SUMIFS('LC-Final List'!$W:$W,'LC-Final List'!$Y:$Y,$A19,'LC-Final List'!$AE:$AE,"*Unpaid*",'LC-Final List'!$E:$E,B$2) -> 13197600 | C19: =SUMIFS('LC-Final List'!$W:$W,'LC-Final List'!$Y:$Y,$A19,'LC-Final List'!$AE:$AE,"*Unpaid*",'LC-Final List'!$E:$E,C$2) -> 0 | D19: =SUMIFS('LC-Final List'!$W:$W,'LC-Final List'!$Y:$Y,$A19,'LC-Final List'!$AE:$AE,"*Unpaid*",'LC-Final List'!$E:$E,D$2) -> 0 | E19: =SUMIFS('LC-Final List'!$W:$W,'LC-Final List'!$Y:$Y,$A19,'LC-Final List'!$AE:$AE,"*Unpaid*") -> 13197600
A20: =WORKDAY(TODAY(),17) -> 46203 | B20: =SUMIFS('LC-Final List'!$W:$W,'LC-Final List'!$Y:$Y,$A20,'LC-Final List'!$AE:$AE,"*Unpaid*",'LC-Final List'!$E:$E,B$2) -> 0 | C20: =SUMIFS('LC-Final List'!$W:$W,'LC-Final List'!$Y:$Y,$A20,'LC-Final List'!$AE:$AE,"*Unpaid*",'LC-Final List'!$E:$E,C$2) -> 0 | D20: =SUMIFS('LC-Final List'!$W:$W,'LC-Final List'!$Y:$Y,$A20,'LC-Final List'!$AE:$AE,"*Unpaid*",'LC-Final List'!$E:$E,D$2) -> 0 | E20: =SUMIFS('LC-Final List'!$W:$W,'LC-Final List'!$Y:$Y,$A20,'LC-Final List'!$AE:$AE,"*Unpaid*") -> 0
A21: =WORKDAY(TODAY(),18) -> 46204 | B21: =SUMIFS('LC-Final List'!$W:$W,'LC-Final List'!$Y:$Y,$A21,'LC-Final List'!$AE:$AE,"*Unpaid*",'LC-Final List'!$E:$E,B$2) -> 0 | C21: =SUMIFS('LC-Final List'!$W:$W,'LC-Final List'!$Y:$Y,$A21,'LC-Final List'!$AE:$AE,"*Unpaid*",'LC-Final List'!$E:$E,C$2) -> 0 | D21: =SUMIFS('LC-Final List'!$W:$W,'LC-Final List'!$Y:$Y,$A21,'LC-Final List'!$AE:$AE,"*Unpaid*",'LC-Final List'!$E:$E,D$2) -> 0 | E21: =SUMIFS('LC-Final List'!$W:$W,'LC-Final List'!$Y:$Y,$A21,'LC-Final List'!$AE:$AE,"*Unpaid*") -> 0
A22: =WORKDAY(TODAY(),19) -> 46205 | B22: =SUMIFS('LC-Final List'!$W:$W,'LC-Final List'!$Y:$Y,$A22,'LC-Final List'!$AE:$AE,"*Unpaid*",'LC-Final List'!$E:$E,B$2) -> 0 | C22: =SUMIFS('LC-Final List'!$W:$W,'LC-Final List'!$Y:$Y,$A22,'LC-Final List'!$AE:$AE,"*Unpaid*",'LC-Final List'!$E:$E,C$2) -> 0 | D22: =SUMIFS('LC-Final List'!$W:$W,'LC-Final List'!$Y:$Y,$A22,'LC-Final List'!$AE:$AE,"*Unpaid*",'LC-Final List'!$E:$E,D$2) -> 45771970 | E22: =SUMIFS('LC-Final List'!$W:$W,'LC-Final List'!$Y:$Y,$A22,'LC-Final List'!$AE:$AE,"*Unpaid*") -> 45771970
A23: =WORKDAY(TODAY(),20) -> 46206 | B23: =SUMIFS('LC-Final List'!$W:$W,'LC-Final List'!$Y:$Y,$A23,'LC-Final List'!$AE:$AE,"*Unpaid*",'LC-Final List'!$E:$E,B$2) -> 46944000 | C23: =SUMIFS('LC-Final List'!$W:$W,'LC-Final List'!$Y:$Y,$A23,'LC-Final List'!$AE:$AE,"*Unpaid*",'LC-Final List'!$E:$E,C$2) -> 0 | D23: =SUMIFS('LC-Final List'!$W:$W,'LC-Final List'!$Y:$Y,$A23,'LC-Final List'!$AE:$AE,"*Unpaid*",'LC-Final List'!$E:$E,D$2) -> 0 | E23: =SUMIFS('LC-Final List'!$W:$W,'LC-Final List'!$Y:$Y,$A23,'LC-Final List'!$AE:$AE,"*Unpaid*") -> 46944000
A24: =WORKDAY(TODAY(),21) -> 46209 | B24: =SUMIFS('LC-Final List'!$W:$W,'LC-Final List'!$Y:$Y,$A24,'LC-Final List'!$AE:$AE,"*Unpaid*",'LC-Final List'!$E:$E,B$2) -> 26155411 | C24: =SUMIFS('LC-Final List'!$W:$W,'LC-Final List'!$Y:$Y,$A24,'LC-Final List'!$AE:$AE,"*Unpaid*",'LC-Final List'!$E:$E,C$2) -> 0 | D24: =SUMIFS('LC-Final List'!$W:$W,'LC-Final List'!$Y:$Y,$A24,'LC-Final List'!$AE:$AE,"*Unpaid*",'LC-Final List'!$E:$E,D$2) -> 0 | E24: =SUMIFS('LC-Final List'!$W:$W,'LC-Final List'!$Y:$Y,$A24,'LC-Final List'!$AE:$AE,"*Unpaid*") -> 26155411
A25: =WORKDAY(TODAY(),22) -> 46210 | B25: =SUMIFS('LC-Final List'!$W:$W,'LC-Final List'!$Y:$Y,$A25,'LC-Final List'!$AE:$AE,"*Unpaid*",'LC-Final List'!$E:$E,B$2) -> 46944000 | C25: =SUMIFS('LC-Final List'!$W:$W,'LC-Final List'!$Y:$Y,$A25,'LC-Final List'!$AE:$AE,"*Unpaid*",'LC-Final List'!$E:$E,C$2) -> 0 | D25: =SUMIFS('LC-Final List'!$W:$W,'LC-Final List'!$Y:$Y,$A25,'LC-Final List'!$AE:$AE,"*Unpaid*",'LC-Final List'!$E:$E,D$2) -> 0 | E25: =SUMIFS('LC-Final List'!$W:$W,'LC-Final List'!$Y:$Y,$A25,'LC-Final List'!$AE:$AE,"*Unpaid*") -> 46944000
A26: =WORKDAY(TODAY(),23) -> 46211 | B26: =SUMIFS('LC-Final List'!$W:$W,'LC-Final List'!$Y:$Y,$A26,'LC-Final List'!$AE:$AE,"*Unpaid*",'LC-Final List'!$E:$E,B$2) -> 71927381 | C26: =SUMIFS('LC-Final List'!$W:$W,'LC-Final List'!$Y:$Y,$A26,'LC-Final List'!$AE:$AE,"*Unpaid*",'LC-Final List'!$E:$E,C$2) -> 0 | D26: =SUMIFS('LC-Final List'!$W:$W,'LC-Final List'!$Y:$Y,$A26,'LC-Final List'!$AE:$AE,"*Unpaid*",'LC-Final List'!$E:$E,D$2) -> 0 | E26: =SUMIFS('LC-Final List'!$W:$W,'LC-Final List'!$Y:$Y,$A26,'LC-Final List'!$AE:$AE,"*Unpaid*") -> 71927381
A27: =WORKDAY(TODAY(),24) -> 46212 | B27: =SUMIFS('LC-Final List'!$W:$W,'LC-Final List'!$Y:$Y,$A27,'LC-Final List'!$AE:$AE,"*Unpaid*",'LC-Final List'!$E:$E,B$2) -> 0 | C27: =SUMIFS('LC-Final List'!$W:$W,'LC-Final List'!$Y:$Y,$A27,'LC-Final List'!$AE:$AE,"*Unpaid*",'LC-Final List'!$E:$E,C$2) -> 0 | D27: =SUMIFS('LC-Final List'!$W:$W,'LC-Final List'!$Y:$Y,$A27,'LC-Final List'!$AE:$AE,"*Unpaid*",'LC-Final List'!$E:$E,D$2) -> 0 | E27: =SUMIFS('LC-Final List'!$W:$W,'LC-Final List'!$Y:$Y,$A27,'LC-Final List'!$AE:$AE,"*Unpaid*") -> 0
A28: =WORKDAY(TODAY(),25) -> 46213 | B28: =SUMIFS('LC-Final List'!$W:$W,'LC-Final List'!$Y:$Y,$A28,'LC-Final List'!$AE:$AE,"*Unpaid*",'LC-Final List'!$E:$E,B$2) -> 0 | C28: =SUMIFS('LC-Final List'!$W:$W,'LC-Final List'!$Y:$Y,$A28,'LC-Final List'!$AE:$AE,"*Unpaid*",'LC-Final List'!$E:$E,C$2) -> 0 | D28: =SUMIFS('LC-Final List'!$W:$W,'LC-Final List'!$Y:$Y,$A28,'LC-Final List'!$AE:$AE,"*Unpaid*",'LC-Final List'!$E:$E,D$2) -> 0 | E28: =SUMIFS('LC-Final List'!$W:$W,'LC-Final List'!$Y:$Y,$A28,'LC-Final List'!$AE:$AE,"*Unpaid*") -> 0
A29: =WORKDAY(TODAY(),26) -> 46216 | B29: =SUMIFS('LC-Final List'!$W:$W,'LC-Final List'!$Y:$Y,$A29,'LC-Final List'!$AE:$AE,"*Unpaid*",'LC-Final List'!$E:$E,B$2) -> 0 | C29: =SUMIFS('LC-Final List'!$W:$W,'LC-Final List'!$Y:$Y,$A29,'LC-Final List'!$AE:$AE,"*Unpaid*",'LC-Final List'!$E:$E,C$2) -> 5431296 | D29: =SUMIFS('LC-Final List'!$W:$W,'LC-Final List'!$Y:$Y,$A29,'LC-Final List'!$AE:$AE,"*Unpaid*",'LC-Final List'!$E:$E,D$2) -> 0 | E29: =SUMIFS('LC-Final List'!$W:$W,'LC-Final List'!$Y:$Y,$A29,'LC-Final List'!$AE:$AE,"*Unpaid*") -> 5431296
A30: =WORKDAY(TODAY(),27) -> 46217 | B30: =SUMIFS('LC-Final List'!$W:$W,'LC-Final List'!$Y:$Y,$A30,'LC-Final List'!$AE:$AE,"*Unpaid*",'LC-Final List'!$E:$E,B$2) -> 57673728 | C30: =SUMIFS('LC-Final List'!$W:$W,'LC-Final List'!$Y:$Y,$A30,'LC-Final List'!$AE:$AE,"*Unpaid*",'LC-Final List'!$E:$E,C$2) -> 0 | D30: =SUMIFS('LC-Final List'!$W:$W,'LC-Final List'!$Y:$Y,$A30,'LC-Final List'!$AE:$AE,"*Unpaid*",'LC-Final List'!$E:$E,D$2) -> 0 | E30: =SUMIFS('LC-Final List'!$W:$W,'LC-Final List'!$Y:$Y,$A30,'LC-Final List'!$AE:$AE,"*Unpaid*") -> 57673728
A31: =WORKDAY(TODAY(),28) -> 46218 | B31: =SUMIFS('LC-Final List'!$W:$W,'LC-Final List'!$Y:$Y,$A31,'LC-Final List'!$AE:$AE,"*Unpaid*",'LC-Final List'!$E:$E,B$2) -> 53705760 | C31: =SUMIFS('LC-Final List'!$W:$W,'LC-Final List'!$Y:$Y,$A31,'LC-Final List'!$AE:$AE,"*Unpaid*",'LC-Final List'!$E:$E,C$2) -> 0 | D31: =SUMIFS('LC-Final List'!$W:$W,'LC-Final List'!$Y:$Y,$A31,'LC-Final List'!$AE:$AE,"*Unpaid*",'LC-Final List'!$E:$E,D$2) -> 0 | E31: =SUMIFS('LC-Final List'!$W:$W,'LC-Final List'!$Y:$Y,$A31,'LC-Final List'!$AE:$AE,"*Unpaid*") -> 53705760
A32: =WORKDAY(TODAY(),29) -> 46219 | B32: =SUMIFS('LC-Final List'!$W:$W,'LC-Final List'!$Y:$Y,$A32,'LC-Final List'!$AE:$AE,"*Unpaid*",'LC-Final List'!$E:$E,B$2) -> 0 | C32: =SUMIFS('LC-Final List'!$W:$W,'LC-Final List'!$Y:$Y,$A32,'LC-Final List'!$AE:$AE,"*Unpaid*",'LC-Final List'!$E:$E,C$2) -> 0 | D32: =SUMIFS('LC-Final List'!$W:$W,'LC-Final List'!$Y:$Y,$A32,'LC-Final List'!$AE:$AE,"*Unpaid*",'LC-Final List'!$E:$E,D$2) -> 0 | E32: =SUMIFS('LC-Final List'!$W:$W,'LC-Final List'!$Y:$Y,$A32,'LC-Final List'!$AE:$AE,"*Unpaid*") -> 0
A33: =WORKDAY(TODAY(),30) -> 46220 | B33: =SUMIFS('LC-Final List'!$W:$W,'LC-Final List'!$Y:$Y,$A33,'LC-Final List'!$AE:$AE,"*Unpaid*",'LC-Final List'!$E:$E,B$2) -> 0 | C33: =SUMIFS('LC-Final List'!$W:$W,'LC-Final List'!$Y:$Y,$A33,'LC-Final List'!$AE:$AE,"*Unpaid*",'LC-Final List'!$E:$E,C$2) -> 0 | D33: =SUMIFS('LC-Final List'!$W:$W,'LC-Final List'!$Y:$Y,$A33,'LC-Final List'!$AE:$AE,"*Unpaid*",'LC-Final List'!$E:$E,D$2) -> 0 | E33: =SUMIFS('LC-Final List'!$W:$W,'LC-Final List'!$Y:$Y,$A33,'LC-Final List'!$AE:$AE,"*Unpaid*") -> 0
A34: =WORKDAY(TODAY(),31) -> 46223 | B34: =SUMIFS('LC-Final List'!$W:$W,'LC-Final List'!$Y:$Y,$A34,'LC-Final List'!$AE:$AE,"*Unpaid*",'LC-Final List'!$E:$E,B$2) -> 0 | C34: =SUMIFS('LC-Final List'!$W:$W,'LC-Final List'!$Y:$Y,$A34,'LC-Final List'!$AE:$AE,"*Unpaid*",'LC-Final List'!$E:$E,C$2) -> 0 | D34: =SUMIFS('LC-Final List'!$W:$W,'LC-Final List'!$Y:$Y,$A34,'LC-Final List'!$AE:$AE,"*Unpaid*",'LC-Final List'!$E:$E,D$2) -> 0 | E34: =SUMIFS('LC-Final List'!$W:$W,'LC-Final List'!$Y:$Y,$A34,'LC-Final List'!$AE:$AE,"*Unpaid*") -> 0
A36: TOTAL OUTSTANDING | E36: =SUM(E3:E22) -> 3.0841039e+09 | G36: TOTAL OUTSTANDING | H36: =SUM(H3:H35) -> 4417019976

Sheet C_Limit Available_Planning
A1: LC Limit Available
A3: SBLC Status | B3: (Multiple Items)
A5: Sum of LC Limit Available
B6: CANCELLED | D6: NO | F6: YES | I6: SOFT COPY | K6: Grand Total
A7: Row Labels | B7: IDBI | C7: SBI | D7: IDBI | E7: SBI | F7: IDBI | G7: SBI | H7: BOI | I7: IDBI | J7: SBI
A8: 46173 | B8: 6626521 | K8: 6626521
A9: 46176 | G9: 672489216 | K9: 672489216
A10: 46177 | G10: 3.0758289e+08 | K10: 3.0758289e+08
A11: 46178 | G11: 1.3027923e+08 | K11: 1.3027923e+08
A12: 46179 | F12: 8697848.7 | H12: 40095952 | K12: 48793801
A13: 46184 | G13: 4.8433801e+08 | H13: 72808013 | K13: 5.5714602e+08
A14: 46186 | G14: 2.4195297e+08 | K14: 2.4195297e+08
A15: 46187 | G15: 5.509516e+08 | H15: 169992000 | K15: 7.209436e+08
A16: 46190 | G16: 5.9444844e+08 | H16: 232502400 | K16: 8.2695084e+08
A17: 46191 | G17: 76898304 | K17: 76898304
A18: 46192 | C18: 3.3370871e+08 | G18: 1.304605e+08 | K18: 4.641692e+08
A19: 46194 | B19: 15587582 | K19: 15587582
A20: 46197 | B20: 825702.72 | F20: 3.5825918e+08 | G20: 182793600 | K20: 541878480
A21: 46198 | J21: 6344064 | K21: 6344064
A22: 46200 | H22: 52310822 | K22: 52310822
A23: 46204 | G23: 105580800 | K23: 105580800
A24: 46207 | H24: 45771970 | K24: 45771970
A25: 46212 | G25: 93888000 | K25: 93888000
A26: 46213 | J26: 98082794 | K26: 98082794
A27: 46216 | I27: 5431296 | K27: 5431296
A28: 46219 | E28: 57673728 | K28: 57673728
A29: 46220 | E29: 53705760 | K29: 53705760
A30: 46224 | I30: 49147085 | K30: 49147085
A31: 46235 | E31: 106310400 | K31: 106310400
A32: 46250 | D32: 22579200 | K32: 22579200
A33: 46255 | D33: 6420480 | K33: 6420480
A34: (blank) | C34: 0 | E34: 0 | G34: 0 | K34: 0
A35: Grand Total | B35: 23039806 | C35: 3.3370871e+08 | D35: 28999680 | E35: 217689888 | F35: 366957026 | G35: 3.5716636e+09 | H35: 6.1348116e+08 | I35: 54578381 | J35: 1.0442686e+08 | K35: 5.3145451e+09

Sheet LC-Summary
A1: Sr. No. | B1: Particular | C1: Amount | E1: Details | F1: Existing Limit | G1: TRANSFER FROM CC TO LC limit | H1: Interchangeability Limit to SBLC | I1: Total Current NFB limit | J1: Outstanding | K1: In Process | L1: LC request received and not process | N1: LC Limit Available | O1: BG Limit Available
E2: IDBI -LC | F2: =1500000000 -> 1500000000 | G2: =160000000+7000000-140000000 -> 27000000 | H2: 822500000 | I2: =F2+G2 -> 1527000000 | J2: =$C$5+H2 -> 1.2651629e+09 | N2: =I2-J2 -> 2.6183706e+08
A3: 2 | B3: LC Cancelled | C3: =SUMIF('LC-Final List'!$AD$2:$AD$222,B3,'LC-Final List'!$W$2:$W$222) -> 36772620 | E3: BOI -LC | F3: =1570000000 -> 1570000000 | G3: 0 | H3: 820000000 | I3: =F3+G3 -> 1570000000 | J3: =$C$6+H3 -> 1.3933852e+09 | K3: 0 | N3: =I3-J3-K3 -> 1.766148e+08
A4: 3 | B4: BOE Received and Paid | C4: =SUMIFS('LC-Final List'!$W:$W,'LC-Final List'!$AD:$AD,B4) -> 7.9891687e+09 | E4: SBI -LC | F4: 7840000000 | G4: 0 | H4: 1810000000 | I4: =F4-H4 -> 6030000000 | J4: =$C$8+5000000 -> 3.961815e+09 | K4: 45000000 | L4: ='LC BG in Process'!H10-'LC-Summary'!K2-'LC-Summary'!K3-'LC-Summary'!K4 -> 4.1646475e+08 | N4: =I4-J4-K4 -> 2.023185e+09
B5: IDBI | C5: =SUMIFS('LC-Final List'!$W:$W,'LC-Final List'!$AH:$AH,"Open",'LC-Final List'!$E:$E,'LC-Summary'!B5) -> 4.4266294e+08 | E5: SBI -CAPEX LC | J5: =$C$7 -> 1.3209023e+08
B6: BOI | C6: =SUMIFS('LC-Final List'!$W:$W,'LC-Final List'!$AH:$AH,"Open",'LC-Final List'!$E:$E,'LC-Summary'!B6) -> 5.733852e+08 | E6: SBI -LC 110% | J6: 0
A7: Capex | B7: 1 | C7: =SUMIFS('LC-Final List'!$M:$M,'LC-Final List'!$F:$F,B7,'LC-Final List'!$AH:$AH,"Open") -> 1.3209023e+08
A8: 0.1 | B8: SBI | C8: =SUMIFS('LC-Final List'!$M:$M,'LC-Final List'!$AH:$AH,"Open",'LC-Final List'!$E:$E,'LC-Summary'!B8,'LC-Final List'!$F:$F,A8) -> 3.956815e+09
B9: Total LC Outstanding | C9: =C8+C5+C6 -> 4.9728631e+09 | E9: SBI-BG 10% | F9: 4500000000 | H9: 0 | I9: =F9-H9 -> 4500000000 | J9: =SUMIF('Bank Guarantee'!$B$2:$B$32,'LC-Summary'!E9,'Bank Guarantee'!$F$2:$F$32) -> 1801696196 | N9: =I9-J9-K9 -> 2698303804
A10: 4 | B10: Part/Full BOE received & Unpaid | C10: =SUMIFS('LC-Final List'!$W:$W,'LC-Final List'!$AD:$AD,'LC-Summary'!B10,'LC-Final List'!$AE:$AE,"Unpaid") -> 3.3306531e+09 | E10: IDBI -BG | F10: 630000000 | H10: 0 | I10: =F10-H10 -> 630000000 | J10: =SUMIF('Bank Guarantee'!$B$2:$B$24,'LC-Summary'!E10,'Bank Guarantee'!$F$2:$F$24) -> 157812020 | K10: 0 | N10: =I10-J10-K10 -> 472187980
A11: 5 | B11: BOE not received | C11: =SUMIF('LC-Final List'!$AD$2:$AD$222,B11,'LC-Final List'!$W$2:$W$222) -> 1.1769724e+09 | E11: BOI-BG | F11: 770000000 | H11: 0 | I11: =F11-H11 -> 770000000 | J11: 0 | K11: 0 | N11: =I11-J11-K11 -> 770000000
A12: Bill Paid | B12: Part/Full BOE received & Unpaid | C12: =SUMIFS('LC-Final List'!$W:$W,'LC-Final List'!$AD:$AD,'LC-Summary'!B12,'LC-Final List'!$AE:$AE,"paid") -> 4.6523767e+08 | E12: SBI BG 100% | F12: 0 | H12: 0 | I12: =F12-H12 -> 0 | J12: =SUMIF('Bank Guarantee'!$B$2:$B$33,'LC-Summary'!E12,'Bank Guarantee'!$F$2:$F$33) -> 94783120 | K12: 0
E13: TOTAL | F13: =SUM(F2:F11) -> 16810000000 | H13: =SUM(H2:H11) -> 3452500000 | I13: =I2+I10+I4+I9+I3+I11 -> 15027000000 | J13: =J2+J10+J4+J9+J3+J11 -> 8.5798713e+09 | K13: =K4+K9+K3+K11+K2 -> 45000000 | N13: =SUM(N2:N12) -> 6.4021287e+09 | O13: =SUM(O2:O12) -> 0
A16: SBLC OUTSTANDING
A18: Month | C18: TOTAL SBLC AMT | D18: Paid till Date | E18: O/s as on date
A19: 46113 | C19: =SUMIF(SBLC!$S$2:$S$27,'LC-Summary'!A19,SBLC!$Q$2:$Q$27) -> 135016110 | D19: =SUMIFS(SBLC!Q:Q,SBLC!T:T,"Paid",SBLC!S:S,'LC-Summary'!A19) -> 135016110 | E19: =C19-D19 -> 0
A20: 46204 | C20: =SUMIF(SBLC!$S$2:$S$70,'LC-Summary'!A20,SBLC!$X$2:$X$70) -> 1.7340395e+09 | D20: =SUMIFS(SBLC!X:X,SBLC!T:T,"Paid",SBLC!S:S,'LC-Summary'!A20) -> 0 | E20: =C20-D20 -> 1.7340395e+09
A21: 46235 | C21: =SUMIF(SBLC!$S$2:$S$70,'LC-Summary'!A21,SBLC!$X$2:$X$70) -> 2.6826307e+08 | D21: =SUMIFS(SBLC!X:X,SBLC!T:T,"Paid",SBLC!S:S,'LC-Summary'!A21) -> 0 | E21: =C21-D21 -> 2.6826307e+08
A22: 46266 | C22: =SUMIF(SBLC!$S$2:$S$70,'LC-Summary'!A22,SBLC!$X$2:$X$70) -> 1.22739e+08 | D22: =SUMIFS(SBLC!X:X,SBLC!T:T,"Paid",SBLC!S:S,'LC-Summary'!A22) -> 0 | E22: =C22-D22 -> 1.22739e+08
A23: 46296 | C23: =SUMIF(SBLC!$S$2:$S$70,'LC-Summary'!A23,SBLC!$X$2:$X$70) -> 0 | D23: =SUMIFS(SBLC!X:X,SBLC!T:T,"Paid",SBLC!S:S,'LC-Summary'!A23) -> 0 | E23: =C23-D23 -> 0
A24: 46327 | C24: =SUMIF(SBLC!$S$2:$S$70,'LC-Summary'!A24,SBLC!$X$2:$X$70) -> 6.4625993e+08 | D24: =SUMIFS(SBLC!X:X,SBLC!T:T,"Paid",SBLC!S:S,'LC-Summary'!A24) -> 0 | E24: =C24-D24 -> 6.4625993e+08
A26: Total | C26: =SUM(C19:C25) -> 2.9063176e+09 | D26: =SUM(D19:D25) -> 135016110 | E26: =SUM(E19:E25) -> 2.7713015e+09

Sheet DAILY UPDATE SHEET
A1: 📊 SUMMARY – LC & BILL POSITION
A3: 1️⃣ Total LC Exposure and Available Limit Snapshot | G3: 1️⃣ (a) Margin Wise LC Bifurcation - Total LC Exposure
A5: Category | B5: SBI | C5: IDBI | D5: BOI | E5: Total | G5: Margin % | H5: SBI | I5: IDBI | J5: BOI | K5: Total
A6: A. BANK LIMITS (10% Margin) | G6: 0.1 | H6: =B14 -> 4.0026525e+09 | I6: =C14 -> 4.4266294e+08 | J6: =D14 -> 5.733852e+08 | K6: =SUM(H6:J6) -> 5.0187006e+09
A7: Existing Limit | B7: 7840000000 | C7: 1500000000 | D7: 1570000000 | E7: =B7+C7+D7 -> 10910000000 | G7: 1 | H7: =B26 -> 1.3209023e+08 | I7: =C26 -> 0 | J7: =D26 -> 0 | K7: =SUM(H7:J7) -> 1.3209023e+08
A8: Interchangability Limit | B8: 1810000000 | C8: =160000000+7000000-140000000 -> 27000000 | E8: =B8+C8+D8 -> 1837000000 | G8: 1.1 | H8: =B33 -> 0 | I8: =C33 -> 0 | J8: =D33 -> 0 | K8: =SUM(H8:J8) -> 0
A9: Total Current NFB limit (A) | B9: =B7-B8 -> 6030000000 | C9: =C7+C8 -> 1527000000 | D9: =D7+D8 -> 1570000000 | E9: =SUM(B9:D9) -> 9127000000 | G9: Total | H9: =SUM(H6:H8) -> 4.1347427e+09 | I9: =SUM(I6:I8) -> 4.4266294e+08 | J9: =SUM(J6:J8) -> 5.733852e+08 | K9: =SUM(K6:K8) -> 5.1507909e+09
A11: B. UTILIZATION
A12: LC Outstanding | B12: =SUMIFS('LC-Final List'!$M:$M,'LC-Final List'!$AH:$AH,"Open",'LC-Final List'!$E:$E,'DAILY UPDATE SHEET'!B$5,'LC-Final List'!$F:$F,"10%") -> 3.956815e+09 | C12: =SUMIFS('LC-Final List'!$W:$W,'LC-Final List'!$AH:$AH,"Open",'LC-Final List'!$E:$E,'DAILY UPDATE SHEET'!C$5,'LC-Final List'!$F:$F,"10%") -> 4.4266294e+08 | D12: =SUMIFS('LC-Final List'!$W:$W,'LC-Final List'!$AH:$AH,"Open",'LC-Final List'!$E:$E,'DAILY UPDATE SHEET'!D$5,'LC-Final List'!$F:$F,"10%") -> 5.733852e+08 | E12: =B12+C12+D12 -> 4.9728631e+09 | G12: 1️⃣ (b) 10% Margin - BOE Position (Open LCs)
A13: LC in Process | B13: =SUMIFS('LC BG in Process'!$H:$H,'LC BG in Process'!$K:$K,"DOC SUBMITTED TO BANK",'LC BG in Process'!$A:$A,"LC",'LC BG in Process'!$C:$C,"10%",'LC BG in Process'!$B:$B,'DAILY UPDATE SHEET'!B$5) -> 45837500 | C13: =SUMIFS('LC BG in Process'!$H:$H,'LC BG in Process'!$K:$K,"DOC SUBMITTED TO BANK",'LC BG in Process'!$A:$A,"LC",'LC BG in Process'!$C:$C,"10%",'LC BG in Process'!$B:$B,'DAILY UPDATE SHEET'!C$5) -> 0 | D13: =SUMIFS('LC BG in Process'!$H:$H,'LC BG in Process'!$K:$K,"DOC SUBMITTED TO BANK",'LC BG in Process'!$A:$A,"LC",'LC BG in Process'!$C:$C,"10%",'LC BG in Process'!$B:$B,'DAILY UPDATE SHEET'!D$5) -> 0 | E13: =B13+C13+D13 -> 45837500
A14: Total LC Exposure (B) | B14: =SUM(B12:B13) -> 4.0026525e+09 | C14: =SUM(C12:C13) -> 4.4266294e+08 | D14: =SUM(D12:D13) -> 5.733852e+08 | E14: =SUM(E12:E13) -> 5.0187006e+09 | G14: Bill Status | H14: =H5 -> SBI | I14: =I5 -> IDBI | J14: =J5 -> BOI | K14: Total
G15: BOE Received and Paid | H15: =SUMIFS('LC-Final List'!$W:$W,'LC-Final List'!$AH:$AH,"Open",'LC-Final List'!$AF:$AF,"Received",'LC-Final List'!$AE:$AE,"Paid",'LC-Final List'!$F:$F,"10%",'LC-Final List'!$E:$E,$H$14) -> 4.6523767e+08 | I15: =SUMIFS('LC-Final List'!$W:$W,'LC-Final List'!$AH:$AH,"Open",'LC-Final List'!$AF:$AF,"Received",'LC-Final List'!$AE:$AE,"Paid",'LC-Final List'!$F:$F,"10%",'LC-Final List'!$E:$E,$I$14) -> 0 | J15: =SUMIFS('LC-Final List'!$W:$W,'LC-Final List'!$AH:$AH,"Open",'LC-Final List'!$AF:$AF,"Received",'LC-Final List'!$AE:$AE,"Paid",'LC-Final List'!$F:$F,"10%",'LC-Final List'!$E:$E,$J$14) -> 0 | K15: =SUM(H15:J15) -> 4.6523767e+08
A16: C. SBLC UTILIZATION | G16: BOE Received and Unpaid | H16: =SUMIFS('LC-Final List'!$W:$W,'LC-Final List'!$AH:$AH,"Open",'LC-Final List'!$AF:$AF,"Received",'LC-Final List'!$AE:$AE,"Unpaid",'LC-Final List'!$F:$F,"10%",'LC-Final List'!$E:$E,$H$14) -> 2.3444303e+09 | I16: =SUMIFS('LC-Final List'!$W:$W,'LC-Final List'!$AH:$AH,"Open",'LC-Final List'!$AF:$AF,"Received",'LC-Final List'!$AE:$AE,"Unpaid",'LC-Final List'!$F:$F,"10%",'LC-Final List'!$E:$E,$I$14) -> 4.1283756e+08 | J16: =SUMIFS('LC-Final List'!$W:$W,'LC-Final List'!$AH:$AH,"Open",'LC-Final List'!$AF:$AF,"Received",'LC-Final List'!$AE:$AE,"Unpaid",'LC-Final List'!$F:$F,"10%",'LC-Final List'!$E:$E,$J$14) -> 5.733852e+08 | K16: =SUM(H16:J16) -> 3.3306531e+09
A17: SBLC Outstanding | B17: =SUMIFS(SBLC!$X:$X,SBLC!$T:$T,"Unpaid",SBLC!$B:$B,'DAILY UPDATE SHEET'!B$5) -> 1.1375264e+09 | C17: =SUMIFS(SBLC!$X:$X,SBLC!$T:$T,"Unpaid",SBLC!$B:$B,'DAILY UPDATE SHEET'!C$5) -> 8.2202324e+08 | D17: =SUMIFS(SBLC!$X:$X,SBLC!$T:$T,"Unpaid",SBLC!$B:$B,'DAILY UPDATE SHEET'!D$5) -> 8.205892e+08 | E17: =SUM(B17:D17) -> 2.7801389e+09 | G17: BOE Not Received | H17: =SUMIFS('LC-Final List'!$W:$W,'LC-Final List'!$AH:$AH,"Open",'LC-Final List'!$AF:$AF,"Not Received",'LC-Final List'!$AE:$AE,"Unpaid",'LC-Final List'!$F:$F,"10%",'LC-Final List'!$E:$E,$H$14) -> 1.0573672e+09 | I17: =SUMIFS('LC-Final List'!$W:$W,'LC-Final List'!$AH:$AH,"Open",'LC-Final List'!$AF:$AF,"Not Received",'LC-Final List'!$AE:$AE,"Unpaid",'LC-Final List'!$F:$F,"10%",'LC-Final List'!$E:$E,$I$14) -> 28999680 | J17: =SUMIFS('LC-Final List'!$W:$W,'LC-Final List'!$AH:$AH,"Open",'LC-Final List'!$AF:$AF,"Not Received",'LC-Final List'!$AE:$AE,"Unpaid",'LC-Final List'!$F:$F,"10%",'LC-Final List'!$E:$E,$J$14) -> 0 | K17: =SUM(H17:J17) -> 1.0863669e+09
A18: Total SBLC Exposure (C) | B18: =SUM(B16:B17) -> 1.1375264e+09 | C18: =SUM(C16:C17) -> 8.2202324e+08 | D18: =SUM(D16:D17) -> 8.205892e+08 | E18: =SUM(E16:E17) -> 2.7801389e+09 | G18: Cancelled | H18: =SUMIFS('LC-Final List'!$W:$W,'LC-Final List'!$AH:$AH,"Open",'LC-Final List'!$AF:$AF,"Cancelled",'LC-Final List'!$F:$F,"10%",'LC-Final List'!$E:$E,$H$14) -> 89779774 | I18: =SUMIFS('LC-Final List'!$W:$W,'LC-Final List'!$AH:$AH,"Open",'LC-Final List'!$AF:$AF,"Cancelled",'LC-Final List'!$F:$F,"10%",'LC-Final List'!$E:$E,$I$14) -> 825702.72 | J18: =SUMIFS('LC-Final List'!$W:$W,'LC-Final List'!$AH:$AH,"Open",'LC-Final List'!$AF:$AF,"Cancelled",'LC-Final List'!$F:$F,"10%",'LC-Final List'!$E:$E,$J$14) -> 0 | K18: =SUM(H18:J18) -> 90605477
G19: Total | H19: =SUM(H15:H18) -> 3.956815e+09 | I19: =SUM(I15:I18) -> 4.4266294e+08 | J19: =SUM(J15:J18) -> 5.733852e+08 | K19: =SUM(K15:K18) -> 4.9728631e+09
A20: C. HEADROOM
A21: Available Balance (D) = (A - B-C) | B21: =B9-B14 -> 2.0273475e+09 | C21: =C9-C14-C18 -> 2.6231382e+08 | D21: =D9-D14-D18 -> 1.760256e+08 | E21: =B21+C21+D21 -> 2.4656869e+09 | G21: Reconcilation | H21: =H19-B12 -> -2.3039999 | I21: =I19-C12 -> 0 | J21: =J19-D12 -> 0 | K21: =K19-E12 -> -2.3039999
A22: AVAILABLE SBLC LIMIT IN SBI | B22: =B8-B18 -> 6.7247356e+08 | E22: =B22+C22+D22 -> 6.7247356e+08
A23: LC Limit Utilization (%) | B23: =B14/B9 -> 0.6637898 | C23: =(C14+C18)/C9 -> 0.82821623 | D23: =(D14+D18)/D9 -> 0.88788178
A24: SBLC Limit Utilization | B24: =B17/B8 -> 0.62846765 | G24: 1️⃣ ( C ) Outstanding Payables: Currency Exposure & Hedge Status
A26: Total 100% Margin LC Exposure | B26: =SUM(B27:B28) -> 1.3209023e+08 | C26: =SUM(C27:C28) -> 0 | D26: =SUM(D27:D28) -> 0 | E26: =SUM(B26:D26) -> 1.3209023e+08 | G26: Currency Exposure (FX Risk) | H26: TOTAL Unpaid Bill | I26: HEDGED | J26: UNHEDGED
A27: 100% LC Outstanding | B27: =SUMIFS('LC-Final List'!$M:$M,'LC-Final List'!$AH:$AH,"Open",'LC-Final List'!$E:$E,'DAILY UPDATE SHEET'!B$5,'LC-Final List'!$F:$F,"100%") -> 1.3209023e+08 | C27: =SUMIFS('LC-Final List'!$M:$M,'LC-Final List'!$AH:$AH,"Open",'LC-Final List'!$E:$E,'DAILY UPDATE SHEET'!C$5,'LC-Final List'!$F:$F,"100%") -> 0 | D27: =SUMIFS('LC-Final List'!$M:$M,'LC-Final List'!$AH:$AH,"Open",'LC-Final List'!$E:$E,'DAILY UPDATE SHEET'!D$5,'LC-Final List'!$F:$F,"100%") -> 0 | E27: =SUM(B27:D27) -> 1.3209023e+08 | G27: USD- RAW MATERIAL | H27: =SUMIFS('LC-Final List'!$U:$U,'LC-Final List'!$AH:$AH,"Open",'LC-Final List'!$AE:$AE,"Unpaid",'LC-Final List'!$F:$F,"10%",'LC-Final List'!$H:$H,"USD") -> 46010625 | J27: =H27-I27 -> 46010625
A28: 100% in Process | B28: =SUMIFS('LC BG in Process'!$H:$H,'LC BG in Process'!$K:$K,"DOC SUBMITTED TO BANK",'LC BG in Process'!$A:$A,"LC",'LC BG in Process'!$C:$C,"100%",'LC BG in Process'!$B:$B,'DAILY UPDATE SHEET'!B$5) -> 0 | C28: =SUMIFS('LC BG in Process'!$H:$H,'LC BG in Process'!$K:$K,"DOC SUBMITTED TO BANK",'LC BG in Process'!$A:$A,"LC",'LC BG in Process'!$C:$C,"100%",'LC BG in Process'!$B:$B,'DAILY UPDATE SHEET'!C$5) -> 0 | D28: =SUMIFS('LC BG in Process'!$H:$H,'LC BG in Process'!$K:$K,"DOC SUBMITTED TO BANK",'LC BG in Process'!$A:$A,"LC",'LC BG in Process'!$C:$C,"100%",'LC BG in Process'!$B:$B,'DAILY UPDATE SHEET'!D$5) -> 0 | E28: =SUM(B28:D28) -> 0 | G28: USD-CAPEX | H28: =SUMIFS('LC-Final List'!$U:$U,'LC-Final List'!$AH:$AH,"Open",'LC-Final List'!$AE:$AE,"Unpaid",'LC-Final List'!$F:$F,"100%",'LC-Final List'!$H:$H,"USD") -> 1345674 | I28: 1345674 | J28: =H28-I28 -> 0
G29: EUR-CAPEX | H29: =SUMIFS('LC-Final List'!$U:$U,'LC-Final List'!$AH:$AH,"Open",'LC-Final List'!$AE:$AE,"Unpaid",'LC-Final List'!$F:$F,"100%",'LC-Final List'!$H:$H,"EUR") -> 30000 | I29: 30000 | J29: =H29-I29 -> 0
A30: Total 110% Margin LC Exposure | B30: =SUM(B31:B32) -> 0 | C30: =SUM(C31:C32) -> 0 | D30: =SUM(D31:D32) -> 0 | E30: =SUM(B30:D30) -> 0 | G30: Total | H30: 80416960 | I30: 1375674 | J30: 79041286
A31: 110% LC Outstanding | B31: =SUMIFS('LC-Final List'!$M:$M,'LC-Final List'!$AH:$AH,"Open",'LC-Final List'!$E:$E,'DAILY UPDATE SHEET'!B$5,'LC-Final List'!$F:$F,"110%") -> 0 | C31: =SUMIFS('LC-Final List'!$M:$M,'LC-Final List'!$AH:$AH,"Open",'LC-Final List'!$E:$E,'DAILY UPDATE SHEET'!C$5,'LC-Final List'!$F:$F,"110%") -> 0 | D31: =SUMIFS('LC-Final List'!$M:$M,'LC-Final List'!$AH:$AH,"Open",'LC-Final List'!$E:$E,'DAILY UPDATE SHEET'!D$5,'LC-Final List'!$F:$F,"110%") -> 0 | E31: =SUM(B31:D31) -> 0
A32: 110% in Process | B32: =SUMIFS('LC BG in Process'!$H:$H,'LC BG in Process'!$K:$K,"DOC SUBMITTED TO BANK",'LC BG in Process'!$A:$A,"LC",'LC BG in Process'!$C:$C,"110%",'LC BG in Process'!$B:$B,'DAILY UPDATE SHEET'!B$5) -> 0 | C32: =SUMIFS('LC BG in Process'!$H:$H,'LC BG in Process'!$K:$K,"DOC SUBMITTED TO BANK",'LC BG in Process'!$A:$A,"LC",'LC BG in Process'!$C:$C,"110%",'LC BG in Process'!$B:$B,'DAILY UPDATE SHEET'!C$5) -> 0 | D32: =SUMIFS('LC BG in Process'!$H:$H,'LC BG in Process'!$K:$K,"DOC SUBMITTED TO BANK",'LC BG in Process'!$A:$A,"LC",'LC BG in Process'!$C:$C,"110%",'LC BG in Process'!$B:$B,'DAILY UPDATE SHEET'!D$5) -> 0 | E32: =SUM(B32:D32) -> 0
A34: Daily Payment Schedule
A36: DAILY PAYMENT SCHEDULE | B36: SBI | D36: IDBI | F36: BOI | H36: PAYABLE AMOUNT (INR)
B37: LC | C37: SBLC | D37: LC | E37: SBLC | F37: LC | G37: SBLC
A38: =TODAY() -> 46178 | B38: =SUMIFS('LC-Final List'!$W:$W,'LC-Final List'!$AE:$AE,"Unpaid",'LC-Final List'!$Y:$Y,'DAILY UPDATE SHEET'!$A38,'LC-Final List'!$E:$E,'DAILY UPDATE SHEET'!B$36,'LC-Final List'!$F:$F,"10%") -> 103736160 | C38: =SUMIFS(SBLC!$X:$X,SBLC!$T:$T,"Unpaid",SBLC!$R:$R,'DAILY UPDATE SHEET'!$A38,SBLC!$B:$B,$B$36,SBLC!$H:$H,"10%") -> 0 | D38: =SUMIFS('LC-Final List'!$W:$W,'LC-Final List'!$AE:$AE,"Unpaid",'LC-Final List'!$Y:$Y,'DAILY UPDATE SHEET'!$A38,'LC-Final List'!$E:$E,'DAILY UPDATE SHEET'!D$36,'LC-Final List'!$F:$F,"10%") -> 0 | E38: =SUMIFS(SBLC!$X:$X,SBLC!$T:$T,"Unpaid",SBLC!$R:$R,'DAILY UPDATE SHEET'!$A38,SBLC!$B:$B,$D$36,SBLC!$H:$H,"10%") -> 0 | F38: =SUMIFS('LC-Final List'!$W:$W,'LC-Final List'!$AE:$AE,"Unpaid",'LC-Final List'!$Y:$Y,'DAILY UPDATE SHEET'!$A38,'LC-Final List'!$E:$E,'DAILY UPDATE SHEET'!F$36,'LC-Final List'!$F:$F,"10%") -> 0 | G38: =SUMIFS(SBLC!$X:$X,SBLC!$T:$T,"Unpaid",SBLC!$R:$R,'DAILY UPDATE SHEET'!$A38,SBLC!$B:$B,$F$36,SBLC!$H:$H,"10%") -> 0 | H38: =SUM(B38:G38) -> 103736160
A39: =A38+1 -> 46179 | B39: =SUMIFS('LC-Final List'!$W:$W,'LC-Final List'!$AE:$AE,"Unpaid",'LC-Final List'!$Y:$Y,'DAILY UPDATE SHEET'!$A39,'LC-Final List'!$E:$E,'DAILY UPDATE SHEET'!B$36,'LC-Final List'!$F:$F,"10%") -> 0 | C39: =SUMIFS(SBLC!$X:$X,SBLC!$T:$T,"Unpaid",SBLC!$R:$R,'DAILY UPDATE SHEET'!$A39,SBLC!$B:$B,$B$36,SBLC!$H:$H,"10%") -> 0 | D39: =SUMIFS('LC-Final List'!$W:$W,'LC-Final List'!$AE:$AE,"Unpaid",'LC-Final List'!$Y:$Y,'DAILY UPDATE SHEET'!$A39,'LC-Final List'!$E:$E,'DAILY UPDATE SHEET'!D$36,'LC-Final List'!$F:$F,"10%") -> 0 | E39: =SUMIFS(SBLC!$X:$X,SBLC!$T:$T,"Unpaid",SBLC!$R:$R,'DAILY UPDATE SHEET'!$A39,SBLC!$B:$B,$D$36,SBLC!$H:$H,"10%") -> 0 | F39: =SUMIFS('LC-Final List'!$W:$W,'LC-Final List'!$AE:$AE,"Unpaid",'LC-Final List'!$Y:$Y,'DAILY UPDATE SHEET'!$A39,'LC-Final List'!$E:$E,'DAILY UPDATE SHEET'!F$36,'LC-Final List'!$F:$F,"10%") -> 0 | G39: =SUMIFS(SBLC!$X:$X,SBLC!$T:$T,"Unpaid",SBLC!$R:$R,'DAILY UPDATE SHEET'!$A39,SBLC!$B:$B,$F$36,SBLC!$H:$H,"10%") -> 0 | H39: =SUM(B39:G39) -> 0
A40: =A39+1 -> 46180 | B40: =SUMIFS('LC-Final List'!$W:$W,'LC-Final List'!$AE:$AE,"Unpaid",'LC-Final List'!$Y:$Y,'DAILY UPDATE SHEET'!$A40,'LC-Final List'!$E:$E,'DAILY UPDATE SHEET'!B$36,'LC-Final List'!$F:$F,"10%") -> 0 | C40: =SUMIFS(SBLC!$X:$X,SBLC!$T:$T,"Unpaid",SBLC!$R:$R,'DAILY UPDATE SHEET'!$A40,SBLC!$B:$B,$B$36,SBLC!$H:$H,"10%") -> 0 | D40: =SUMIFS('LC-Final List'!$W:$W,'LC-Final List'!$AE:$AE,"Unpaid",'LC-Final List'!$Y:$Y,'DAILY UPDATE SHEET'!$A40,'LC-Final List'!$E:$E,'DAILY UPDATE SHEET'!D$36,'LC-Final List'!$F:$F,"10%") -> 0 | E40: =SUMIFS(SBLC!$X:$X,SBLC!$T:$T,"Unpaid",SBLC!$R:$R,'DAILY UPDATE SHEET'!$A40,SBLC!$B:$B,$D$36,SBLC!$H:$H,"10%") -> 0 | F40: =SUMIFS('LC-Final List'!$W:$W,'LC-Final List'!$AE:$AE,"Unpaid",'LC-Final List'!$Y:$Y,'DAILY UPDATE SHEET'!$A40,'LC-Final List'!$E:$E,'DAILY UPDATE SHEET'!F$36,'LC-Final List'!$F:$F,"10%") -> 0 | G40: =SUMIFS(SBLC!$X:$X,SBLC!$T:$T,"Unpaid",SBLC!$R:$R,'DAILY UPDATE SHEET'!$A40,SBLC!$B:$B,$F$36,SBLC!$H:$H,"10%") -> 0 | H40: =SUM(B40:G40) -> 0
A41: =A40+1 -> 46181 | B41: =SUMIFS('LC-Final List'!$W:$W,'LC-Final List'!$AE:$AE,"Unpaid",'LC-Final List'!$Y:$Y,'DAILY UPDATE SHEET'!$A41,'LC-Final List'!$E:$E,'DAILY UPDATE SHEET'!B$36,'LC-Final List'!$F:$F,"10%") -> 1.1980314e+08 | C41: =SUMIFS(SBLC!$X:$X,SBLC!$T:$T,"Unpaid",SBLC!$R:$R,'DAILY UPDATE SHEET'!$A41,SBLC!$B:$B,$B$36,SBLC!$H:$H,"10%") -> 0 | D41: =SUMIFS('LC-Final List'!$W:$W,'LC-Final List'!$AE:$AE,"Unpaid",'LC-Final List'!$Y:$Y,'DAILY UPDATE SHEET'!$A41,'LC-Final List'!$E:$E,'DAILY UPDATE SHEET'!D$36,'LC-Final List'!$F:$F,"10%") -> 0 | E41: =SUMIFS(SBLC!$X:$X,SBLC!$T:$T,"Unpaid",SBLC!$R:$R,'DAILY UPDATE SHEET'!$A41,SBLC!$B:$B,$D$36,SBLC!$H:$H,"10%") -> 0 | F41: =SUMIFS('LC-Final List'!$W:$W,'LC-Final List'!$AE:$AE,"Unpaid",'LC-Final List'!$Y:$Y,'DAILY UPDATE SHEET'!$A41,'LC-Final List'!$E:$E,'DAILY UPDATE SHEET'!F$36,'LC-Final List'!$F:$F,"10%") -> 0 | G41: =SUMIFS(SBLC!$X:$X,SBLC!$T:$T,"Unpaid",SBLC!$R:$R,'DAILY UPDATE SHEET'!$A41,SBLC!$B:$B,$F$36,SBLC!$H:$H,"10%") -> 0 | H41: =SUM(B41:G41) -> 1.1980314e+08
A42: =A41+1 -> 46182 | B42: =SUMIFS('LC-Final List'!$W:$W,'LC-Final List'!$AE:$AE,"Unpaid",'LC-Final List'!$Y:$Y,'DAILY UPDATE SHEET'!$A42,'LC-Final List'!$E:$E,'DAILY UPDATE SHEET'!B$36,'LC-Final List'!$F:$F,"10%") -> 4.5797035e+08 | C42: =SUMIFS(SBLC!$X:$X,SBLC!$T:$T,"Unpaid",SBLC!$R:$R,'DAILY UPDATE SHEET'!$A42,SBLC!$B:$B,$B$36,SBLC!$H:$H,"10%") -> 0 | D42: =SUMIFS('LC-Final List'!$W:$W,'LC-Final List'!$AE:$AE,"Unpaid",'LC-Final List'!$Y:$Y,'DAILY UPDATE SHEET'!$A42,'LC-Final List'!$E:$E,'DAILY UPDATE SHEET'!D$36,'LC-Final List'!$F:$F,"10%") -> 0 | E42: =SUMIFS(SBLC!$X:$X,SBLC!$T:$T,"Unpaid",SBLC!$R:$R,'DAILY UPDATE SHEET'!$A42,SBLC!$B:$B,$D$36,SBLC!$H:$H,"10%") -> 0 | F42: =SUMIFS('LC-Final List'!$W:$W,'LC-Final List'!$AE:$AE,"Unpaid",'LC-Final List'!$Y:$Y,'DAILY UPDATE SHEET'!$A42,'LC-Final List'!$E:$E,'DAILY UPDATE SHEET'!F$36,'LC-Final List'!$F:$F,"10%") -> 72808013 | G42: =SUMIFS(SBLC!$X:$X,SBLC!$T:$T,"Unpaid",SBLC!$R:$R,'DAILY UPDATE SHEET'!$A42,SBLC!$B:$B,$F$36,SBLC!$H:$H,"10%") -> 0 | H42: =SUM(B42:G42) -> 5.3077836e+08
A43: =A42+1 -> 46183 | B43: =SUMIFS('LC-Final List'!$W:$W,'LC-Final List'!$AE:$AE,"Unpaid",'LC-Final List'!$Y:$Y,'DAILY UPDATE SHEET'!$A43,'LC-Final List'!$E:$E,'DAILY UPDATE SHEET'!B$36,'LC-Final List'!$F:$F,"10%") -> 0 | C43: =SUMIFS(SBLC!$X:$X,SBLC!$T:$T,"Unpaid",SBLC!$R:$R,'DAILY UPDATE SHEET'!$A43,SBLC!$B:$B,$B$36,SBLC!$H:$H,"10%") -> 0 | D43: =SUMIFS('LC-Final List'!$W:$W,'LC-Final List'!$AE:$AE,"Unpaid",'LC-Final List'!$Y:$Y,'DAILY UPDATE SHEET'!$A43,'LC-Final List'!$E:$E,'DAILY UPDATE SHEET'!D$36,'LC-Final List'!$F:$F,"10%") -> 0 | E43: =SUMIFS(SBLC!$X:$X,SBLC!$T:$T,"Unpaid",SBLC!$R:$R,'DAILY UPDATE SHEET'!$A43,SBLC!$B:$B,$D$36,SBLC!$H:$H,"10%") -> 0 | F43: =SUMIFS('LC-Final List'!$W:$W,'LC-Final List'!$AE:$AE,"Unpaid",'LC-Final List'!$Y:$Y,'DAILY UPDATE SHEET'!$A43,'LC-Final List'!$E:$E,'DAILY UPDATE SHEET'!F$36,'LC-Final List'!$F:$F,"10%") -> 0 | G43: =SUMIFS(SBLC!$X:$X,SBLC!$T:$T,"Unpaid",SBLC!$R:$R,'DAILY UPDATE SHEET'!$A43,SBLC!$B:$B,$F$36,SBLC!$H:$H,"10%") -> 0 | H43: =SUM(B43:G43) -> 0
A44: =A43+1 -> 46184 | B44: =SUMIFS('LC-Final List'!$W:$W,'LC-Final List'!$AE:$AE,"Unpaid",'LC-Final List'!$Y:$Y,'DAILY UPDATE SHEET'!$A44,'LC-Final List'!$E:$E,'DAILY UPDATE SHEET'!B$36,'LC-Final List'!$F:$F,"10%") -> 2.4195292e+08 | C44: =SUMIFS(SBLC!$X:$X,SBLC!$T:$T,"Unpaid",SBLC!$R:$R,'DAILY UPDATE SHEET'!$A44,SBLC!$B:$B,$B$36,SBLC!$H:$H,"10%") -> 0 | D44: =SUMIFS('LC-Final List'!$W:$W,'LC-Final List'!$AE:$AE,"Unpaid",'LC-Final List'!$Y:$Y,'DAILY UPDATE SHEET'!$A44,'LC-Final List'!$E:$E,'DAILY UPDATE SHEET'!D$36,'LC-Final List'!$F:$F,"10%") -> 0 | E44: =SUMIFS(SBLC!$X:$X,SBLC!$T:$T,"Unpaid",SBLC!$R:$R,'DAILY UPDATE SHEET'!$A44,SBLC!$B:$B,$D$36,SBLC!$H:$H,"10%") -> 0 | F44: =SUMIFS('LC-Final List'!$W:$W,'LC-Final List'!$AE:$AE,"Unpaid",'LC-Final List'!$Y:$Y,'DAILY UPDATE SHEET'!$A44,'LC-Final List'!$E:$E,'DAILY UPDATE SHEET'!F$36,'LC-Final List'!$F:$F,"10%") -> 0 | G44: =SUMIFS(SBLC!$X:$X,SBLC!$T:$T,"Unpaid",SBLC!$R:$R,'DAILY UPDATE SHEET'!$A44,SBLC!$B:$B,$F$36,SBLC!$H:$H,"10%") -> 0 | H44: =SUM(B44:G44) -> 2.4195292e+08
A45: =A44+1 -> 46185 | B45: =SUMIFS('LC-Final List'!$W:$W,'LC-Final List'!$AE:$AE,"Unpaid",'LC-Final List'!$Y:$Y,'DAILY UPDATE SHEET'!$A45,'LC-Final List'!$E:$E,'DAILY UPDATE SHEET'!B$36,'LC-Final List'!$F:$F,"10%") -> 3.7510745e+08 | C45: =SUMIFS(SBLC!$X:$X,SBLC!$T:$T,"Unpaid",SBLC!$R:$R,'DAILY UPDATE SHEET'!$A45,SBLC!$B:$B,$B$36,SBLC!$H:$H,"10%") -> 0 | D45: =SUMIFS('LC-Final List'!$W:$W,'LC-Final List'!$AE:$AE,"Unpaid",'LC-Final List'!$Y:$Y,'DAILY UPDATE SHEET'!$A45,'LC-Final List'!$E:$E,'DAILY UPDATE SHEET'!D$36,'LC-Final List'!$F:$F,"10%") -> 0 | E45: =SUMIFS(SBLC!$X:$X,SBLC!$T:$T,"Unpaid",SBLC!$R:$R,'DAILY UPDATE SHEET'!$A45,SBLC!$B:$B,$D$36,SBLC!$H:$H,"10%") -> 0 | F45: =SUMIFS('LC-Final List'!$W:$W,'LC-Final List'!$AE:$AE,"Unpaid",'LC-Final List'!$Y:$Y,'DAILY UPDATE SHEET'!$A45,'LC-Final List'!$E:$E,'DAILY UPDATE SHEET'!F$36,'LC-Final List'!$F:$F,"10%") -> 169992000 | G45: =SUMIFS(SBLC!$X:$X,SBLC!$T:$T,"Unpaid",SBLC!$R:$R,'DAILY UPDATE SHEET'!$A45,SBLC!$B:$B,$F$36,SBLC!$H:$H,"10%") -> 0 | H45: =SUM(B45:G45) -> 5.4509945e+08
A46: =A45+1 -> 46186 | B46: =SUMIFS('LC-Final List'!$W:$W,'LC-Final List'!$AE:$AE,"Unpaid",'LC-Final List'!$Y:$Y,'DAILY UPDATE SHEET'!$A46,'LC-Final List'!$E:$E,'DAILY UPDATE SHEET'!B$36,'LC-Final List'!$F:$F,"10%") -> 0 | C46: =SUMIFS(SBLC!$X:$X,SBLC!$T:$T,"Unpaid",SBLC!$R:$R,'DAILY UPDATE SHEET'!$A46,SBLC!$B:$B,$B$36,SBLC!$H:$H,"10%") -> 0 | D46: =SUMIFS('LC-Final List'!$W:$W,'LC-Final List'!$AE:$AE,"Unpaid",'LC-Final List'!$Y:$Y,'DAILY UPDATE SHEET'!$A46,'LC-Final List'!$E:$E,'DAILY UPDATE SHEET'!D$36,'LC-Final List'!$F:$F,"10%") -> 0 | E46: =SUMIFS(SBLC!$X:$X,SBLC!$T:$T,"Unpaid",SBLC!$R:$R,'DAILY UPDATE SHEET'!$A46,SBLC!$B:$B,$D$36,SBLC!$H:$H,"10%") -> 0 | F46: =SUMIFS('LC-Final List'!$W:$W,'LC-Final List'!$AE:$AE,"Unpaid",'LC-Final List'!$Y:$Y,'DAILY UPDATE SHEET'!$A46,'LC-Final List'!$E:$E,'DAILY UPDATE SHEET'!F$36,'LC-Final List'!$F:$F,"10%") -> 0 | G46: =SUMIFS(SBLC!$X:$X,SBLC!$T:$T,"Unpaid",SBLC!$R:$R,'DAILY UPDATE SHEET'!$A46,SBLC!$B:$B,$F$36,SBLC!$H:$H,"10%") -> 0 | H46: =SUM(B46:G46) -> 0
A47: =A46+1 -> 46187 | B47: =SUMIFS('LC-Final List'!$W:$W,'LC-Final List'!$AE:$AE,"Unpaid",'LC-Final List'!$Y:$Y,'DAILY UPDATE SHEET'!$A47,'LC-Final List'!$E:$E,'DAILY UPDATE SHEET'!B$36,'LC-Final List'!$F:$F,"10%") -> 0 | C47: =SUMIFS(SBLC!$X:$X,SBLC!$T:$T,"Unpaid",SBLC!$R:$R,'DAILY UPDATE SHEET'!$A47,SBLC!$B:$B,$B$36,SBLC!$H:$H,"10%") -> 0 | D47: =SUMIFS('LC-Final List'!$W:$W,'LC-Final List'!$AE:$AE,"Unpaid",'LC-Final List'!$Y:$Y,'DAILY UPDATE SHEET'!$A47,'LC-Final List'!$E:$E,'DAILY UPDATE SHEET'!D$36,'LC-Final List'!$F:$F,"10%") -> 0 | E47: =SUMIFS(SBLC!$X:$X,SBLC!$T:$T,"Unpaid",SBLC!$R:$R,'DAILY UPDATE SHEET'!$A47,SBLC!$B:$B,$D$36,SBLC!$H:$H,"10%") -> 0 | F47: =SUMIFS('LC-Final List'!$W:$W,'LC-Final List'!$AE:$AE,"Unpaid",'LC-Final List'!$Y:$Y,'DAILY UPDATE SHEET'!$A47,'LC-Final List'!$E:$E,'DAILY UPDATE SHEET'!F$36,'LC-Final List'!$F:$F,"10%") -> 0 | G47: =SUMIFS(SBLC!$X:$X,SBLC!$T:$T,"Unpaid",SBLC!$R:$R,'DAILY UPDATE SHEET'!$A47,SBLC!$B:$B,$F$36,SBLC!$H:$H,"10%") -> 0 | H47: =SUM(B47:G47) -> 0
A48: =A47+1 -> 46188 | B48: =SUMIFS('LC-Final List'!$W:$W,'LC-Final List'!$AE:$AE,"Unpaid",'LC-Final List'!$Y:$Y,'DAILY UPDATE SHEET'!$A48,'LC-Final List'!$E:$E,'DAILY UPDATE SHEET'!B$36,'LC-Final List'!$F:$F,"10%") -> 3.7662287e+08 | C48: =SUMIFS(SBLC!$X:$X,SBLC!$T:$T,"Unpaid",SBLC!$R:$R,'DAILY UPDATE SHEET'!$A48,SBLC!$B:$B,$B$36,SBLC!$H:$H,"10%") -> 0 | D48: =SUMIFS('LC-Final List'!$W:$W,'LC-Final List'!$AE:$AE,"Unpaid",'LC-Final List'!$Y:$Y,'DAILY UPDATE SHEET'!$A48,'LC-Final List'!$E:$E,'DAILY UPDATE SHEET'!D$36,'LC-Final List'!$F:$F,"10%") -> 0 | E48: =SUMIFS(SBLC!$X:$X,SBLC!$T:$T,"Unpaid",SBLC!$R:$R,'DAILY UPDATE SHEET'!$A48,SBLC!$B:$B,$D$36,SBLC!$H:$H,"10%") -> 0 | F48: =SUMIFS('LC-Final List'!$W:$W,'LC-Final List'!$AE:$AE,"Unpaid",'LC-Final List'!$Y:$Y,'DAILY UPDATE SHEET'!$A48,'LC-Final List'!$E:$E,'DAILY UPDATE SHEET'!F$36,'LC-Final List'!$F:$F,"10%") -> 232502400 | G48: =SUMIFS(SBLC!$X:$X,SBLC!$T:$T,"Unpaid",SBLC!$R:$R,'DAILY UPDATE SHEET'!$A48,SBLC!$B:$B,$F$36,SBLC!$H:$H,"10%") -> 0 | H48: =SUM(B48:G48) -> 6.0912527e+08
A49: =A48+1 -> 46189 | B49: =SUMIFS('LC-Final List'!$W:$W,'LC-Final List'!$AE:$AE,"Unpaid",'LC-Final List'!$Y:$Y,'DAILY UPDATE SHEET'!$A49,'LC-Final List'!$E:$E,'DAILY UPDATE SHEET'!B$36,'LC-Final List'!$F:$F,"10%") -> 76898304 | C49: =SUMIFS(SBLC!$X:$X,SBLC!$T:$T,"Unpaid",SBLC!$R:$R,'DAILY UPDATE SHEET'!$A49,SBLC!$B:$B,$B$36,SBLC!$H:$H,"10%") -> 0 | D49: =SUMIFS('LC-Final List'!$W:$W,'LC-Final List'!$AE:$AE,"Unpaid",'LC-Final List'!$Y:$Y,'DAILY UPDATE SHEET'!$A49,'LC-Final List'!$E:$E,'DAILY UPDATE SHEET'!D$36,'LC-Final List'!$F:$F,"10%") -> 0 | E49: =SUMIFS(SBLC!$X:$X,SBLC!$T:$T,"Unpaid",SBLC!$R:$R,'DAILY UPDATE SHEET'!$A49,SBLC!$B:$B,$D$36,SBLC!$H:$H,"10%") -> 0 | F49: =SUMIFS('LC-Final List'!$W:$W,'LC-Final List'!$AE:$AE,"Unpaid",'LC-Final List'!$Y:$Y,'DAILY UPDATE SHEET'!$A49,'LC-Final List'!$E:$E,'DAILY UPDATE SHEET'!F$36,'LC-Final List'!$F:$F,"10%") -> 0 | G49: =SUMIFS(SBLC!$X:$X,SBLC!$T:$T,"Unpaid",SBLC!$R:$R,'DAILY UPDATE SHEET'!$A49,SBLC!$B:$B,$F$36,SBLC!$H:$H,"10%") -> 0 | H49: =SUM(B49:G49) -> 76898304
A50: =A49+1 -> 46190 | B50: =SUMIFS('LC-Final List'!$W:$W,'LC-Final List'!$AE:$AE,"Unpaid",'LC-Final List'!$Y:$Y,'DAILY UPDATE SHEET'!$A50,'LC-Final List'!$E:$E,'DAILY UPDATE SHEET'!B$36,'LC-Final List'!$F:$F,"10%") -> 2.6303468e+08 | C50: =SUMIFS(SBLC!$X:$X,SBLC!$T:$T,"Unpaid",SBLC!$R:$R,'DAILY UPDATE SHEET'!$A50,SBLC!$B:$B,$B$36,SBLC!$H:$H,"10%") -> 0 | D50: =SUMIFS('LC-Final List'!$W:$W,'LC-Final List'!$AE:$AE,"Unpaid",'LC-Final List'!$Y:$Y,'DAILY UPDATE SHEET'!$A50,'LC-Final List'!$E:$E,'DAILY UPDATE SHEET'!D$36,'LC-Final List'!$F:$F,"10%") -> 0 | E50: =SUMIFS(SBLC!$X:$X,SBLC!$T:$T,"Unpaid",SBLC!$R:$R,'DAILY UPDATE SHEET'!$A50,SBLC!$B:$B,$D$36,SBLC!$H:$H,"10%") -> 0 | F50: =SUMIFS('LC-Final List'!$W:$W,'LC-Final List'!$AE:$AE,"Unpaid",'LC-Final List'!$Y:$Y,'DAILY UPDATE SHEET'!$A50,'LC-Final List'!$E:$E,'DAILY UPDATE SHEET'!F$36,'LC-Final List'!$F:$F,"10%") -> 0 | G50: =SUMIFS(SBLC!$X:$X,SBLC!$T:$T,"Unpaid",SBLC!$R:$R,'DAILY UPDATE SHEET'!$A50,SBLC!$B:$B,$F$36,SBLC!$H:$H,"10%") -> 0 | H50: =SUM(B50:G50) -> 2.6303468e+08
... A152: =A151+1 -> 46292 | B152: =SUMIFS('LC-Final List'!$W:$W,'LC-Final List'!$AE:$AE,"Unpaid",'LC-Final List'!$Y:$Y,'DAILY UPDATE SHEET'!$A152,'LC-Final List'!$E:$E,'DAILY UPDATE SHEET'!B$36,'LC-Final List'!$F:$F,"10%") -> 0 | C152: =SUMIFS(SBLC!$X:$X,SBLC!$T:$T,"Unpaid",SBLC!$R:$R,'DAILY UPDATE SHEET'!$A152,SBLC!$B:$B,$B$36,SBLC!$H:$H,"10%") -> 0 | D152: =SUMIFS('LC-Final List'!$W:$W,'LC-Final List'!$AE:$AE,"Unpaid",'LC-Final List'!$Y:$Y,'DAILY UPDATE SHEET'!$A152,'LC-Final List'!$E:$E,'DAILY UPDATE SHEET'!D$36,'LC-Final List'!$F:$F,"10%") -> 0 | E152: =SUMIFS(SBLC!$X:$X,SBLC!$T:$T,"Unpaid",SBLC!$R:$R,'DAILY UPDATE SHEET'!$A152,SBLC!$B:$B,$D$36,SBLC!$H:$H,"10%") -> 0 | F152: =SUMIFS('LC-Final List'!$W:$W,'LC-Final List'!$AE:$AE,"Unpaid",'LC-Final List'!$Y:$Y,'DAILY UPDATE SHEET'!$A152,'LC-Final List'!$E:$E,'DAILY UPDATE SHEET'!F$36,'LC-Final List'!$F:$F,"10%") -> 0 | G152: =SUMIFS(SBLC!$X:$X,SBLC!$T:$T,"Unpaid",SBLC!$R:$R,'DAILY UPDATE SHEET'!$A152,SBLC!$B:$B,$F$36,SBLC!$H:$H,"10%") -> 0 | H152: =SUM(B152:G152) -> 0
A153: TOTAL OUTSTANDING | B153: =SUM(B38:B152) -> 3.4017975e+09 | C153: =SUM(C38:C152) -> 1.1375264e+09 | D153: =SUM(D38:D152) -> 4.4183724e+08 | E153: =SUM(E38:E152) -> 1.6692593e+08 | F153: =SUM(F38:F152) -> 5.733852e+08 | G153: =SUM(G38:G152) -> 8.205892e+08 | H153: =SUM(H38:H152) -> 6.5420615e+09
A155: Monthly Payable | E155: Expiring LCs and documents not received (Next 10 Days) | K155: Expiring FDs if plan for withdraw (Next 7 Days)
A157: MONTHLY PAYABLE SUMMARY | B157: LC AMOUNT (INR) | C157: SBLC AMOUNT (INR) | E157: Expiring LCs | F157: SBI | G157: IDBI | H157: BOI | I157: AMOUNT (INR) | K157: Expiring FDs | L157: SBI | M157: IDBI | N157: BOI | O157: AMOUNT (INR)
A158: 46143 | B158: =SUMIFS('LC-Final List'!$W:$W, 'LC-Final List'!$AC:$AC, $A158, 'LC-Final List'!$AE:$AE, "*Unpaid*") -> 0 | C158: 0 | E158: =A38 -> 46178 | I158: =SUM(F158:H158) -> 0 | K158: =E158 -> 46178 | O158: =SUM(L158:N158) -> 0
A159: 46174 | B159: =SUMIFS('LC-Final List'!$W:$W, 'LC-Final List'!$AC:$AC, $A159, 'LC-Final List'!$AE:$AE, "*Unpaid*") -> 3.038332e+09 | C159: 0 | E159: =A39 -> 46179 | I159: =SUM(F159:H159) -> 0 | K159: =E159 -> 46179 | O159: =SUM(L159:N159) -> 0
A160: 46204 | B160: =SUMIFS('LC-Final List'!$W:$W, 'LC-Final List'!$AC:$AC, $A160, 'LC-Final List'!$AE:$AE, "*Unpaid*") -> 1.2268206e+09 | C160: =SUMIFS(SBLC!$X:$X,SBLC!S:S,'DAILY UPDATE SHEET'!$A160,SBLC!T:T,"Unpaid") -> 1.7340395e+09 | E160: =A40 -> 46180 | I160: =SUM(F160:H160) -> 0 | K160: =E160 -> 46180 | O160: =SUM(L160:N160) -> 0
A161: 46235 | B161: =SUMIFS('LC-Final List'!$W:$W, 'LC-Final List'!$AC:$AC, $A161, 'LC-Final List'!$AE:$AE, "*Unpaid*") -> 28999680 | C161: =SUMIFS(SBLC!$X:$X,SBLC!S:S,'DAILY UPDATE SHEET'!$A161,SBLC!T:T,"Unpaid") -> 2.6826307e+08 | E161: =A41 -> 46181 | I161: =SUM(F161:H161) -> 0 | K161: =E161 -> 46181 | O161: =SUM(L161:N161) -> 0
A162: 46266 | B162: =SUMIFS('LC-Final List'!$W:$W, 'LC-Final List'!$AC:$AC, $A162, 'LC-Final List'!$AE:$AE, "*Unpaid*") -> 122867712 | C162: =SUMIFS(SBLC!$X:$X,SBLC!S:S,'DAILY UPDATE SHEET'!$A162,SBLC!T:T,"Unpaid") -> 1.22739e+08 | E162: =A42 -> 46182 | I162: =SUM(F162:H162) -> 0 | K162: =E162 -> 46182 | O162: =SUM(L162:N162) -> 0
A163: 46296 | B163: =SUMIFS('LC-Final List'!$W:$W, 'LC-Final List'!$AC:$AC, $A163, 'LC-Final List'!$AE:$AE, "*Unpaid*") -> 0 | C163: =SUMIFS(SBLC!$X:$X,SBLC!S:S,'DAILY UPDATE SHEET'!$A163,SBLC!T:T,"Unpaid") -> 0 | E163: =A43 -> 46183 | I163: =SUM(F163:H163) -> 0 | K163: =E163 -> 46183 | O163: =SUM(L163:N163) -> 0
A164: 46327 | B164: =SUMIFS('LC-Final List'!$W:$W, 'LC-Final List'!$AC:$AC, $A164, 'LC-Final List'!$AE:$AE, "*Unpaid*") -> 0 | C164: =SUMIFS(SBLC!$X:$X,SBLC!S:S,'DAILY UPDATE SHEET'!$A164,SBLC!T:T,"Unpaid") -> 6.4625993e+08 | E164: =A44 -> 46184 | I164: =SUM(F164:H164) -> 0 | K164: =E164 -> 46184 | O164: =SUM(L164:N164) -> 0
A165: 46357 | B165: =SUMIFS('LC-Final List'!$W:$W, 'LC-Final List'!$AC:$AC, $A165, 'LC-Final List'!$AE:$AE, "*Unpaid*") -> 0 | C165: =SUMIFS(SBLC!$X:$X,SBLC!S:S,'DAILY UPDATE SHEET'!$A165,SBLC!T:T,"Unpaid") -> 8837386.4 | E165: =A45 -> 46185 | I165: =SUM(F165:H165) -> 0 | K165: =E165 -> 46185 | O165: =SUM(L165:N165) -> 0
C166: =SUMIFS(SBLC!$Q:$Q,SBLC!S:S,'DAILY UPDATE SHEET'!$A166,SBLC!T:T,"Unpaid") -> 0 | E166: =A46 -> 46186 | I166: =SUM(F166:H166) -> 0 | K166: =E166 -> 46186 | O166: =SUM(L166:N166) -> 0
A167: TOTAL OUTSTANDING | B167: =SUM(B158:B166) -> 4417019976 | C167: =SUM(C158:C166) -> 2.7801389e+09 | E167: =A47 -> 46187 | I167: =SUM(F167:H167) -> 0 | K167: =E167 -> 46187 | O167: =SUM(L167:N167) -> 0
E168: TOTAL | F168: =SUM(F158:F167) -> 0 | G168: =SUM(G158:G167) -> 0 | H168: =SUM(H158:H167) -> 0 | I168: 0 | K168: TOTAL | L168: =SUM(L158:L167) -> 0 | M168: =SUM(M158:M167) -> 0 | N168: =SUM(N158:N167) -> 0 | O168: 0
A170: LC Limit Available
A172: SBLC Status | B172: (Multiple Items)
A174: Sum of LC Limit Available
B175: CANCELLED | D175: NO | F175: YES | I175: SOFT COPY | J175: Grand Total
A176: Row Labels | B176: SBI | C176: IDBI | D176: SBI | E176: IDBI | F176: SBI | G176: IDBI | H176: BOI | I176: IDBI
A177: 46178 | F177: 1.3027923e+08 | J177: 1.3027923e+08
A178: 46184 | F178: 4.8433801e+08 | J178: 4.8433801e+08
A179: 46186 | F179: 2.4195297e+08 | J179: 2.4195297e+08
A180: 46187 | F180: 5.509516e+08 | H180: 169992000 | J180: 7.209436e+08
A181: 46190 | F181: 5.9444844e+08 | H181: 232502400 | J181: 8.2695084e+08
A182: 46191 | F182: 76898304 | J182: 76898304
A183: 46192 | B183: 3.3370871e+08 | F183: 1.304605e+08 | J183: 4.641692e+08
A184: 46197 | C184: 825702.72 | F184: 182793600 | G184: 3.5825918e+08 | J184: 541878480
A185: 46198 | F185: 6344064 | J185: 6344064
A186: 46204 | F186: 105580800 | J186: 105580800
A187: 46207 | H187: 45771970 | J187: 45771970
A188: 46212 | F188: 93888000 | J188: 93888000
A189: 46213 | F189: 98082794 | J189: 98082794
A190: 46219 | D190: 57673728 | J190: 57673728
A191: 46220 | D191: 53705760 | J191: 53705760
A192: 46224 | I192: 49147085 | J192: 49147085
A193: 46235 | D193: 160043352 | J193: 160043352
A194: 46250 | E194: 22579200 | J194: 22579200
A195: 46255 | E195: 6420480 | J195: 6420480
A196: 46280 | D196: 122867712 | J196: 122867712
A197: (blank) | B197: 0 | D197: 0 | F197: 0 | J197: 0
A198: Grand Total | B198: 3.3370871e+08 | C198: 825702.72 | D198: 394290552 | E198: 28999680 | F198: 2.6960183e+09 | G198: 3.5825918e+08 | H198: 4.4826637e+08 | I198: 49147085 | J198: 4.3095156e+09

Sheet SBLC
A1: SBLC REF NO | B1: BANK | C1: SBLC ISSUE DATE | D1: PO NO | E1: LC no. | F1: BILL REF NO | G1: LC Op. Date | H1: Percentage | I1: Supplier Name | J1: Currency | K1: DOCUMENTS RECEIVED | L1: Bill Invoice No | M1: Bill Lodge date | N1: Bill Acceptance date | O1: SBLC Bill Amt (in FC) | P1: Rate | Q1: BOE Bill Amt (in INR) | R1: SBLC LC Payment Due Date | S1: MONTH | T1: Payment Status | U1: Notional Int Amt (USD) | V1: Final Int Amt (USD) | W1: PAYMENT AMT [USD] BILL AMT +INT AMT | X1: Final PAYMENT AMT INR | Y1: FD NO | Z1: LIEN AMT | AA1: FD NO | AB1: LIEN AMT | AC1: FD NO | AD1: LIEN AMT
A2: 0692625TC0A00009 | B2: SBI | C2: 45943 | D2: 5600000237 | E2: 0692625IM0Y00181 | F2: 0692625US0B00519 | G2: 45828 | H2: 0.1 | I2: JIETAI NEW ENERGY TECHNOLOGY (HK) LIMITED | J2: USD | K2: YES | L2: HK-GREW-250808 | M2: 45894 | N2: 45899 | O2: 741181.06 | P2: 90 | Q2: =O2*P2 -> 66706295 | R2: 46030 | S2: =IF(R2="","-",TEXT(R2,"mmmmyy")) -> January26 | T2: Paid | U2: 7889.3573 | V2: 7811 | W2: =V2+O2 -> 748992.06 | Y2: 42039487699 | Z2: 870318 | AA2: 42855164420 | AB2: 308987 | AC2: 44085316349 | AD2: 5418700 | AF2: =Z2+AB2+AD2 -> 6598005 | AG2: =Q2*10% -> 6670629.5 | AH2: =AG2-AF2 -> 72624.54
A3: 0692625TC0A00010 | B3: SBI | C3: 45943 | D3: 5600000264 | E3: 0692625IM0Y00241 | F3: 0692625US0B00561 | G3: 45873 | H3: 1.1 | I3: FLAT HONG KONG CO LTD | J3: USD | K3: YES | L3: 80883796/80875012/80883463/80884631 | M3: 45908 | N3: 45917 | O3: 1111500 | P3: 90 | Q3: =O3*P3 -> 100035000 | R3: 46030 | S3: =IF(R3="","-",TEXT(R3,"mmmmyy")) -> January26 | T3: Paid | U3: 11831.145 | V3: 11713.64 | W3: =V3+O3 -> 1123213.6 | Y3: 44085316349 | Z3: 9894573 | AA3: - | AB3: 0 | AC3: - | AD3: 0 | AF3: =Z3+AB3+AD3 -> 9894573 | AG3: =Q3*10% -> 10003500 | AH3: =AG3-AF3 -> 108927
A4: 0692625TC0A00011 | B4: SBI | C4: 45943 | D4: 5600000268 | E4: 0692625IM0Y00238 | F4: 0692625US0B00546 | G4: 45873 | H4: 1.1 | I4: XINYI PV PRODUCTS (ANHUI) HOLDINGSLTD | J4: USD | K4: YES | L4: 42025080096 | M4: 45901 | N4: 45908 | O4: 83049.5 | P4: 90 | Q4: =O4*P4 -> 7474455 | R4: 46030 | S4: =IF(R4="","-",TEXT(R4,"mmmmyy")) -> January26 | T4: Paid | U4: 884.00421 | V4: 875.22 | W4: =V4+O4 -> 83924.72 | Y4: 44085316349 | Z4: 739307 | AA4: - | AB4: 0 | AC4: - | AD4: 0 | AF4: =Z4+AB4+AD4 -> 739307 | AG4: =Q4*10% -> 747445.5 | AH4: =AG4-AF4 -> 8138.5
A5: 0692625TC0A00012 | B5: SBI | C5: 45943 | D5: 5600000268 | E5: 0692625IM0Y00238 | F5: 0692625US0B00540 | G5: 45873 | H5: 1.1 | I5: XINYI PV PRODUCTS (ANHUI) HOLDINGSLTD | J5: USD | K5: YES | L5: 42025080075 | M5: 45901 | N5: 45908 | O5: 83049.5 | P5: 90 | Q5: =O5*P5 -> 7474455 | R5: 46030 | S5: =IF(R5="","-",TEXT(R5,"mmmmyy")) -> January26 | T5: Paid | U5: 884.00421 | V5: 875.22 | W5: =V5+O5 -> 83924.72 | Y5: 44085316349 | Z5: 3647682 | AA5: - | AB5: 0 | AC5: - | AD5: 0 | AF5: =Z5+AB5+AD5 -> 3647682 | AG5: =Q5*10% -> 747445.5 | AH5: =AG5-AF5 -> -2900236.5
A6: 0692625TC0A00013 | B6: SBI | C6: 45943 | D6: 5600000267 | E6: 0692625IM0Y00237 | F6: 0692625US0B00541 | G6: 45873 | H6: 0.1 | I6: YIBIN YINGFA DEYAO TECHNOLOGY CO LTD | J6: USD | K6: YES | L6: YFDY25080804 | M6: 45901 | N6: 45904 | O6: 409759.8 | P6: 90 | Q6: =O6*P6 -> 36878382 | R6: 46030 | S6: =IF(R6="","-",TEXT(R6,"mmmmyy")) -> January26 | T6: Paid | U6: 4361.6083 | V6: 4318.29 | W6: =V6+O6 -> 414078.09 | Y6: 44085316349 | Z6: 3647682 | AA6: - | AB6: 0 | AC6: - | AD6: 0 | AF6: =Z6+AB6+AD6 -> 3647682 | AG6: =Q6*10% -> 3687838.2 | AH6: =AG6-AF6 -> 40156.2
A7: 0692625TC0A00014 | B7: SBI | C7: 45943 | D7: 5600000251 | E7: 0692625IM0Y00261 | F7: 0692625US0B00559 | G7: 45890 | H7: 0.1 | I7: FLAT HONG KONG CO LTD | J7: USD | K7: YES | L7: 80876299 | M7: 45908 | N7: 45916 | O7: 225540 | P7: 90 | Q7: =O7*P7 -> 20298600 | R7: 46030 | S7: =IF(R7="","-",TEXT(R7,"mmmmyy")) -> January26 | T7: Paid | U7: 2400.7165 | V7: 2376.87 | W7: =V7+O7 -> 227916.87 | Y7: 44085316349 | Z7: 2007757 | AA7: - | AB7: 0 | AC7: - | AD7: 0 | AF7: =Z7+AB7+AD7 -> 2007757 | AG7: =Q7*10% -> 2029860 | AH7: =AG7-AF7 -> 22103
A8: 0692625TC0A00015 | B8: SBI | C8: 45943 | D8: 5600000237 | E8: 0692625IM0Y00181 | F8: 0692625US0B00555 | G8: 45828 | H8: 0.1 | I8: JIETAI NEW ENERGY TECHNOLOGY (HK) LIMITED | J8: USD | K8: YES | L8: HK-GREW-250811 | M8: 45908 | N8: 45911 | O8: 369693.68 | P8: 90 | Q8: =O8*P8 -> 33272431 | R8: 46030 | S8: =IF(R8="","-",TEXT(R8,"mmmmyy")) -> January26 | T8: Paid | U8: 3935.1323 | V8: 3896.05 | W8: =V8+O8 -> 373589.73 | Y8: 42855164420 | Z8: 3291013 | AA8: - | AB8: 0 | AC8: - | AD8: 0 | AF8: =Z8+AB8+AD8 -> 3291013 | AG8: =Q8*10% -> 3327243.1 | AH8: =AG8-AF8 -> 36230.12
A9: 0692625TC0A00021 | B9: SBI | C9: 45945 | D9: 5600000246 | E9: 0692625IM0Y00216 | F9: 0692625US0B00526 | G9: 45856 | H9: 0.1 | I9: JIANGYIN TINZE NEW ENERGY TECHNOLOGY CO., LTD | J9: USD | K9: YES | L9: STG2025-0721 | M9: 45898 | N9: 45903 | O9: 573882 | P9: 90 | Q9: =O9*P9 -> 51649380 | R9: 46035 | S9: =IF(R9="","-",TEXT(R9,"mmmmyy")) -> January26 | T9: Paid | U9: 6303.5629 | V9: 6233.52 | W9: =V9+O9 -> 580115.52 | Y9: 44361399732 | Z9: 941024 | AA9: 44361399732 | AB9: 12645000 | AC9: 44085316349 | AD9: 4167674 | AF9: =Z9+AB9+AD9 -> 17753698 | AG9: =Q9*10% -> 5164938 | AH9: =AG9-AF9 -> -12588760
A10: 0692625TC0A00022 | B10: SBI | C10: 45946 | D10: 5600000264 | E10: 0692625IM0Y00248 | F10: 0692625US0B00627 | G10: 45880 | H10: 0.1 | I10: FLAT HONG KONG CO LTD | J10: USD | K10: YES | L10: 80886515 | M10: 45926 | N10: 45933 | O10: 237315 | P10: 90 | Q10: =O10*P10 -> 21358350 | R10: 46035 | S10: =IF(R10="","-",TEXT(R10,"mmmmyy")) -> January26 | T10: Paid | U10: 2606.6858 | V10: 2570.68 | W10: =V10+O10 -> 239885.68 | Y10: 44361399732 | Z10: 2112578 | AA10: - | AB10: 0 | AC10: - | AD10: 0 | AF10: =Z10+AB10+AD10 -> 2112578 | AG10: =Q10*10% -> 2135835 | AH10: =AG10-AF10 -> 23257
A11: 0692625TC0A00023 | B11: SBI | C11: 45946 | D11: 5600000264 | E11: 0692625IM0Y00246 | F11: 0692625US0B00579 | G11: 45876 | H11: 0.1 | I11: FLAT HONG KONG CO LTD | J11: USD | K11: YES | L11: 80889650 | M11: 45916 | N11: 45920 | O11: 266760 | P11: 90 | Q11: =O11*P11 -> 24008400 | R11: 46035 | S11: =IF(R11="","-",TEXT(R11,"mmmmyy")) -> January26 | T11: Paid | U11: 2930.1118 | V11: 2889.64 | W11: =V11+O11 -> 269649.64 | Y11: 44361399732 | Z11: 2961428 | AA11: - | AB11: 0 | AC11: - | AD11: 0 | AF11: =Z11+AB11+AD11 -> 2961428 | AG11: =Q11*10% -> 2400840 | AH11: =AG11-AF11 -> -560588
A12: 0692625TC0A00024 | B12: SBI | C12: 45946 | D12: 5600000246 | E12: 0692625IM0Y00223 | F12: 0692625US0B00575 | G12: 45863 | H12: 0.1 | I12: JIANGYIN TINZE NEW ENERGY TECHNOLOGY CO., LTD | J12: USD | K12: YES | L12: STG2025-0728 | M12: 45915 | N12: 45917 | O12: 492000 | P12: 90 | Q12: =O12*P12 -> 44280000 | R12: 46035 | S12: =IF(R12="","-",TEXT(R12,"mmmmyy")) -> January26 | T12: Paid | U12: 5404.1649 | V12: 5329.52 | W12: =V12+O12 -> 497329.52 | Y12: 43707298765 | Z12: 4379784 | AA12: - | AB12: 0 | AC12: - | AD12: 0 | AF12: =Z12+AB12+AD12 -> 4379784 | AG12: =Q12*10% -> 4428000 | AH12: =AG12-AF12 -> 48216
A13: 0692625TC0A00025 | B13: SBI | C13: 45946 | D13: 5600000268 | E13: 0692625IM0Y00244 | F13: 0692625US0B00539 | G13: 45876 | H13: 0.1 | I13: XINYI PV PRODUCTS (ANHUI) HOLDINGSLTD | J13: USD | K13: YES | L13: 42025080092/93 | M13: 45901 | N13: 45904 | O13: 332552 | P13: 90 | Q13: =O13*P13 -> 29929680 | R13: 46035 | S13: =IF(R13="","-",TEXT(R13,"mmmmyy")) -> January26 | T13: Paid | U13: 3652.7761 | V13: 3602.32 | W13: =V13+O13 -> 336154.32 | Y13: 43707298765 | Z13: 2960377 | AA13: - | AB13: 0 | AC13: - | AD13: 0 | AF13: =Z13+AB13+AD13 -> 2960377 | AG13: =Q13*10% -> 2992968 | AH13: =AG13-AF13 -> 32591
A14: 0692625TC0A00026 | B14: SBI | C14: 45946 | D14: 5600000268 | E14: 0692625IM0Y00244 | F14: 0692625US0B00556 | G14: 45876 | H14: 0.1 | I14: XINYI PV PRODUCTS (ANHUI) HOLDINGSLTD | J14: USD | K14: YES | L14: 42025080098/99 | M14: 45908 | N14: 45916 | O14: 332670 | P14: 90 | Q14: =O14*P14 -> 29940300 | R14: 46035 | S14: =IF(R14="","-",TEXT(R14,"mmmmyy")) -> January26 | T14: Paid | U14: 3654.0722 | V14: 3603.6 | W14: =V14+O14 -> 336273.6 | AA14: - | AB14: 0 | AC14: - | AD14: 0 | AF14: =Z14+AB14+AD14 -> 0 | AG14: =Q14*10% -> 2994030 | AH14: =AG14-AF14 -> 2994030
A15: 0692625TC0A00027 | B15: SBI | C15: 45946 | D15: 5600000264 | E15: 0692625IM0Y00248 | F15: 0692625US0B00603 | G15: 45880 | H15: 0.1 | I15: FLAT HONG KONG CO LTD | J15: USD | K15: YES | L15: 80881389/80888026/80884223 | M15: 45920 | N15: 45925 | O15: 474630 | P15: 90 | Q15: =O15*P15 -> 42716700 | R15: 46035 | S15: =IF(R15="","-",TEXT(R15,"mmmmyy")) -> January26 | T15: Paid | U15: 5213.3715 | V15: 5141.36 | W15: =V15+O15 -> 479771.36 | Y15: 44361399732 | Z15: 4225156 | AA15: - | AB15: 0 | AC15: - | AD15: 0 | AF15: =Z15+AB15+AD15 -> 4225156 | AG15: =Q15*10% -> 4271670 | AH15: =AG15-AF15 -> 46514
A16: 0692625TC0A00029 | B16: SBI | C16: 45971 | D16: 5600000238 | E16: 0692625IM0Y00220 | F16: 0692625US0B00613 | G16: 45857 | H16: 0.1 | I16: JIETAI NEW ENERGY TECHNOLOGY (HK) LIMITED | J16: USD | K16: YES | L16: HK-GREW-250831 | M16: 45926 | N16: 45933 | O16: 900028.08 | P16: 90 | Q16: =O16*P16 -> 81002527 | R16: 46058 | S16: =IF(R16="","-",TEXT(R16,"mmmmyy")) -> February26 | T16: Paid | U16: 9933.9474 | V16: 9602.82 | W16: =O16+V16 -> 909630.9 | Y16: 43630359430 | Z16: 7581573 | AA16: 43607525170 | AB16: 479978 | AC16: - | AD16: 0 | AF16: =Z16+AB16+AD16 -> 8061551 | AG16: =Q16*10% -> 8100252.7 | AH16: =AG16-AF16 -> 38701.72
A17: 0692625TC0A00032 | B17: SBI | C17: 45971 | D17: 5600000275 | E17: 0692625IM0Y00231 | F17: 0692625US0B00623 | G17: 45867 | H17: 0.1 | I17: JIETAI NEW ENERGY TECHNOLOGY (HK) LIMITED | J17: USD | K17: YES | L17: HK-GREW-250818 | M17: 45925 | N17: 45930 | O17: 825742.11 | P17: 90 | Q17: =O17*P17 -> 74316790 | R17: 46058 | S17: =IF(R17="","-",TEXT(R17,"mmmmyy")) -> February26 | T17: Paid | U17: 9114.0253 | V17: 8810.22 | W17: =O17+V17 -> 834552.33 | Y17: 43630359430 | Z17: 7412687 | AA17: - | AB17: 0 | AC17: - | AD17: 0 | AF17: =Z17+AB17+AD17 -> 7412687 | AG17: =Q17*10% -> 7431679 | AH17: =AG17-AF17 -> 18991.99
A18: 0692625TC0A00030 | B18: SBI | C18: 45971 | D18: 5600000261 | E18: 0692625IM0Y00250 | F18: 0692625US0B00653 | G18: 45882 | H18: 0.1 | I18: JIANGYIN TINZE NEW ENERGY TECHNOLOGY CO., LTD | J18: USD | K18: YES | L18: STG2025-0815/STG2025-0817/STG2025-0818 | M18: 45922 | N18: 45931 | O18: 1230000 | P18: 90 | Q18: =O18*P18 -> 110700000 | R18: 46058 | S18: =IF(R18="","-",TEXT(R18,"mmmmyy")) -> February26 | T18: Paid | U18: 13575.971 | V18: 13123.44 | W18: =O18+V18 -> 1243123.4 | Y18: 43649959856 | Z18: 11029410 | AA18: - | AB18: 0 | AC18: - | AD18: 0 | AF18: =Z18+AB18+AD18 -> 11029410 | AG18: =Q18*10% -> 11070000 | AH18: =AG18-AF18 -> 40590
A19: 0692625TC0A00031 | B19: SBI | C19: 45971 | D19: 5600000259 | E19: 0692625IM0Y00257 | F19: 0692625US0B00618 | G19: 45889 | H19: 0.1 | I19: JIANGSU SULV NEW MATERIAL TECHNOLOGY CO LTD | J19: USD | K19: YES | L19: SL-GREW-2025-8-29 | M19: 45922 | N19: 45925 | O19: 384750 | P19: 90 | Q19: =O19*P19 -> 34627500 | R19: 46058 | S19: =IF(R19="","-",TEXT(R19,"mmmmyy")) -> February26 | T19: Paid | U19: 4246.63 | V19: 4105.08 | W19: =O19+V19 -> 388855.08 | Y19: 43649959856 | Z19: 179863 | AA19: 43792161126 | AB19: 3266342 | AC19: - | AD19: 0 | AF19: =Z19+AB19+AD19 -> 3446205 | AG19: =Q19*10% -> 3462750 | AH19: =AG19-AF19 -> 16545
A20: 0692625TC0A00033 | B20: SBI | C20: 45971 | D20: 5600000261 | E20: 0692625IM0Y00259 | F20: 0692625US0B00616 | G20: 45889 | H20: 0.1 | I20: JIANGYIN TINZE NEW ENERGY TECHNOLOGY CO., LTD | J20: USD | K20: YES | L20: STG2025-0823/STG2025-0822 | M20: 45922 | N20: 45925 | O20: 820000 | P20: 90 | Q20: =O20*P20 -> 73800000 | R20: 46058 | S20: =IF(R20="","-",TEXT(R20,"mmmmyy")) -> February26 | T20: Paid | U20: 9050.6475 | V20: 8748.96 | W20: =O20+V20 -> 828748.96 | Y20: 43630359430 | Z20: 7344740 | AA20: - | AB20: 0 | AC20: - | AD20: 0 | AF20: =Z20+AB20+AD20 -> 7344740 | AG20: =Q20*10% -> 7380000 | AH20: =AG20-AF20 -> 35260
A21: 0692625TC0A00028 | B21: SBI | C21: 45971 | D21: 5600000249 | E21: 0692625IM0Y00260 | F21: 0692625US0B00636 | G21: 45890 | H21: 0.1 | I21: JIANGYIN TINZE NEW ENERGY TECHNOLOGY CO., LTD | J21: USD | K21: YES | L21: STG2025-0828 | M21: 45930 | N21: 45938 | O21: 377432 | P21: 90 | Q21: =O21*P21 -> 33968880 | R21: 46058 | S21: =IF(R21="","-",TEXT(R21,"mmmmyy")) -> February26 | T21: Paid | U21: 4165.8585 | V21: 4027 | W21: =O21+V21 -> 381459 | Y21: 43792161126 | Z21: 3380658 | AA21: - | AB21: 0 | AC21: - | AD21: 0 | AF21: =Z21+AB21+AD21 -> 3380658 | AG21: =Q21*10% -> 3396888 | AH21: =AG21-AF21 -> 16230
A22: 0692625TC0A00034 | B22: SBI | C22: 45975 | D22: 5600000296 | E22: 0692625IM0Y00287 | F22: 0692625US0B00685 | G22: 45918 | H22: 0.1 | I22: FLAT HONG KONG CO LTD | J22: USD | K22: YES | L22: 80906601 | M22: 45954 | N22: 45962 | O22: 568425 | P22: 90 | Q22: =O22*P22 -> 51158250 | R22: 46063 | S22: =IF(R22="","-",TEXT(R22,"mmmmyy")) -> February26 | T22: Paid | U22: 6187.5431 | V22: 6170.47 | W22: =O22+V22 -> 574595.47 | Y22: 43607525170 | Z22: 5054435 | AA22: - | AB22: 0 | AC22: - | AD22: 0 | AF22: =Z22+AB22+AD22 -> 5054435 | AG22: =Q22*10% -> 5115825 | AH22: =AG22-AF22 -> 61390
A23: 0692625TC0A00039 | B23: SBI | C23: 45985 | D23: 5600000238 | E23: 0692625IM0Y00221 | F23: 0692625US0B00642 | G23: 45859 | H23: 0.1 | I23: JIETAI NEW ENERGY TECHNOLOGY (HK) LIMITED | J23: USD | K23: YES | L23: HK-GREW-250918 | M23: 45931 | N23: 45938 | O23: 898101.22 | P23: 90 | Q23: =O23*P23 -> 80829110 | R23: 46072 | S23: =IF(R23="","-",TEXT(R23,"mmmmyy")) -> February26 | T23: Paid | U23: 9940.3864 | V23: 9609.04 | W23: =O23+V23 -> 907710.26 | Y23: 43630359430 | Z23: 8057764 | AA23: - | AB23: 0 | AC23: - | AD23: 0 | AF23: =Z23+AB23+AD23 -> 8057764 | AG23: =Q23*10% -> 8082911 | AH23: =AG23-AF23 -> 25146.98
A24: 0692626TC0A00003 | B24: SBI | C24: 46044 | D24: 5600000294 | E24: 0692625IM0Y00327 | F24: 0692625US0B00744 | G24: 45979 | H24: 0.1 | I24: TAICANG JUREN INTERNATIONAL TRADE CO LTD | J24: USD | K24: YES | L24: JRIT20251119004 | M24: 45995 | N24: 46000 | O24: 602782 | P24: 90 | Q24: =O24*P24 -> 54250380 | R24: 46132 | S24: =IF(R24="","-",TEXT(R24,"mmmmyy")) -> April26 | T24: Paid | U24: 6313.6745 | V24: 6243.52 | W24: =O24+V24 -> 609025.52
A25: 0692626TC0A00004 | B25: SBI | C25: 46044 | D25: 5600000293 | E25: 0692625IM0Y00328 | F25: 0692625US0B00743 | G25: 45979 | H25: 0.1 | I25: TAICANG JUREN INTERNATIONAL TRADE CO LTD | J25: USD | K25: YES | L25: JRIT20251119002 | M25: 45995 | N25: 46000 | O25: 897397 | P25: 90 | Q25: =O25*P25 -> 80765730 | R25: 46132 | S25: =IF(R25="","-",TEXT(R25,"mmmmyy")) -> April26 | T25: Paid | U25: 9399.5389 | V25: 9295.1 | W25: =O25+V25 -> 906692.1
A26: 261001TCBG00015 | B26: IDBI | C26: 46150 | D26: 5600000383 | E26: 261001FLCU00023 | F26: 26100FBIN00063 | G26: 46056 | H26: 0.1 | I26: FIRST MATERIAL SCIENCE (THAILAND) CO LTD | J26: USD | K26: YES | L26: MSBT250644-2 | M26: 46114 | N26: 46122 | O26: 465125.59 | P26: 95 | Q26: =O26*P26 -> 44186931 | R26: 46239 | S26: =IF(R26="","-",TEXT(R26,"mmmmyy")) -> August26 | T26: Unpaid | W26: =O26+V26 -> 465125.59 | X26: =W26*P26 -> 44186931
A27: 2035BBC26T001144 | B27: BOI | C27: 46150 | D27: 5600000440 | E27: 2035FLCDA260034 | F27: 2035FBRLC260037 | G27: 46099 | H27: 0.1 | I27: JIANGSU SULV PRECISION TECHNOLOGY CO.,LTD | J27: USD | K27: YES | L27: SL-GREW-2026-3-20 | M27: 46128 | N27: 46134 | O27: 912600 | P27: 95 | Q27: =O27*P27 -> 86697000 | R27: 46225 | S27: =IF(R27="","-",TEXT(R27,"mmmmyy")) -> July26 | T27: Unpaid | U27: 0 | V27: =8188.02+240 -> 8428.02 | W27: =O27+V27 -> 921028.02 | X27: =W27*P27 -> 87497662
A28: 2035BBC26T001144 | B28: BOI | C28: 46150 | D28: 5600000440 | E28: 2035FLCDA260034 | F28: 2035FBRLC260035 | G28: 46099 | H28: 0.1 | I28: JIANGSU SULV PRECISION TECHNOLOGY CO.,LTD | J28: USD | K28: YES | L28: SL-GREW-2026-3-17 | M28: 46128 | N28: 46134 | O28: 0 | P28: 0 | Q28: =O28*P28 -> 0 | R28: 46225 | S28: =IF(R28="","-",TEXT(R28,"mmmmyy")) -> July26 | T28: Unpaid | U28: 0 | V28: 0 | W28: =O28+V28 -> 0 | X28: =W28*P28 -> 0
A29: 0692626TC0A00005 | B29: SBI | C29: 46153 | D29: 5600000446 | E29: 0692626IM0Y00074 | F29: 0692626US0B00240 | G29: 46101 | H29: 0.1 | I29: FLAT HONG KONG CO LTD | J29: USD | K29: YES | L29: 81007400 /7403/7405/7674/7678 | M29: 46119 | N29: 46122 | O29: 1307700 | P29: 95 | Q29: =O29*P29 -> 124231500 | R29: 46217 | S29: =IF(R29="","-",TEXT(R29,"mmmmyy")) -> July26 | T29: Unpaid | U29: 10094.592 | W29: =O29+V29 -> 1307700 | X29: =W29*P29 -> 124231500 | Y29: 43074817405 | Z29: 10913952 | AA29: 43286332815 | AB29: 1354889
A30: 0692626TC0A00008 | B30: SBI | C30: 46154 | D30: 5600000395 | E30: 0692626IM0Y00081 | F30: 0692626US0B00253 | G30: 46111 | H30: 0.1 | I30: ARVEE INTERNATIONAL PTE LTD | J30: USD | K30: YES | L30: HKJTGREW20260207-1 | M30: 46127 | N30: 46128 | O30: 1285346.2 | P30: 95 | Q30: =O30*P30 -> 1.2210789e+08 | R30: 46227 | S30: =IF(R30="","-",TEXT(R30,"mmmmyy")) -> July26 | T30: Unpaid | U30: 11402.938 | W30: =O30+V30 -> 1285346.2 | X30: =W30*P30 -> 1.2210789e+08 | Y30: 43607525170 | Z30: 16,27,905.00
A31: 0692626TC0A00006 | B31: SBI | C31: 46154 | D31: 5600000392 | E31: 0692626IM0Y00083 | F31: 0692626US0B00250 | G31: 46111 | H31: 0.1 | I31: ARVEE INTERNATIONAL PTE LTD | J31: USD | K31: YES | L31: ID20260115A-1 | M31: 46127 | N31: 46128 | O31: 671806.77 | P31: 95 | Q31: =O31*P31 -> 63821643 | R31: 46228 | S31: =IF(R31="","-",TEXT(R31,"mmmmyy")) -> July26 | T31: Unpaid | U31: 6038.389 | W31: =O31+V31 -> 671806.77 | X31: =W31*P31 -> 63821643 | Y31: 43286332815 | Z31: 6330875
A32: 0692626TC0A00009 | B32: SBI | C32: 46154 | D32: 5600000392 | E32: 0692626IM0Y00084 | F32: 0692626US0B00254 | G32: 46111 | H32: 0.1 | I32: ARVEE INTERNATIONAL PTE LTD | J32: USD | K32: YES | L32: ID20260115A-2 | M32: 46130 | N32: 46134 | O32: 670006.13 | P32: 95 | Q32: =O32*P32 -> 63650582 | R32: 46228 | S32: =IF(R32="","-",TEXT(R32,"mmmmyy")) -> July26 | T32: Unpaid | U32: 5784.4134 | W32: =O32+V32 -> 670006.13 | X32: =W32*P32 -> 63650582 | Y32: 43183923893 | Z32: 6419789.2
A33: 2035BBC26T001160 | B33: BOI | C33: 46156 | D33: 5600000410 | E33: 2035FLCDA260036 | F33: 2035FBRLC260055 | G33: 46099 | H33: 0.1 | I33: ANHUI CSG NEW ENERGY MATERIAL TECHNOLOGY CO LTD | J33: USD | K33: YES | L33: SFG2602016-5 | M33: 46136 | N33: 46143 | O33: =256680 -> 256680 | P33: 95 | Q33: =O33*P33 -> 24384600 | R33: 46230 | S33: =IF(R33="","-",TEXT(R33,"mmmmyy")) -> July26 | T33: Unpaid | U33: 0 | V33: =11208.14+200 -> 11408.14 | W33: 1294183.1 | X33: =W33*P33 -> 1.229474e+08
A34: 2035BBC26T001160 | B34: BOI | C34: 46156 | D34: 5600000410 | E34: 2035FLCDA260036 | F34: 2035FBRLC260054 | G34: 46099 | H34: 0.1 | I34: ANHUI CSG NEW ENERGY MATERIAL TECHNOLOGY CO LTD | J34: USD | K34: YES | L34: SFG2602016-4 | M34: 46136 | N34: 46143 | O34: =256680 -> 256680 | P34: 95 | Q34: =O34*P34 -> 24384600 | R34: 46230 | S34: =IF(R34="","-",TEXT(R34,"mmmmyy")) -> July26 | T34: Unpaid | U34: 0 | V34: 0
A35: 2035BBC26T001160 | B35: BOI | C35: 46156 | D35: 5600000410 | E35: 2035FLCDA260036 | F35: 2035FBRLC260053 | G35: 46099 | H35: 0.1 | I35: ANHUI CSG NEW ENERGY MATERIAL TECHNOLOGY CO LTD | J35: USD | K35: YES | L35: SFG2602016-3 | M35: 46136 | N35: 46143 | O35: =256680 -> 256680 | P35: 95 | Q35: =O35*P35 -> 24384600 | R35: 46230 | S35: =IF(R35="","-",TEXT(R35,"mmmmyy")) -> July26 | T35: Unpaid | U35: 0 | V35: 0
A36: 2035BBC26T001160 | B36: BOI | C36: 46156 | D36: 5600000410 | E36: 2035FLCDA260036 | F36: 2035FBRLC260049 | G36: 46099 | H36: 0.1 | I36: ANHUI CSG NEW ENERGY MATERIAL TECHNOLOGY CO LTD | J36: USD | K36: YES | L36: SFG2602016-2 | M36: 46134 | N36: 46143 | O36: 256680 | P36: 95 | Q36: =O36*P36 -> 24384600 | R36: 46230 | S36: =IF(R36="","-",TEXT(R36,"mmmmyy")) -> July26 | T36: Unpaid | U36: 0 | V36: 0
A37: 2035BBC26T001160 | B37: BOI | C37: 46156 | D37: 5600000410 | E37: 2035FLCDA260036 | F37: 2035FBRLC260052 | G37: 46099 | H37: 0.1 | I37: ANHUI CSG NEW ENERGY MATERIAL TECHNOLOGY CO LTD | J37: USD | K37: YES | L37: SFG2602016-1 | M37: 46135 | N37: 46143 | O37: 256680 | P37: 95 | Q37: =O37*P37 -> 24384600 | R37: 46230 | S37: =IF(R37="","-",TEXT(R37,"mmmmyy")) -> July26 | T37: Unpaid | U37: 0 | V37: 0
A38: 0692626TC0A00010 | B38: SBI | C38: 46156 | D38: 5600000395 | E38: 0692626IM0Y00082 | F38: 0692626US0B00252 | G38: 46108 | H38: 0.1 | I38: ARVEE INTERNATIONAL PTE LTD | J38: USD | K38: YES | L38: HKJTREW20260207-2 | M38: 46127 | N38: 46128 | O38: 1933395.2 | P38: 95 | Q38: =O38*P38 -> 183672544 | R38: 46224 | S38: =IF(R38="","-",TEXT(R38,"mmmmyy")) -> July26 | T38: Unpaid | U38: 15579.669 | W38: =O38+V38 -> 1933395.2 | X38: =W38*P38 -> 183672544 | Y38: 43630359430 | Z38: 1,82,17,561.37
A39: 261001TCBG00017 | B39: IDBI | C39: 46157 | D39: 5600000384 | E39: 261001FLCU00022 | F39: 261001FIBN00068 | G39: 46056 | H39: 0.1 | I39: FIRST MATERIAL SCIENCE (THAILAND) CO LTD | J39: USD | K39: YES | L39: MSBT250643-3 | M39: 46118 | N39: 46122 | O39: 775209.3 | P39: 95 | Q39: =O39*P39 -> 73644884 | R39: 46332 | S39: =IF(R39="","-",TEXT(R39,"mmmmyy")) -> November26 | T39: Unpaid | W39: =O39+V39 -> 775209.3 | X39: =W39*P39 -> 73644884
A40: 261001TCBG00017 | B40: IDBI | C40: 46157 | D40: 5600000384 | E40: 261001FLCU00022 | F40: 261001FIBN00069 | G40: 46056 | H40: 0.1 | I40: FIRST MATERIAL SCIENCE (THAILAND) CO LTD | J40: USD | K40: YES | L40: MSBT250643-2 | M40: 46114 | N40: 46122 | Q40: =O40*P40 -> 0 | R40: 46332 | S40: =IF(R40="","-",TEXT(R40,"mmmmyy")) -> November26 | T40: Unpaid
A41: 261001TCBG00017 | B41: IDBI | C41: 46157 | D41: 5600000384 | E41: 261001FLCU00022 | F41: 261001FIBN00070 | G41: 46056 | H41: 0.1 | I41: FIRST MATERIAL SCIENCE (THAILAND) CO LTD | J41: USD | K41: YES | L41: MSBT250643-1 | M41: 46114 | N41: 46122 | Q41: =O41*P41 -> 0 | R41: 46332 | S41: =IF(R41="","-",TEXT(R41,"mmmmyy")) -> November26 | T41: Unpaid
A42: 2035BBC26T001163 | B42: BOI | C42: 46157 | D42: 5600000409 | E42: 2035FLCDA260030 | F42: 2035FBRLC260048 | G42: 46099 | H42: 0.1 | I42: GUANGXI CSG NEW ENERGY MATERIAL TECHNOLOGY CO LTD | J42: USD | K42: YES | L42: SFG2602015-5 | M42: 46134 | N42: 46139 | O42: 794430 | P42: 95 | Q42: =O42*P42 -> 75470850 | R42: 46231 | S42: =IF(R42="","-",TEXT(R42,"mmmmyy")) -> July26 | T42: Unpaid | V42: =6941.27+200 -> 7141.27 | W42: =O42+V42 -> 801571.27 | X42: =W42*P42 -> 76149271
A43: 2035BBC26T001163 | B43: BOI | C43: 46157 | D43: 5600000409 | E43: 2035FLCDA260030 | F43: 2035FBRLC260044 | G43: 46099 | H43: 0.1 | I43: GUANGXI CSG NEW ENERGY MATERIAL TECHNOLOGY CO LTD | J43: USD | K43: YES | L43: SFG2602015-4 | M43: 46134 | N43: 46139 | Q43: =O43*P43 -> 0 | R43: 46231 | S43: =IF(R43="","-",TEXT(R43,"mmmmyy")) -> July26 | T43: Unpaid
A44: 2035BBC26T001163 | B44: BOI | C44: 46157 | D44: 5600000409 | E44: 2035FLCDA260030 | F44: 2035FBRLC260046 | G44: 46099 | H44: 0.1 | I44: GUANGXI CSG NEW ENERGY MATERIAL TECHNOLOGY CO LTD | J44: USD | K44: YES | L44: SFG2602015-1 | M44: 46134 | N44: 46139 | Q44: =O44*P44 -> 0 | R44: 46231 | S44: =IF(R44="","-",TEXT(R44,"mmmmyy")) -> July26 | T44: Unpaid
A45: 2035BBC26T001167 | B45: BOI | C45: 46160 | D45: 5600000440 | E45: 2035FLCDA260034 | F45: 2035FBRLC260040 | G45: 46099 | H45: 0.1 | I45: JIANGSU SULV PRECISION TECHNOLOGY CO LTD | J45: USD | K45: YES | L45: SL-GREW-2026-3-25 | M45: 46133 | N45: 46139 | O45: 456300 | P45: 95 | Q45: =O45*P45 -> 43348500 | R45: 46232 | S45: =IF(R45="","-",TEXT(R45,"mmmmyy")) -> July26 | T45: Unpaid | V45: =3993.84+100 -> 4093.84 | W45: =O45+V45 -> 460393.84 | X45: =W45*P45 -> 43737415
A46: 2035BBC26T001168 | B46: BOI | C46: 46160 | D46: 5600000440 | E46: 2035FLCDA260034 | F46: 2035FBRLC260042 | G46: 46099 | H46: 0.1 | I46: JIANGSU SULV PRECISION TECHNOLOGY CO LTD | J46: USD | K46: YES | L46: SL-GREW-2026-3-30 | M46: 46133 | N46: 46139 | O46: 456300 | P46: 95 | Q46: =O46*P46 -> 43348500 | R46: 46234 | S46: =IF(R46="","-",TEXT(R46,"mmmmyy")) -> July26 | T46: Unpaid | V46: =4100.14+100 -> 4200.14 | W46: =O46+V46 -> 460500.14 | X46: =W46*P46 -> 43747513
A47: 0692626TC0A00015 | B47: SBI | C47: 46162 | D47: 5600000395 | E47: 0692626IM0Y00093 | F47: 0692626US0B00261 | G47: 46108 | H47: 0.1 | I47: ARVEE INTERNATIONAL PTE LTD | J47: USD | K47: YES | L47: HKJTGREW20260207-3 | M47: 46133 | N47: 46135 | O47: 1290358 | P47: 95 | Q47: =O47*P47 -> 122584010 | R47: 46227 | S47: =IF(R47="","-",TEXT(R47,"mmmmyy")) -> July26 | T47: Unpaid | U47: 9647.9012 | W47: =O47+V47 -> 1290358 | X47: =W47*P47 -> 122584010
A48: 2035BBC26T001185 | B48: BOI | C48: 46163 | D48: 5600000409 | E48: 2035FLCDA260030 | F48: 2035FBRLC260045 | G48: 46099 | H48: 0.1 | I48: GUANGXI CSG NEW ENERGY MATERIAL TECHNOLOGY CO LTD | J48: USD | K48: YES | L48: SFG2602015-3 | M48: 46134 | N48: 46139 | O48: 264810 | P48: 95 | Q48: =O48*P48 -> 25156950 | R48: 46237 | S48: =IF(R48="","-",TEXT(R48,"mmmmyy")) -> August26 | T48: Unpaid | V48: =2335.28+120 -> 2455.28 | W48: =O48+V48 -> 267265.28 | X48: =W48*P48 -> 25390202
A49: 2035BBC26T001187 | B49: BOI | C49: 46163 | D49: 5600000409 | E49: 2035FLCDA260030 | F49: 2035FBRLC260047 | G49: 46099 | H49: 0.1 | I49: GUANGXI CSG NEW ENERGY MATERIAL TECHNOLOGY CO LTD | J49: USD | K49: YES | L49: SFG2602015-2 | M49: 46134 | N49: 46139 | O49: 264810 | P49: 95 | Q49: =O49*P49 -> 25156950 | R49: 46237 | S49: =IF(R49="","-",TEXT(R49,"mmmmyy")) -> August26 | T49: Unpaid | V49: =2335.28+120 -> 2455.28 | W49: =O49+V49 -> 267265.28 | X49: =W49*P49 -> 25390202
B50: IDBI | C50: 46164 | D50: 5600000396 | E50: 261001FLCU00073 | F50: 261001FIBN00093 | G50: 46056 | H50: 0.1 | I50: ARVEE INTERNATIONAL PTE LTD | J50: USD | K50: YES | L50: HKJTGREW20260207-4 | M50: 46140 | N50: 46144 | O50: 1291989.4 | P50: 95 | Q50: =O50*P50 -> 1.22739e+08 | R50: 46284 | S50: =IF(R50="","-",TEXT(R50,"mmmmyy")) -> September26 | T50: Unpaid | W50: =O50+V50 -> 1291989.4 | X50: =W50*P50 -> 1.22739e+08
A51: 0692626TC0A00014 | B51: SBI | C51: 46164 | D51: 5600000396 | E51: 0692626IM0Y00088 | F51: 0692626US0B00260 | G51: 46119 | H51: 0.1 | I51: ARVEE INTERNATIONAL PTE LTD | J51: USD | K51: YES | L51: HKJTGREW20260207-5 | M51: 46132 | N51: 46134 | O51: 1291871.4 | P51: 95 | Q51: =O51*P51 -> 1.2272779e+08 | R51: 46229 | S51: =IF(R51="","-",TEXT(R51,"mmmmyy")) -> July26 | T51: Unpaid | V51: 9659.2112 | W51: =O51+V51 -> 1301530.7 | X51: =W51*P51 -> 1.2364541e+08 | Y51: 43630359430 | Z51: 1,21,59,094.09
A52: 2035BBC26T001197 | B52: BOI | C52: 46168 | D52: 5600000416 | E52: 2035FLCDA260022 | F52: 2035FBRLC260041 | G52: 46091 | H52: 0.1 | I52: ZHONGHUAN (HONG KONG) HOLDING LTD | J52: USD | K52: YES | L52: YC-HK-GREW-26001 | M52: 46133 | N52: 46139 | O52: 266112 | P52: 95 | Q52: =O52*P52 -> 25280640 | R52: 46224 | S52: =IF(R52="","-",TEXT(R52,"mmmmyy")) -> July26 | T52: Unpaid | V52: =1858.84+120 -> 1978.84 | W52: =O52+V52 -> 268090.84 | X52: =W52*P52 -> 25468630
A53: 2035BBC26T001194 | B53: BOI | C53: 46168 | D53: 5600000415 | E53: 2035FLCDA260023 | F53: 2035FBRLC260033 | G53: 46091 | H53: 0.1 | I53: GOKIN SOLAR (HONGKONG) COMPANY LIMITED | J53: USD | K53: YES | L53: CI-GREW-20260313 | M53: 46125 | O53: 249984 | P53: 95 | Q53: =O53*P53 -> 23748480 | R53: 46224 | S53: =IF(R53="","-",TEXT(R53,"mmmmyy")) -> July26 | T53: Unpaid | V53: =1746.18+120 -> 1866.18 | W53: =O53+V53 -> 251850.18 | X53: =W53*P53 -> 23925767
A54: 2035BBC26T001195 | B54: BOI | C54: 46168 | D54: 5600000402 | E54: 2035FLCDA260026 | F54: 2035FBRLC260032 | G54: 46094 | H54: 0.1 | I54: SHUANGLIANG INTERNATIONAL(SHANGHAI) CO LTD | J54: USD | K54: YES | L54: W20260201 | M54: 46125 | N54: 46134 | O54: 274176 | P54: 95 | Q54: =O54*P54 -> 26046720 | R54: 46224 | S54: =IF(R54="","-",TEXT(R54,"mmmmyy")) -> July26 | T54: Unpaid | V54: =1915.17+120 -> 2035.17 | W54: =O54+V54 -> 276211.17 | X54: =W54*P54 -> 26240061
A55: 2035BBC26T001202 | B55: BOI | C55: 46171 | D55: 5600000407 | E55: 2035FLCDA260028 | F55: 2035FBRLC260039 | G55: 46099 | H55: 0.1 | I55: FIRST MATERIAL SCIENCE (THAILAND) CO LTD | J55: USD | K55: YES | L55: MSBT260064-1 | M55: 46132 | N55: 46139 | O55: 477332.76 | P55: 95 | Q55: =O55*P55 -> 45346612 | R55: 46227 | S55: =IF(R55="","-",TEXT(R55,"mmmmyy")) -> July26 | T55: Unpaid | V55: =3219.26+120 -> 3339.26 | W55: =O55+V55 -> 480672.02 | X55: =W55*P55 -> 45663842
A56: 2035BBC26T001201 | B56: BOI | C56: 46171 | D56: 5600000419 | E56: 2035FLCDA260042 | F56: 2035FBRLC260038 | G56: 46105 | H56: 0.1 | I56: SHANGHAI HUITIAN NEW MATERIAL CO LTD | J56: USD | K56: YES | L56: HT-GEW-2026021201 | M56: 46132 | N56: 46139 | O56: 282158.4 | P56: 95 | Q56: =O56*P56 -> 26805048 | R56: 46227 | S56: =IF(R56="","-",TEXT(R56,"mmmmyy")) -> July26 | T56: Unpaid | V56: =1902.95+120 -> 2022.95 | W56: =O56+V56 -> 284181.35 | X56: =W56*P56 -> 26997228
A57: 2035BBC26T001200 | B57: BOI | C57: 46171 | D57: 5600000452 | E57: 2035FLCDA260047 | F57: 2035FBRLC260059 | G57: 46114 | H57: 0.1 | I57: JIANGSU SULV PRECISION TECHNOLOGY CO LTD | J57: USD | K57: YES | L57: SL-GREW-2026-4-12 | M57: 46136 | N57: 46146 | O57: 463050 | P57: 95 | Q57: =O57*P57 -> 43989750 | R57: 46244 | S57: =IF(R57="","-",TEXT(R57,"mmmmyy")) -> August26 | T57: Unpaid | V57: =4038.28+120 -> 4158.28 | W57: =O57+V57 -> 467208.28 | X57: =W57*P57 -> 44384787
A58: 261001TCBG00022 | B58: IDBI | C58: 46171 | D58: 5600000384 | E58: 261001FLCU00022 | F58: 261001FIBN00087 | G58: 46056 | H58: 0.1 | I58: FIRST MATERIAL SCIENCE (THAILAND) CO LTD | J58: USD | K58: YES | L58: MSBT250643-4 | M58: 46132 | N58: 46143 | O58: 217058.61 | P58: 95 | Q58: =O58*P58 -> 20620568 | R58: 46349 | S58: =IF(R58="","-",TEXT(R58,"mmmmyy")) -> November26 | T58: Unpaid | V58: 0 | W58: =O58+V58 -> 217058.61 | X58: =W58*P58 -> 20620568
A59: 261001TCBG00024 | B59: IDBI | C59: 46171 | D59: 5600000398 | E59: 261001FLCU00040 | F59: 261001FIBN00081 | G59: 46074 | H59: 0.1 | I59: JIETAI NEW ENERGY TECHNOLOGY (HK) LIMITED | J59: USD | K59: YES | L59: HKJTGREW20260226 -1 /HKJTGREW20260226-2 | M59: 46132 | N59: 46143 | O59: 3730346.2 | P59: 95 | Q59: =O59*P59 -> 3.5438289e+08 | R59: 46351 | S59: =IF(R59="","-",TEXT(R59,"mmmmyy")) -> November26 | T59: Unpaid | V59: 0 | W59: =O59+V59 -> 3730346.2 | X59: =W59*P59 -> 3.5438289e+08
A60: 261001TCBG00026 | B60: IDBI | C60: 46174 | D60: 5600000400 | E60: 261001FLCU00026 | F60: 261001FIBN00082 | G60: 46059 | H60: 0.1 | I60: JIETAI NEW ENERGY TECHNOLOGY (HK) LIMITED | J60: USD | K60: YES | L60: HKJTGREW20260212 | M60: 46132 | N60: 46140 | O60: 2080121.9 | P60: 95 | Q60: =O60*P60 -> 1.9761158e+08 | R60: 46351 | S60: =IF(R60="","-",TEXT(R60,"mmmmyy")) -> November26 | T60: Unpaid | V60: 0 | W60: =O60+V60 -> 2080121.9 | X60: =W60*P60 -> 1.9761158e+08
A61: 2035BBC26T001211 | B61: BOI | C61: 46174 | D61: 5600000438 | E61: 2035FLCDA260027 | F61: 2035FBRLC260036 | G61: 46099 | H61: 0.1 | I61: JIANGYIN TINZE NEW ENERGY TECHNOLOGY CO., LTD | J61: USD | K61: YES | L61: STG2026-0322 /STG2026-0323 | M61: 46128 | N61: 46134 | O61: 500400 | P61: 95 | Q61: =O61*P61 -> 47538000 | R61: 46225 | S61: =IF(R61="","-",TEXT(R61,"mmmmyy")) -> July26 | T61: Unpaid | V61: =3146.88+120 -> 3266.88 | W61: =O61+V61 -> 503666.88 | X61: =W61*P61 -> 47848354
A62: 2035BBC26T001210 | B62: BOI | C62: 46174 | D62: 5600000406 | E62: 2035FLCDA260037 | F62: 2035FBRLC260034 | G62: 46101 | H62: 0.1 | I62: TAICANG JUREN INTERNATIONAL TRADE CO LTD | J62: USD | K62: YES | L62: JRIT20260323003 | M62: 46125 | N62: 46134 | O62: 1207470 | P62: 95 | Q62: =O62*P62 -> 114709650 | R62: 46231 | S62: =IF(R62="","-",TEXT(R62,"mmmmyy")) -> July26 | T62: Unpaid | V62: =8437.16+120 -> 8557.16 | W62: =O62+V62 -> 1216027.2 | X62: =W62*P62 -> 1.1552258e+08
A63: 0692626TC0A00017 | B63: SBI | C63: 46174 | D63: 5600000444 | E63: 0692626IM0Y00070 | F63: 0692626US0B00272 | G63: 46099 | H63: 0.1 | I63: PT BINTAN CELLULAR INDONESIA | J63: USD | K63: YES | L63: BCI26032305 | M63: 46134 | N63: 46141 | O63: 433266.62 | P63: 95 | Q63: =O63*P63 -> 41160329 | R63: 46216 | S63: =IF(R63="","-",TEXT(R63,"mmmmyy")) -> July26 | T63: Unpaid | U63: 2256.1167 | W63: =O63+U63 -> 435522.74 | X63: =W63*P63 -> 41374660 | Y63: 44730457174 | Z63: 4300000
A64: 0692626TC0A00016 | B64: SBI | C64: 46174 | D64: 5600000444 | E64: 0692626IM0Y00070 | F64: 0692626US0B00270 | G64: 46099 | H64: 0.1 | I64: PT BINTAN CELLULAR INDONESIA | J64: USD | K64: YES | L64: BCI26032307 | M64: 46134 | N64: 46141 | O64: 433266.62 | P64: 95 | Q64: =O64*P64 -> 41160329 | R64: 46216 | S64: =IF(R64="","-",TEXT(R64,"mmmmyy")) -> July26 | T64: Unpaid | U64: 2256.1167 | W64: =O64+V64 -> 433266.62 | X64: =W64*P64 -> 41160329 | Y64: 44730457174 | Z64: 4300000
A65: 0692626TC0A00021 | B65: SBI | C65: 46174 | D65: 5600000444 | E65: 0692626IM0Y00070 | F65: 0692626US0B00271 | G65: 46099 | H65: 0.1 | I65: PT BINTAN CELLULAR INDONESIA | J65: USD | K65: YES | L65: BCI26032306 | M65: 46134 | N65: 46141 | O65: 361972.8 | P65: 95 | Q65: =O65*P65 -> 34387416 | R65: 46216 | S65: =IF(R65="","-",TEXT(R65,"mmmmyy")) -> July26 | T65: Unpaid | U65: 1884.8734 | W65: =O65+V65 -> 361972.8 | X65: =W65*P65 -> 34387416 | Y65: 44730457174 | Z65: 3500000
A66: 0692626TC0A00018 | B66: SBI | C66: 46174 | D66: 5600000452 | E66: 0692626IM0Y00085 | F66: 0692626US0B00284 | G66: 46116 | H66: 0.1 | I66: JIANGSU SULV PRECISION TECHNOLOGY CO LTD | J66: USD | K66: YES | L66: SL-GREW-2026-4-10 | M66: 46144 | N66: 46149 | O66: 463050 | P66: 95 | Q66: =O66*P66 -> 43989750 | R66: 46231 | S66: =IF(R66="","-",TEXT(R66,"mmmmyy")) -> July26 | T66: Unpaid | U66: 3214.9401 | W66: =O66+V66 -> 463050 | X66: =W66*P66 -> 43989750 | Y66: 44730457174 | Z66: 4440000
A67: 0692626TC0A00019 | B67: SBI | C67: 46174 | D67: 5600000452 | E67: 0692626IM0Y00085 | F67: 0692626US0B00285 | G67: 46116 | H67: 0.1 | I67: JIANGSU SULV PRECISION TECHNOLOGY CO LTD | J67: USD | K67: YES | L67: SL-GREW-2026-4-11 | M67: 46144 | N67: 46149 | O67: 463050 | P67: 95 | Q67: =O67*P67 -> 43989750 | R67: 46231 | S67: =IF(R67="","-",TEXT(R67,"mmmmyy")) -> July26 | T67: Unpaid | U67: 3214.9401 | W67: =O67+V67 -> 463050 | X67: =W67*P67 -> 43989750 | Y67: 44730457174 | Z67: 4440000
A68: 0692626TC0A00020 | B68: SBI | C68: 46176 | D68: 5600000433 | E68: 0692626IM0Y00100 | F68: 0692626US0B00278 | G68: 46130 | H68: 0.1 | I68: ARVEE INTERNATIONAL PTE LTD | J68: USD | K68: YES | L68: HKJTGREW20260312-1 | M68: 46140 | N68: 46143 | O68: 1356957.4 | P68: 95 | Q68: =O68*P68 -> 1.2891095e+08 | R68: 46235 | S68: =IF(R68="","-",TEXT(R68,"mmmmyy")) -> August26 | T68: Unpaid | U68: 10049.397 | W68: =O68+V68 -> 1356957.4 | X68: =W68*P68 -> 1.2891095e+08 | Y68: 44730457174 | Z68: 1,30,00,000.00
B69: IDBI | C69: 46177 | D69: 5600000384 | E69: 261001FLCU00022 | F69: 261001FIBN00086 | G69: 46056 | H69: 0.1 | I69: FIRST MATERIAL SCIENCE (THAILAND) CO LTD | J69: USD | K69: YES | L69: MSBT250643-5 | M69: 46132 | N69: 46143 | O69: 93025.12 | P69: 95 | Q69: =O69*P69 -> 8837386.4 | R69: 46357 | S69: =IF(R69="","-",TEXT(R69,"mmmmyy")) -> December26 | T69: Unpaid | W69: =O69+V69 -> 93025.12 | X69: =W69*P69 -> 8837386.4
A70: 2035BBC26T001216 | B70: BOI | C70: 46177 | D70: 5600000407 | E70: 2035FLCDA260028 | F70: 2035FBRLC260051 | G70: 46099 | H70: 0.1 | I70: FIRST MATERIAL SCIENCE (THAILAND) CO LTD | J70: USD | K70: YES | L70: MSBT260064-2 | M70: 46135 | N70: 46143 | O70: 417666.17 | P70: 95 | Q70: =O70*P70 -> 39678286 | R70: 46234 | S70: =IF(R70="","-",TEXT(R70,"mmmmyy")) -> July26 | T70: Unpaid | W70: =O70+V70 -> 417666.17 | X70: =W70*P70 -> 39678286

Sheet Day wise
A1: TOTAL ALL BANK LC DATY WISE
A2: DATE | B2: LC OPENING BALANCE | C2: LC OPENED | D2: LC CLOSED | E2: LC OUTSTANDING
A3: 46111 | B3: =9255352769.85+79677082.92 -> 9.3350299e+09 | D3: 0 | E3: =B3+C3-D3 -> 9.3350299e+09
A4: =A3+1 -> 46112 | B4: =E3 -> 9.3350299e+09 | C4: =SUMIFS('LC-Final List'!$M:$M,'LC-Final List'!$D:$D,'Day wise'!A4,'LC-Final List'!$F:$F,"<>100%") -> 0 | D4: =SUMIFS('LC-Final List'!$M:$M,'LC-Final List'!$AG:$AG,'Day wise'!A4,'LC-Final List'!$F:$F,"<>100%") -> 0 | E4: =B4+C4-D4 -> 9.3350299e+09
A5: =A4+1 -> 46113 | B5: =E4 -> 9.3350299e+09 | C5: =SUMIFS('LC-Final List'!$M:$M,'LC-Final List'!$D:$D,'Day wise'!A5,'LC-Final List'!$F:$F,"<>100%") -> 0 | D5: =SUMIFS('LC-Final List'!$M:$M,'LC-Final List'!$AG:$AG,'Day wise'!A5,'LC-Final List'!$F:$F,"<>100%") -> 0 | E5: =B5+C5-D5 -> 9.3350299e+09
A6: =A5+1 -> 46114 | B6: =E5 -> 9.3350299e+09 | C6: =SUMIFS('LC-Final List'!$M:$M,'LC-Final List'!$D:$D,'Day wise'!A6,'LC-Final List'!$F:$F,"<>100%") -> 1.8698839e+08 | D6: =SUMIFS('LC-Final List'!$M:$M,'LC-Final List'!$AG:$AG,'Day wise'!A6,'LC-Final List'!$F:$F,"<>100%") -> 57926653 | E6: =B6+C6-D6 -> 9.4640916e+09
A7: =A6+1 -> 46115 | B7: =E6 -> 9.4640916e+09 | C7: =SUMIFS('LC-Final List'!$M:$M,'LC-Final List'!$D:$D,'Day wise'!A7,'LC-Final List'!$F:$F,"<>100%") -> 0 | D7: =SUMIFS('LC-Final List'!$M:$M,'LC-Final List'!$AG:$AG,'Day wise'!A7,'LC-Final List'!$F:$F,"<>100%") -> 0 | E7: =B7+C7-D7 -> 9.4640916e+09
A8: =A7+1 -> 46116 | B8: =E7 -> 9.4640916e+09 | C8: =SUMIFS('LC-Final List'!$M:$M,'LC-Final List'!$D:$D,'Day wise'!A8,'LC-Final List'!$F:$F,"<>100%") -> 88905600 | D8: =SUMIFS('LC-Final List'!$M:$M,'LC-Final List'!$AG:$AG,'Day wise'!A8,'LC-Final List'!$F:$F,"<>100%") -> 0 | E8: =B8+C8-D8 -> 9.5529972e+09
A9: =A8+1 -> 46117 | B9: =E8 -> 9.5529972e+09 | C9: =SUMIFS('LC-Final List'!$M:$M,'LC-Final List'!$D:$D,'Day wise'!A9,'LC-Final List'!$F:$F,"<>100%") -> 0 | D9: =SUMIFS('LC-Final List'!$M:$M,'LC-Final List'!$AG:$AG,'Day wise'!A9,'LC-Final List'!$F:$F,"<>100%") -> 0 | E9: =B9+C9-D9 -> 9.5529972e+09
A10: =A9+1 -> 46118 | B10: =E9 -> 9.5529972e+09 | C10: =SUMIFS('LC-Final List'!$M:$M,'LC-Final List'!$D:$D,'Day wise'!A10,'LC-Final List'!$F:$F,"<>100%") -> 2.7842941e+08 | D10: =SUMIFS('LC-Final List'!$M:$M,'LC-Final List'!$AG:$AG,'Day wise'!A10,'LC-Final List'!$F:$F,"<>100%") -> 3.2890061e+08 | E10: =B10+C10-D10 -> 9.502526e+09
A11: =A10+1 -> 46119 | B11: =E10 -> 9.502526e+09 | C11: =SUMIFS('LC-Final List'!$M:$M,'LC-Final List'!$D:$D,'Day wise'!A11,'LC-Final List'!$F:$F,"<>100%") -> 2.9761738e+08 | D11: =SUMIFS('LC-Final List'!$M:$M,'LC-Final List'!$AG:$AG,'Day wise'!A11,'LC-Final List'!$F:$F,"<>100%") -> 0 | E11: =B11+C11-D11 -> 9.8001434e+09
A12: =A11+1 -> 46120 | B12: =E11 -> 9.8001434e+09 | C12: =SUMIFS('LC-Final List'!$M:$M,'LC-Final List'!$D:$D,'Day wise'!A12,'LC-Final List'!$F:$F,"<>100%") -> 1.224927e+08 | D12: =SUMIFS('LC-Final List'!$M:$M,'LC-Final List'!$AG:$AG,'Day wise'!A12,'LC-Final List'!$F:$F,"<>100%") -> 0 | E12: =B12+C12-D12 -> 9.9226361e+09
A13: =A12+1 -> 46121 | B13: =E12 -> 9.9226361e+09 | C13: =SUMIFS('LC-Final List'!$M:$M,'LC-Final List'!$D:$D,'Day wise'!A13,'LC-Final List'!$F:$F,"<>100%") -> 0 | D13: =SUMIFS('LC-Final List'!$M:$M,'LC-Final List'!$AG:$AG,'Day wise'!A13,'LC-Final List'!$F:$F,"<>100%") -> 0 | E13: =B13+C13-D13 -> 9.9226361e+09
A14: =A13+1 -> 46122 | B14: =E13 -> 9.9226361e+09 | C14: =SUMIFS('LC-Final List'!$M:$M,'LC-Final List'!$D:$D,'Day wise'!A14,'LC-Final List'!$F:$F,"<>100%") -> 0 | D14: =SUMIFS('LC-Final List'!$M:$M,'LC-Final List'!$AG:$AG,'Day wise'!A14,'LC-Final List'!$F:$F,"<>100%") -> 1.9162409e+08 | E14: =B14+C14-D14 -> 9.731012e+09
A15: =A14+1 -> 46123 | B15: =E14 -> 9.731012e+09 | C15: =SUMIFS('LC-Final List'!$M:$M,'LC-Final List'!$D:$D,'Day wise'!A15,'LC-Final List'!$F:$F,"<>100%") -> 0 | D15: =SUMIFS('LC-Final List'!$M:$M,'LC-Final List'!$AG:$AG,'Day wise'!A15,'LC-Final List'!$F:$F,"<>100%") -> 0 | E15: =B15+C15-D15 -> 9.731012e+09
... A52: =A51+1 -> 46160 | B52: =E51 -> 7.6689934e+09 | C52: =SUMIFS('LC-Final List'!$M:$M,'LC-Final List'!$D:$D,'Day wise'!A52,'LC-Final List'!$F:$F,"<>100%") -> 0 | D52: =SUMIFS('LC-Final List'!$M:$M,'LC-Final List'!$AG:$AG,'Day wise'!A52,'LC-Final List'!$F:$F,"<>100%") -> 5.9726798e+08 | E52: =B52+C52-D52 -> 7.0717254e+09

Sheet LC-Final List
A1: Sr No | B1: PO NO | C1: LC no. | D1: LC Op. Date | E1: Bank Name | F1: Margin | G1: Supplier Name | H1: Currency | I1: LC Amt without Tolerance | J1: Tolerance Amt /Reduction Amt | K1: Final LC Amt (in FC) | L1: RATE | M1: LC Amt (in INR) | N1: Type | O1: USANCE NO OF DAYS | P1: DOCUMENTS RECEIVED | Q1: Bill Invoice No | R1: Bill Lodge date | S1: Bill Acceptance date | T1: Shipment Date for LC due date | U1: BOE Bill Amt (in FC) | V1: Pending BOE Amt (in FC) | W1: BOE Bill Amt (in INR) | X1: Pending BOE Amt (in INR) | Y1: LC Payment Due Date | Z1: Limit Available date | AA1: LC Limit Available | AB1: Material Receipt Date | AC1: LC Payment Due Month | AD1: BOE Status/LC OUTSTANDING | AE1: Payment Status | AF1: BOE Status | AG1: LC Close date | AH1: LC Status | AI1: SBLC Status | AJ1: FD Number | AK1: Margin FD Made | AL1: LC SHIPMENT DATE | AM1: LC EXPIRY DATE | AN1: Bill of Entry No. | AO1: Date of Bill of Entry Submitted to Bank | AP1: Product Name
A2: 191 | B2: 5600000355 | C2: 0692625IM0Y00380 | D2: 46009 | E2: SBI | F2: 0.1 | G2: JIETAI NEW ENERGY TECHNOLOGY (HK) LIMITED | H2: USD | I2: 1870000 | J2: 526966 | K2: =I2-J2 -> 1343034 | L2: 95.12 | M2: =K2*L2 -> 1.2774939e+08 | N2: Raw Material | O2: 60 | P2: YES | Q2: HKCE-GREW-20260210 | R2: 46084 | S2: 46086 | T2: 46067 | U2: 1333841 | V2: =K2-U2 -> 9192.96 | W2: =U2*L2 -> 1.2687496e+08 | X2: =V2*L2 -> 874434.36 | Y2: 46127 | Z2: =Y2+2 -> 46129 | AA2: =M2 -> 1.2774939e+08 | AB2: 46100 | AC2: =IF(Y2="","-",TEXT(Y2,"mmmmyy")) -> April26 | AD2: BOE Received and Paid | AE2: Paid | AF2: Received | AG2: 46127 | AH2: Closed | AJ2: 44321009525 | AK2: 10000000 | AL2: 46073 | AM2: 46101 | AN2: 7833669 | AO2: 46127 | AP2: SOLAR CELLS
B3: 5600000355 | C3: 0692625IM0Y00380 | D3: 46009 | E3: SBI | F3: 0.1 | G3: JIETAI NEW ENERGY TECHNOLOGY (HK) LIMITED | H3: USD | I3: 0 | J3: 0 | K3: =J3+I3 -> 0 | L3: 92.42 | M3: =K3*L3 -> 0 | N3: Raw Material | O3: 60 | P3: CANCELLED | U3: 9192.96 | V3: =K3-U3 -> -9192.96 | W3: =U3*L3 -> 849613.36 | X3: =V3*L3 -> -849613.36 | Y3: 46127 | AA3: =M3 -> 0 | AC3: =IF(Y3="","-",TEXT(Y3,"mmmmyy")) -> April26 | AD3: LC Cancelled | AE3: Paid | AF3: Cancelled | AG3: 46127 | AH3: Closed | AJ3: 44730457174 | AK3: 7050000 | AL3: 46073 | AM3: 46101 | AP3: SOLAR CELLS
A4: 192 | B4: 5600000355 | C4: 0692625IM0Y00379 | D4: 46009 | E4: SBI | F4: 0.1 | G4: JIETAI NEW ENERGY TECHNOLOGY (HK) LIMITED | H4: USD | I4: 1343034 | J4: 0 | K4: =J4+I4 -> 1343034 | L4: 95.12 | M4: =K4*L4 -> 1.2774939e+08 | N4: Raw Material | O4: 60 | P4: YES | Q4: HKCE-GREW-20260203-2 | R4: 46086 | S4: 46092 | T4: 46053 | U4: 1339478.9 | V4: =K4-U4 -> 3555.09 | W4: =U4*L4 -> 1.2741123e+08 | X4: =V4*L4 -> 338160.16 | Y4: 46125 | Z4: =Y4+2 -> 46127 | AA4: =M4 -> 1.2774939e+08 | AB4: 46097 | AC4: =IF(Y4="","-",TEXT(Y4,"mmmmyy")) -> April26 | AD4: BOE Received and Paid | AE4: Paid | AF4: Received | AG4: 46125 | AH4: Closed | AJ4: 43630359430 | AK4: 10900000 | AL4: 46073 | AM4: 46101 | AN4: 7972021 | AO4: 46125 | AP4: SOLAR CELLS
B5: 5600000355 | C5: 0692625IM0Y00379 | D5: 46009 | E5: SBI | F5: 0.1 | G5: JIETAI NEW ENERGY TECHNOLOGY (HK) LIMITED | H5: USD | I5: 0 | J5: 0 | K5: =J5+I5 -> 0 | L5: 95.12 | M5: =K5*L5 -> 0 | N5: Raw Material | O5: 60 | P5: CANCELLED | U5: 3555.09 | V5: =K5-U5 -> -3555.09 | W5: =U5*L5 -> 338160.16 | X5: =V5*L5 -> -338160.16 | Y5: 46125 | AA5: =M5 -> 0 | AC5: =IF(Y5="","-",TEXT(Y5,"mmmmyy")) -> April26 | AD5: LC Cancelled | AE5: Paid | AF5: Cancelled | AG5: 46125 | AH5: Closed | AJ5: 43607525170 | AK5: 6150000 | AL5: 46073 | AM5: 46101 | AP5: SOLAR CELLS
A6: 193 | B6: 5600000355/388 | C6: 0692625IM0Y00377 | D6: 46009 | E6: SBI | F6: 0.1 | G6: JIETAI NEW ENERGY TECHNOLOGY (HK) LIMITED | H6: USD | I6: 2014551 | J6: 0 | K6: =J6+I6 -> 2014551 | L6: 95.12 | M6: =K6*L6 -> 1.9162409e+08 | N6: Raw Material | O6: 60 | P6: YES | Q6: HKCE-GREW-20260205-1/2/3 ,& HKCE-GREW-20260209-1/2/3/4/5/6 | R6: 46087 | S6: 46092 | T6: 46053 | U6: 2007440.8 | V6: =K6-U6 -> 7110.18 | W6: =U6*L6 -> 1.9094777e+08 | X6: =V6*L6 -> 676320.32 | Y6: 46122 | Z6: =Y6+2 -> 46124 | AA6: =M6 -> 1.9162409e+08 | AB6: 46098 | AC6: =IF(Y6="","-",TEXT(Y6,"mmmmyy")) -> April26 | AD6: BOE Received and Paid | AE6: Paid | AF6: Received | AG6: 46122 | AH6: Closed | AJ6: 44730457174 | AK6: 17050000 | AL6: 46073 | AM6: 46111 | AN6: 7466829 / 7457784 /7476535 /7606483 /7605503 /7607504 / 7607501 / 7601470 /7601488 | AO6: 46122 | AP6: SOLAR CELLS
B7: 5600000355/388 | C7: 0692625IM0Y00377 | D7: 46009 | E7: SBI | F7: 0.1 | G7: JIETAI NEW ENERGY TECHNOLOGY (HK) LIMITED | H7: USD | I7: 0 | J7: 0 | K7: =J7+I7 -> 0 | L7: 95.12 | M7: =K7*L7 -> 0 | N7: Raw Material | O7: 60 | P7: CANCELLED | U7: 7110.18 | V7: =K7-U7 -> -7110.18 | W7: =U7*L7 -> 676320.32 | X7: =V7*L7 -> -676320.32 | Y7: 46122 | Z7: =Y7+2 -> 46124 | AA7: =M7 -> 0 | AC7: =IF(Y7="","-",TEXT(Y7,"mmmmyy")) -> April26 | AD7: LC Cancelled | AE7: Paid | AF7: Cancelled | AG7: 46122 | AH7: Closed | AJ7: 44730457174 | AK7: 17050000 | AL7: 46073 | AM7: 46111 | AP7: SOLAR CELLS
A8: 195 | B8: 5600000355/388 | C8: 0692625IM0Y00378 | D8: 46010 | E8: SBI | F8: 0.1 | G8: JIETAI NEW ENERGY TECHNOLOGY (HK) LIMITED | H8: USD | I8: 1343034 | J8: 0 | K8: =J8+I8 -> 1343034 | L8: 95.12 | M8: =K8*L8 -> 1.2774939e+08 | N8: Raw Material | O8: 60 | P8: YES | Q8: HKCE-GREW-20260203-1 | R8: 46086 | S8: 46094 | T8: 46063 | U8: 1339909.8 | V8: =K8-U8 -> 3124.17 | W8: =U8*L8 -> 1.2745222e+08 | X8: =V8*L8 -> 297171.05 | Y8: 46125 | Z8: =Y8+2 -> 46127 | AA8: =M8 -> 1.2774939e+08 | AB8: 46097 | AC8: =IF(Y8="","-",TEXT(Y8,"mmmmyy")) -> April26 | AD8: BOE Received and Paid | AE8: Paid | AF8: Received | AG8: 46125 | AH8: Closed | AL8: 46073 | AM8: 46101 | AN8: 7972143 | AO8: 46125 | AP8: SOLAR CELLS
B9: 5600000355/388 | C9: 0692625IM0Y00378 | D9: 46010 | E9: SBI | F9: 0.1 | G9: JIETAI NEW ENERGY TECHNOLOGY (HK) LIMITED | H9: USD | I9: 0 | J9: 0 | K9: =J9+I9 -> 0 | L9: 95.12 | M9: =K9*L9 -> 0 | N9: Raw Material | O9: 60 | P9: CANCELLED | U9: 3124.17 | V9: =K9-U9 -> -3124.17 | W9: =U9*L9 -> 297171.05 | X9: =V9*L9 -> -297171.05 | Y9: 46125 | Z9: =Y9+2 -> 46127 | AA9: =M9 -> 0 | AC9: =IF(Y9="","-",TEXT(Y9,"mmmmyy")) -> April26 | AD9: LC Cancelled | AE9: Paid | AF9: Cancelled | AG9: 46125 | AH9: Closed | AL9: 46073 | AM9: 46101 | AP9: SOLAR CELLS
A10: 197 | B10: 5600000351 | C10: 0692625IM0Y00381 | D10: 46011 | E10: SBI | F10: 0.1 | G10: FIRST MATERIAL SCIENCE (THAILAND) CO LTD | H10: USD | I10: 447499.47 | J10: 0 | K10: =J10+I10 -> 447499.47 | L10: 95.12 | M10: =K10*L10 -> 42566150 | N10: Raw Material | O10: 60 | P10: YES | Q10: MSBT250577-1 | R10: 46051 | S10: 46058 | T10: 46037 | U10: 149166.49 | V10: =K10-U10 -> 298332.98 | W10: =U10*L10 -> 14188717 | X10: =V10*L10 -> 28377433 | Y10: =T10+O10 -> 46097 | AB10: 46092 | AC10: =IF(Y10="","-",TEXT(Y10,"mmmmyy")) -> March26 | AD10: BOE Received and Paid | AE10: Paid | AF10: Received | AG10: 46127 | AH10: Closed | AL10: 46053 | AM10: 46074 | AN10: 7970293 | AO10: 46097 | AP10: EVA FILM
B11: 5600000351 | C11: 0692625IM0Y00381 | D11: 46011 | E11: SBI | F11: 0.1 | G11: FIRST MATERIAL SCIENCE (THAILAND) CO LTD | H11: USD | I11: 0 | J11: 0 | K11: =J11+I11 -> 0 | L11: 95.12 | M11: =K11*L11 -> 0 | N11: Raw Material | O11: 60 | P11: YES | Q11: MSBT250577-2 | R11: 46084 | S11: 46092 | T11: 46066 | U11: 298332.98 | V11: =K11-U11 -> -298332.98 | W11: =U11*L11 -> 28377433 | X11: =V11*L11 -> -28377433 | Y11: 46127 | Z11: =Y11+2 -> 46129 | AA11: =M10 -> 42566150 | AB11: 46099 | AC11: =IF(Y11="","-",TEXT(Y11,"mmmmyy")) -> April26 | AD11: BOE Received and Paid | AE11: Paid | AF11: Received | AG11: 46127 | AH11: Closed | AL11: 46053 | AM11: 46074 | AN11: 8017928 | AO11: 46127 | AP11: EVA FILM
A12: 205 | B12: 1400000398 | C12: 0692626IM0Y00002 | D12: 46027 | E12: SBI | F12: 1 | G12: GNBS ECO CO. LTD | H12: USD | I12: 1260000 | J12: 0 | K12: =J12+I12 -> 1260000 | L12: 91.456 | M12: =K12*L12 -> 115234560 | N12: CAPEX | O12: 180 | P12: YES | Q12: GNBS-20260109-02 | R12: 46070 | S12: 46077 | T12: 46053 | U12: 1260000 | V12: =K12-U12 -> 0 | W12: 0 | X12: =V12*L12 -> 0 | Y12: =T12+O12 -> 46233 | AC12: =IF(Y12="","-",TEXT(Y12,"mmmmyy")) -> July26 | AD12: Part/Full BOE received & Unpaid | AE12: Unpaid | AF12: Received | AH12: Open | AJ12: 44794347236 | AK12: 117180000 | AL12: 46053 | AM12: 46081 | AP12: GNBS PLASMA AND WET GAS ABATEMENT SYSTEM
A13: 210 | B13: 5600000341 | C13: 0692626IM0Y00012 | D13: 46031 | E13: SBI | F13: 0.1 | G13: XINYI PV PRODUCTS (ANHUI) HOLDINGSLTD | H13: USD | I13: 608985 | J13: 0 | K13: =J13+I13 -> 608985 | L13: 95.12 | M13: =K13*L13 -> 57926653 | N13: Raw Material | O13: 60 | P13: YES | Q13: 4206010068/70 | R13: 46063 | S13: 46065 | T13: 46046 | U13: 405990 | V13: =K13-U13 -> 202995 | W13: =U13*L13 -> 38617769 | X13: =V13*L13 -> 19308884 | Y13: =T13+O13 -> 46106 | AB13: 46102 | AC13: =IF(Y13="","-",TEXT(Y13,"mmmmyy")) -> March26 | AD13: BOE Received and Paid | AE13: Paid | AF13: Received | AG13: 46114 | AH13: Closed | AJ13: 44730457174 | AL13: 46074 | AN13: 7770706 /8126350 | AO13: 46106 | AP13: GLASS
B14: 5600000341 | C14: 0692626IM0Y00012 | D14: 46031 | E14: SBI | F14: 0.1 | G14: XINYI PV PRODUCTS (ANHUI) HOLDINGSLTD | H14: USD | J14: 0 | K14: =J14+I14 -> 0 | L14: 95.12 | M14: =K14*L14 -> 0 | N14: Raw Material | O14: 60 | P14: YES | Q14: 42026010071/2 | R14: 46070 | S14: 46077 | T14: 46054 | U14: 202995 | V14: =K14-U14 -> -202995 | W14: =U14*L14 -> 19308884 | X14: =V14*L14 -> -19308884 | Y14: 46114 | Z14: =Y14+2 -> 46116 | AA14: =M13 -> 57926653 | AC14: =IF(Y14="","-",TEXT(Y14,"mmmmyy")) -> April26 | AD14: BOE Received and Paid | AE14: Paid | AF14: Received | AG14: 46114 | AH14: Closed | AJ14: 44730457174 | AL14: 46053 | AM14: 46074 | AN14: 8102852 / 8102856 | AO14: 46114 | AP14: GLASS
A15: 211 | B15: 5600000349 | C15: 0692626IM0Y00011 | D15: 46031 | E15: SBI | F15: 0.1 | G15: FIRST MATERIAL SCIENCE (THAILAND) CO LTD | H15: USD | I15: 930251.17 | J15: 0 | K15: =J15+I15 -> 930251.17 | L15: 95.12 | M15: =K15*L15 -> 88485491 | N15: Raw Material | O15: 60 | P15: YES | Q15: MSBT250575-3 | R15: 46086 | S15: 46094 | T15: 46074 | U15: 310083.72 | V15: =K15-U15 -> 620167.45 | W15: =U15*L15 -> 29495163 | X15: =V15*L15 -> 58990328 | Y15: 46134 | AB15: 46107 | AC15: =IF(Y15="","-",TEXT(Y15,"mmmmyy")) -> April26 | AD15: BOE Received and Paid | AE15: Paid | AF15: Received | AG15: 46146 | AH15: Closed | AJ15: 44730457174 | AK15: 8465000 | AL15: 46068 | AM15: 46089 | AN15: 7983882 | AO15: 46134 | AP15: EVA FILM
B16: 5600000349 | C16: 0692626IM0Y00011 | D16: 46031 | E16: SBI | F16: 0.1 | G16: FIRST MATERIAL SCIENCE (THAILAND) CO LTD | H16: USD | I16: 0 | J16: 0 | K16: =J16+I16 -> 0 | L16: 95.12 | M16: =K16*L16 -> 0 | N16: Raw Material | O16: 60 | P16: YES | Q16: MSBT250575-1 | R16: 46084 | S16: 46092 | T16: 46063 | U16: 310083.72 | V16: =K16-U16 -> -310083.72 | W16: =U16*L16 -> 29495163 | X16: =V16*L16 -> -29495163 | Y16: 46125 | AC16: =IF(Y16="","-",TEXT(Y16,"mmmmyy")) -> April26 | AD16: BOE Received and Paid | AE16: Paid | AF16: Received | AG16: 46146 | AH16: Closed | AJ16: 44730457174 | AL16: 46068 | AM16: 46089 | AN16: 7660607 | AO16: 46125 | AP16: EVA FILM
B17: 5600000349 | C17: 0692626IM0Y00011 | D17: 46031 | E17: SBI | F17: 0.1 | G17: FIRST MATERIAL SCIENCE (THAILAND) CO LTD | H17: USD | I17: 0 | J17: 0 | K17: =J17+I17 -> 0 | L17: 95.12 | M17: =K17*L17 -> 0 | N17: Raw Material | O17: 60 | P17: YES | Q17: MSBT250575-2 | R17: 46101 | S17: 46108 | T17: 46086 | U17: 310083.72 | V17: =K17-U17 -> -310083.72 | W17: =U17*L17 -> 29495163 | X17: =V17*L17 -> -29495163 | Y17: 46146 | Z17: =Y17+2 -> 46148 | AA17: =M15 -> 88485491 | AC17: =IF(Y17="","-",TEXT(Y17,"mmmmyy")) -> May26 | AD17: BOE Received and Paid | AE17: Paid | AF17: Received | AG17: 46146 | AH17: Closed | AJ17: 44730457174 | AL17: 46068 | AM17: 46089 | AN17: 8512490 | AO17: 46146 | AP17: EVA FILM
A18: 213 | B18: 5600000349 | C18: 0692626IM0Y00010 | D18: 46034 | E18: SBI | F18: 0.1 | G18: FIRST MATERIAL SCIENCE (THAILAND) CO LTD | H18: USD | I18: 930251.17 | J18: 0 | K18: =J18+I18 -> 930251.17 | L18: 95.12 | M18: =K18*L18 -> 88485491 | N18: Raw Material | O18: 60 | P18: YES | Q18: MSBT250574-1 | R18: 46062 | S18: 46070 | T18: 46050 | U18: 620167.45 | V18: =K18-U18 -> 310083.72 | W18: =U18*L18 -> 58990328 | X18: =V18*L18 -> 29495163 | Y18: 46111 | AC18: =IF(Y18="","-",TEXT(Y18,"mmmmyy")) -> March26 | AD18: BOE Received and Paid | AE18: Paid | AF18: Received | AG18: 46125 | AH18: Closed | AJ18: 44730457174 | AL18: 46068 | AM18: 46089 | AN18: 7382088 | AO18: 46111 | AP18: EVA FILM
B19: 5600000349 | C19: 0692626IM0Y00010 | D19: 46034 | E19: SBI | F19: 0.1 | G19: FIRST MATERIAL SCIENCE (THAILAND) CO LTD | H19: USD | I19: 0 | J19: 0 | K19: =J19+I19 -> 0 | L19: 95.12 | M19: =K19*L19 -> 0 | N19: Raw Material | O19: 60 | P19: YES | Q19: MSBT250574-2 | R19: 46084 | S19: 46092 | T19: 46065 | U19: 155041.86 | V19: =K19-U19 -> -155041.86 | W19: =U19*L19 -> 14747582 | X19: =V19*L19 -> -14747582 | Y19: 46125 | Z19: =Y19+2 -> 46127 | AA19: =M18 -> 88485491 | AC19: =IF(Y19="","-",TEXT(Y19,"mmmmyy")) -> April26 | AD19: BOE Received and Paid | AE19: Paid | AF19: Received | AG19: 46125 | AH19: Closed | AJ19: 44730457174 | AL19: 46068 | AM19: 46089 | AN19: 8069916 | AO19: 46125 | AP19: EVA FILM
B20: 5600000349 | C20: 0692626IM0Y00010 | D20: 46034 | E20: SBI | F20: 0.1 | G20: FIRST MATERIAL SCIENCE (THAILAND) CO LTD | H20: USD | I20: 0 | J20: 0 | K20: =J20+I20 -> 0 | L20: 95.12 | M20: =K20*L20 -> 0 | N20: Raw Material | O20: 60 | P20: YES | Q20: MSBT250574-3 | R20: 46084 | S20: 46092 | T20: 46063 | U20: 155041.86 | V20: =K20-U20 -> -155041.86 | W20: =U20*L20 -> 14747582 | X20: =V20*L20 -> -14747582 | Y20: 46125 | AB20: 46111 | AC20: =IF(Y20="","-",TEXT(Y20,"mmmmyy")) -> April26 | AD20: BOE Received and Paid | AE20: Paid | AF20: Received | AG20: 46125 | AH20: Closed | AJ20: 44730457174 | AL20: 46068 | AM20: 46089 | AN20: 7705857 | AO20: 46125 | AP20: EVA FILM
A21: 214 | B21: 5600000380 | C21: 0692626IM0Y00018 | D21: 46036 | E21: SBI | F21: 0.1 | G21: GUANGXI CSG NEW ENERGY MATERIAL TECHNOLOGY CO LTD | H21: USD | I21: 1283400 | J21: 0 | K21: =J21+I21 -> 1283400 | L21: 95.12 | M21: =K21*L21 -> 122077008 | N21: Raw Material | O21: 45 | P21: YES | Q21: SFG2601009-4 | R21: 46070 | S21: 46077 | T21: 46058 | U21: 256680 | V21: =K21-U21 -> 1026720 | W21: =U21*L21 -> 24415402 | Y21: 46101 | AC21: =IF(Y21="","-",TEXT(Y21,"mmmmyy")) -> March26 | AD21: BOE Received and Paid | AE21: Paid | AF21: Received | AG21: 46125 | AH21: Closed | AJ21: 43183923893 | AL21: 46068 | AM21: 46089 | AN21: 8058471 | AO21: 46101 | AP21: GLASS
B22: 5600000380 | C22: 0692626IM0Y00018 | D22: 46036 | E22: SBI | F22: 0.1 | G22: GUANGXI CSG NEW ENERGY MATERIAL TECHNOLOGY CO LTD | H22: USD | J22: 0 | K22: =J22+I22 -> 0 | L22: 95.12 | M22: =K22*L22 -> 0 | N22: Raw Material | O22: 45 | P22: YES | Q22: SFG2601009-1 | R22: 46070 | S22: 46077 | T22: 46058 | U22: 256680 | V22: =K22-U22 -> -256680 | W22: =U22*L22 -> 24415402 | Y22: 46099 | AC22: =IF(Y22="","-",TEXT(Y22,"mmmmyy")) -> March26 | AD22: BOE Received and Paid | AE22: Paid | AF22: Received | AG22: 46125 | AH22: Closed | AJ22: 43183923893 | AL22: 46068 | AM22: 46089 | AP22: GLASS
B23: 5600000380 | C23: 0692626IM0Y00018 | D23: 46036 | E23: SBI | F23: 0.1 | G23: GUANGXI CSG NEW ENERGY MATERIAL TECHNOLOGY CO LTD | H23: USD | J23: 0 | K23: =J23+I23 -> 0 | L23: 95.12 | M23: =K23*L23 -> 0 | N23: Raw Material | O23: 45 | P23: YES | Q23: SFG2601009-3 | R23: 46085 | S23: 46092 | T23: 46064 | U23: 256680 | V23: =K23-U23 -> -256680 | W23: =U23*L23 -> 24415402 | Y23: 46111 | AC23: =IF(Y23="","-",TEXT(Y23,"mmmmyy")) -> March26 | AD23: BOE Received and Paid | AE23: Paid | AF23: Received | AG23: 46125 | AH23: Closed | AJ23: 43183923893 | AL23: 46068 | AM23: 46089 | AN23: 8128834 | AO23: 46111 | AP23: GLASS
B24: 5600000380 | C24: 0692626IM0Y00018 | D24: 46036 | E24: SBI | F24: 0.1 | G24: GUANGXI CSG NEW ENERGY MATERIAL TECHNOLOGY CO LTD | H24: USD | J24: 0 | K24: =J24+I24 -> 0 | L24: 95.12 | M24: =K24*L24 -> 0 | N24: Raw Material | O24: 45 | P24: YES | Q24: SFG2601009-5 | R24: 46091 | S24: 46097 | T24: 46079 | U24: 256680 | V24: =K24-U24 -> -256680 | W24: =U24*L24 -> 24415402 | Y24: 46125 | Z24: =Y24+2 -> 46127 | AA24: =M21 -> 122077008 | AC24: =IF(Y24="","-",TEXT(Y24,"mmmmyy")) -> April26 | AD24: BOE Received and Paid | AE24: Paid | AF24: Received | AG24: 46125 | AH24: Closed | AJ24: 43183923893 | AL24: 46068 | AM24: 46089 | AN24: 8215860 | AO24: 46125 | AP24: GLASS
B25: 5600000380 | C25: 0692626IM0Y00018 | D25: 46036 | E25: SBI | F25: 0.1 | G25: GUANGXI CSG NEW ENERGY MATERIAL TECHNOLOGY CO LTD | H25: USD | J25: 0 | K25: =J25+I25 -> 0 | L25: 95.12 | M25: =K25*L25 -> 0 | N25: Raw Material | O25: 45 | P25: YES | Q25: SFG2601009-2 | R25: 46091 | S25: 46097 | T25: 46079 | U25: 256680 | V25: =K25-U25 -> -256680 | W25: =U25*L25 -> 24415402 | Y25: 46114 | AC25: =IF(Y25="","-",TEXT(Y25,"mmmmyy")) -> April26 | AD25: BOE Received and Paid | AE25: Paid | AF25: Received | AG25: 46125 | AH25: Closed | AJ25: 43183923893 | AL25: 46068 | AM25: 46089 | AP25: GLASS
A26: 217 | B26: 5600000360 | C26: 0692626IM0Y00025 | D26: 46042 | E26: SBI | F26: 0.1 | G26: TAICANG JUREN INTERNATIONAL TRADE CO LTD | H26: USD | I26: 351900 | J26: 0 | K26: =J26+I26 -> 351900 | L26: 95.12 | M26: =K26*L26 -> 33472728 | N26: Raw Material | O26: 60 | P26: YES | Q26: JRIT20260126001 | R26: 46070 | S26: 46077 | T26: 46057 | U26: 351900 | V26: =K26-U26 -> 0 | W26: =U26*L26 -> 33472728 | Y26: 46118 | Z26: =Y26+2 -> 46120 | AA26: =M26 -> 33472728 | AC26: =IF(Y26="","-",TEXT(Y26,"mmmmyy")) -> April26 | AD26: BOE Received and Paid | AE26: Paid | AF26: Received | AG26: 46118 | AH26: Closed | AJ26: 43607525170 | AK26: 3232000 | AL26: 46063 | AM26: 46089 | AN26: 7764825 | AO26: 46118 | AP26: PV RIBBON BUS BAR
A27: 223 | B27: 5600000361 | C27: 0692626IM0Y00030 | D27: 46050 | E27: SBI | F27: 0.1 | G27: TAICANG JUREN INTERNATIONAL TRADE CO LTD | H27: USD | I27: 1052825 | J27: 0 | K27: =J27+I27 -> 1052825 | L27: 95.12 | M27: =K27*L27 -> 100144714 | N27: Raw Material | O27: 60 | P27: YES | Q27: JRIT20260203009 | R27: 46086 | S27: 46094 | T27: 46066 | U27: 1052825 | V27: =K27-U27 -> 0 | W27: =U27*L27 -> 100144714 | Y27: 46127 | Z27: =Y27+2 -> 46129 | AA27: =M27 -> 100144714 | AC27: =IF(Y27="","-",TEXT(Y27,"mmmmyy")) -> April26 | AD27: BOE Received and Paid | AE27: Paid | AF27: Received | AG27: 46127 | AH27: Closed | AJ27: 44857149620 | AL27: 46063 | AM27: 46084 | AN27: 7931429 | AO27: 46127 | AP27: PV RIBBON BUS BAR
A28: 224 | B28: 5600000394 | C28: 0692626IM0Y00033 | D28: 46050 | E28: SBI | F28: 0.1 | G28: SOLAR SPACE TECHNOLOGY HONG KONG LIMITED | H28: USD | I28: 1230000 | J28: 0 | K28: =J28+I28 -> 1230000 | L28: 95.12 | M28: =K28*L28 -> 116997600 | N28: Raw Material | O28: 60 | P28: YES | Q28: INV2026022011 | R28: 46106 | S28: 46115 | T28: 46078 | U28: 710048.1 | V28: =K28-U28 -> 519951.9 | W28: =U28*L28 -> 67539775 | Y28: 46139 | AB28: 46102 | AC28: =IF(Y28="","-",TEXT(Y28,"mmmmyy")) -> April26 | AD28: BOE Received and Paid | AE28: Paid | AF28: Received | AG28: 46168 | AH28: Closed | AJ28: 43607525170 | AK28: 11530000 | AL28: 46081 | AM28: 46102 | AN28: 7993633 | AO28: 46139 | AP28: SOLAR CELLS
B29: 5600000394 | C29: 0692626IM0Y00033 | D29: 46050 | E29: SBI | F29: 0.1 | G29: SOLAR SPACE TECHNOLOGY HONG KONG LIMITED | H29: USD | I29: 0 | J29: 0 | K29: =J29+I29 -> 0 | L29: 95.12 | M29: =K29*L29 -> 0 | N29: Raw Material | O29: 60 | P29: YES | Q29: INV2026030632 | R29: 46127 | S29: 46133 | T29: 46107 | U29: 519674.72 | V29: =K29-U29 -> -519674.72 | W29: =U29*L29 -> 49431459 | Y29: 46168 | Z29: =Y29+2 -> 46170 | AA29: =M28 -> 116997600 | AC29: =IF(Y29="","-",TEXT(Y29,"mmmmyy")) -> May26 | AD29: BOE Received and Paid | AE29: Paid | AF29: Received | AG29: 46168 | AH29: Closed | AJ29: 43607525170 | AL29: 46081 | AM29: 46102 | AP29: SOLAR CELLS
B30: 5600000394 | C30: 0692626IM0Y00033 | D30: 46050 | E30: SBI | F30: 0.1 | G30: SOLAR SPACE TECHNOLOGY HONG KONG LIMITED | H30: USD | I30: 0 | J30: 0 | K30: =J30+I30 -> 0 | L30: 95.12 | M30: =K30*L30 -> 0 | N30: Raw Material | O30: 60 | P30: CANCELLED | U30: 277.18 | V30: =K30-U30 -> -277.18 | W30: =U30*L30 -> 26365.362 | Y30: 46168 | AA30: =M29 -> 0 | AC30: =IF(Y30="","-",TEXT(Y30,"mmmmyy")) -> May26 | AD30: LC Cancelled | AE30: Paid | AF30: Cancelled | AG30: 46168 | AH30: Closed | AJ30: 43607525170 | AL30: 46081 | AM30: 46102 | AP30: SOLAR CELLS
A31: 228 | B31: 5600000376 | C31: 0692626IM0Y00031 | D31: 46050 | E31: SBI | F31: 0.1 | G31: ZHEJIANG ZHONGHUAN SUNTER PV TECHNOLOGY CO. LTD | H31: USD | I31: 997920 | J31: 0 | K31: =J31+I31 -> 997920 | L31: 95.12 | M31: =K31*L31 -> 94922150 | N31: Raw Material | O31: 60 | P31: YES | Q31: GREW2508A | R31: 46065 | S31: 46070 | T31: 46053 | U31: 399168 | V31: =K31-U31 -> 598752 | W31: =U31*L31 -> 37968860 | Y31: 46114 | AC31: =IF(Y31="","-",TEXT(Y31,"mmmmyy")) -> April26 | AD31: BOE Received and Paid | AE31: Paid | AF31: Received | AG31: 46118 | AH31: Closed | AJ31: 44857149620 | AK31: 9290000 | AL31: 46068 | AM31: 46089 | AN31: 7566638 | AO31: 46114 | AP31: PV - ZH011C-5 SOLDERING
B32: 5600000376 | C32: 0692626IM0Y00031 | D32: 46050 | E32: SBI | F32: 0.1 | G32: ZHEJIANG ZHONGHUAN SUNTER PV TECHNOLOGY CO. LTD | H32: USD | I32: 0 | J32: 0 | K32: =J32+I32 -> 0 | L32: 95.12 | M32: =K32*L32 -> 0 | N32: Raw Material | O32: 60 | P32: YES | Q32: GREW2508B | R32: 46069 | S32: 46077 | T32: 46057 | U32: 598752 | V32: =K32-U32 -> -598752 | W32: =U32*L32 -> 56953290 | Y32: 46118 | Z32: =Y32+2 -> 46120 | AA32: =M31 -> 94922150 | AC32: =IF(Y32="","-",TEXT(Y32,"mmmmyy")) -> April26 | AD32: BOE Received and Paid | AE32: Paid | AF32: Received | AG32: 46118 | AH32: Closed | AJ32: 44857149620 | AL32: 46068 | AM32: 46089 | AN32: 7683760 | AO32: 46118 | AP32: PV - ZH011C-5 SOLDERING
A33: 229 | B33: 5600000384 | C33: 0692626IM0Y00032 | D33: 46051 | E33: SBI | F33: 0.1 | G33: FIRST MATERIAL SCIENCE (THAILAND) CO LTD | H33: USD | I33: 1085293 | J33: 0 | K33: =J33+I33 -> 1085293 | L33: 95.12 | M33: =K33*L33 -> 1.0323307e+08 | N33: Raw Material | O33: 60 | P33: YES | Q33: MSBT250642-2 | R33: 46074 | S33: 46084 | T33: 46063 | U33: 310083.72 | V33: =K33-U33 -> 775209.32 | W33: =U33*L33 -> 29495163 | Y33: 46125 | AC33: =IF(Y33="","-",TEXT(Y33,"mmmmyy")) -> April26 | AD33: BOE Received and Paid | AE33: Paid | AF33: Received | AG33: 46139 | AH33: Closed | AJ33: 43730175696 | AL33: 46091 | AM33: 46112 | AN33: 7660610 | AO33: 46125 | AP33: EVA FILM
B34: 5600000384 | C34: 0692626IM0Y00032 | D34: 46051 | E34: SBI | F34: 0.1 | G34: FIRST MATERIAL SCIENCE (THAILAND) CO LTD | H34: USD | I34: 0 | J34: 0 | K34: =J34+I34 -> 0 | L34: 95.12 | M34: =K34*L34 -> 0 | N34: Raw Material | O34: 60 | P34: YES | Q34: MSBT250642-4 | R34: 46086 | S34: 46094 | T34: 46074 | U34: 310083.72 | V34: =K34-U34 -> -310083.72 | W34: =U34*L34 -> 29495163 | Y34: 46134 | AC34: =IF(Y34="","-",TEXT(Y34,"mmmmyy")) -> April26 | AD34: BOE Received and Paid | AE34: Paid | AF34: Received | AG34: 46139 | AH34: Closed | AJ34: 43607525170 | AL34: 46091 | AM34: 46112 | AN34: 7921474 | AO34: 46134 | AP34: EVA FILM
B35: 5600000384 | C35: 0692626IM0Y00032 | D35: 46051 | E35: SBI | F35: 0.1 | G35: FIRST MATERIAL SCIENCE (THAILAND) CO LTD | H35: USD | I35: 0 | J35: 0 | K35: =J35+I35 -> 0 | L35: 95.12 | M35: =K35*L35 -> 0 | N35: Raw Material | O35: 60 | P35: YES | Q35: MSBT250642-1 | R35: 46084 | S35: 46092 | T35: 46068 | U35: 155041.87 | V35: =K35-U35 -> -155041.87 | W35: =U35*L35 -> 14747583 | Y35: 46128 | AA35: =M34 -> 0 | AC35: =IF(Y35="","-",TEXT(Y35,"mmmmyy")) -> April26 | AD35: BOE Received and Paid | AE35: Paid | AF35: Received | AG35: 46139 | AH35: Closed | AL35: 46091 | AM35: 46112 | AN35: 8104396 | AO35: 46128 | AP35: EVA FILM
B36: 5600000384 | C36: 0692626IM0Y00032 | D36: 46051 | E36: SBI | F36: 0.1 | G36: FIRST MATERIAL SCIENCE (THAILAND) CO LTD | H36: USD | I36: 0 | J36: 0 | K36: =J36+I36 -> 0 | L36: 95.12 | M36: =K36*L36 -> 0 | N36: Raw Material | O36: 60 | P36: YES | Q36: MSBT250642-3 | R36: 46097 | S36: 46101 | T36: 46078 | U36: 310083.73 | V36: =K36-U36 -> -310083.73 | W36: =U36*L36 -> 29495164 | Y36: 46139 | Z36: =Y36+2 -> 46141 | AA36: =M33 -> 1.0323307e+08 | AC36: =IF(Y36="","-",TEXT(Y36,"mmmmyy")) -> April26 | AD36: BOE Received and Paid | AE36: Paid | AF36: Received | AG36: 46139 | AH36: Closed | AJ36: 43607525170 | AK36: 1435000 | AL36: 46091 | AM36: 46112 | AN36: 8048476 | AO36: 46139 | AP36: EVA FILM
A37: 234 | B37: 5600000399 | C37: 0692626IM0Y00039 | D37: 46059 | E37: SBI | F37: 0.1 | G37: JIETAI NEW ENERGY TECHNOLOGY (HK) LIMITED | H37: USD | I37: 4484985.1 | J37: 0 | K37: =J37+I37 -> 4484985.1 | L37: 95.12 | M37: =K37*L37 -> 4.2661178e+08 | N37: Raw Material | O37: 60 | P37: YES | Q37: HKJTGREW20260211-1/2/3/4/5/6/7/8/9/10/11/12 | R37: 46111 | S37: 46119 | T37: 46090 | U37: 4320848.5 | V37: =K37-U37 -> 164136.67 | W37: =U37*L37 -> 4.109991e+08 | X37: =V37*L37 -> 15612680 | Y37: 46160 | AC37: =IF(Y37="","-",TEXT(Y37,"mmmmyy")) -> May26 | AD37: BOE Received and Paid | AE37: Paid | AF37: Received | AG37: 46160 | AH37: Closed | AJ37: 43650012802 | AK37: 12727000 | AL37: 46117 | AM37: 46138 | AP37: SOLAR CELLS
B38: 5600000399 | C38: 0692626IM0Y00039 | D38: 46059 | E38: SBI | F38: 0.1 | G38: JIETAI NEW ENERGY TECHNOLOGY (HK) LIMITED | H38: USD | I38: 0 | J38: 0 | K38: =J38+I38 -> 0 | L38: 95.12 | M38: =K38*L38 -> 0 | N38: Raw Material | O38: 60 | P38: NO | T38: 46117 | U38: 164136.67 | V38: =K38-U38 -> -164136.67 | W38: =U38*L38 -> 15612680 | X38: =V38*L38 -> -15612680 | Y38: 46160 | Z38: =Y38+2 -> 46162 | AA38: =M37 -> 4.2661178e+08 | AC38: =IF(Y38="","-",TEXT(Y38,"mmmmyy")) -> May26 | AD38: BOE Received and Paid | AE38: Paid | AF38: Cancelled | AG38: 46160 | AH38: Cancelled | AJ38: 44361399732 | AK38: 12645000 | AL38: 46117 | AM38: 46138 | AP38: SOLAR CELLS
B39: 5600000399 | C39: 0692626IM0Y00039 | D39: 46059 | E39: SBI | F39: 0.1 | G39: JIETAI NEW ENERGY TECHNOLOGY (HK) LIMITED | H39: USD | I39: 0 | J39: 0 | K39: =J39+I39 -> 0 | L39: 95.12 | M39: =K39*L39 -> 0 | N39: Raw Material | O39: 60 | P39: NO | V39: =K39-U39 -> 0 | W39: =U39*L39 -> 0 | X39: =V39*L39 -> 0 | AA39: =M39 -> 0 | AC39: =IF(Y39="","-",TEXT(Y39,"mmmmyy")) -> - | AD39: BOE Received and Paid | AE39: Paid | AF39: Not Received | AG39: 46160 | AH39: Closed | AJ39: 43730175696 | AK39: 8693000 | AL39: 46117 | AM39: 46138 | AP39: SOLAR CELLS
B40: 5600000399 | C40: 0692626IM0Y00039 | D40: 46059 | E40: SBI | F40: 0.1 | G40: JIETAI NEW ENERGY TECHNOLOGY (HK) LIMITED | H40: USD | I40: 0 | J40: 0 | K40: =J40+I40 -> 0 | L40: 95.12 | M40: =K40*L40 -> 0 | N40: Raw Material | O40: 60 | P40: NO | V40: =K40-U40 -> 0 | W40: =U40*L40 -> 0 | X40: =V40*L40 -> 0 | AA40: =M40 -> 0 | AC40: =IF(Y40="","-",TEXT(Y40,"mmmmyy")) -> - | AD40: BOE Received and Paid | AE40: Paid | AF40: Not Received | AG40: 46160 | AH40: Closed | AJ40: 44416414800 | AK40: 8 | AL40: 46117 | AM40: 46138 | AP40: SOLAR CELLS
B41: 5600000399 | C41: 0692626IM0Y00039 | D41: 46059 | E41: SBI | F41: 0.1 | G41: JIETAI NEW ENERGY TECHNOLOGY (HK) LIMITED | H41: USD | I41: 0 | J41: 0 | K41: =J41+I41 -> 0 | L41: 95.12 | M41: =K41*L41 -> 0 | N41: Raw Material | O41: 60 | P41: NO | V41: =K41-U41 -> 0 | W41: =U41*L41 -> 0 | X41: =V41*L41 -> 0 | AA41: =M41 -> 0 | AC41: =IF(Y41="","-",TEXT(Y41,"mmmmyy")) -> - | AD41: BOE Received and Paid | AE41: Paid | AF41: Not Received | AG41: 46160 | AH41: Closed | AJ41: 44803304283 | AK41: 177000 | AL41: 46117 | AM41: 46138 | AP41: SOLAR CELLS
A42: 236 | B42: 5600000401 | C42: 0692626IM0Y00040 | D42: 46059 | E42: SBI | F42: 0.1 | G42: JIETAI NEW ENERGY TECHNOLOGY (HK) LIMITED | H42: USD | I42: 3737487.6 | J42: 0 | K42: =J42+I42 -> 3737487.6 | L42: 96 | M42: =K42*L42 -> 3.5879881e+08 | N42: Raw Material | O42: 60 | P42: YES | Q42: HKJTGREW20260225-1/2/3/4 | R42: 46106 | S42: 46114 | T42: 46090 | U42: 1428451.9 | V42: =K42-U42 -> 2309035.7 | W42: =U42*L42 -> 1.3713138e+08 | X42: =V42*L42 -> 2.2166743e+08 | Y42: 46150 | AB42: 46099 | AC42: =IF(Y42="","-",TEXT(Y42,"mmmmyy")) -> May26 | AD42: Part/Full BOE received & Unpaid | AE42: Paid | AF42: Received | AH42: Open | AJ42: 43630359430 | AK42: 22339000 | AL42: 46121 | AM42: 46142 | AN42: 8067419 /8067418 /8080855 /8080986 | AO42: 46150 | AP42: SOLAR CELLS
B43: 5600000401 | C43: 0692626IM0Y00040 | D43: 46059 | E43: SBI | F43: 0.1 | G43: JIETAI NEW ENERGY TECHNOLOGY (HK) LIMITED | H43: USD | I43: 0 | J43: 0 | K43: =J43+I43 -> 0 | L43: 96 | M43: =K43*L43 -> 0 | N43: Raw Material | O43: 60 | P43: YES | Q43: HKJTGREW20260225-5/6/7/8/9 | R43: 46133 | S43: 46135 | T43: 46121 | U43: 1436361.7 | V43: =K43-U43 -> -1436361.7 | W43: =U43*L43 -> 1.3789072e+08 | X43: =V43*L43 -> -1.3789072e+08 | Y43: 46182 | Z43: =Y43+2 -> 46184 | AA43: =M42 -> 3.5879881e+08 | AC43: =IF(Y43="","-",TEXT(Y43,"mmmmyy")) -> June26 | AD43: Part/Full BOE received & Unpaid | AE43: Unpaid | AF43: Received | AH43: Open | AJ43: 42371819184 | AK43: 172000 | AL43: 46121 | AM43: 46142 | AP43: SOLAR CELLS
B44: 5600000401 | C44: 0692626IM0Y00040 | D44: 46059 | E44: SBI | F44: 0.1 | G44: JIETAI NEW ENERGY TECHNOLOGY (HK) LIMITED | H44: USD | I44: 0 | J44: 0 | K44: =J44+I44 -> 0 | L44: 96 | M44: =K44*L44 -> 0 | N44: Raw Material | O44: 60 | P44: CANCELLED | U44: 872673.98 | V44: =K44-U44 -> -872673.98 | W44: =U44*L44 -> 83776702 | X44: =V44*L44 -> -83776702 | Y44: 46182 | AA44: =M44 -> 0 | AC44: =IF(Y44="","-",TEXT(Y44,"mmmmyy")) -> June26 | AD44: BOE not received | AE44: Cancelled | AF44: Cancelled | AH44: Open | AJ44: 43649959856 | AK44: 11569000 | AL44: 46121 | AM44: 46142 | AP44: SOLAR CELLS
A45: 238 | B45: 5600000383 | C45: 0692626IM0Y00043 | D45: 46066 | E45: SBI | F45: 0.1 | G45: FIRST MATERIAL SCIENCE (THAILAND) CO LTD | H45: USD | I45: 930251.17 | J45: 0 | K45: =J45+I45 -> 930251.17 | L45: 95.12 | M45: =K45*L45 -> 88485491 | N45: Raw Material | O45: 60 | P45: YES | Q45: MSBT250645-4 | R45: 46118 | S45: 46122 | T45: 46099 | U45: 155041.86 | V45: =K45-U45 -> 775209.31 | W45: =U45*L45 -> 14747582 | Y45: 46160 | AC45: =IF(Y45="","-",TEXT(Y45,"mmmmyy")) -> May26 | AD45: BOE Received and Paid | AE45: Paid | AF45: Received | AG45: 46168 | AH45: Closed | AJ45: 43749450461 | AK45: 5000000 | AL45: 46112 | AM45: 46133 | AP45: EVA FILM
B46: 5600000383 | C46: 0692626IM0Y00043 | D46: 46066 | E46: SBI | F46: 0.1 | G46: FIRST MATERIAL SCIENCE (THAILAND) CO LTD | H46: USD | I46: 0 | J46: 0 | K46: =J46+I46 -> 0 | L46: 95.12 | M46: =K46*L46 -> 0 | N46: Raw Material | O46: 60 | P46: YES | Q46: MSBT250645-2 | R46: 46116 | S46: 46120 | T46: 46099 | U46: 155041.86 | V46: =K46-U46 -> -155041.86 | W46: =U46*L46 -> 14747582 | Y46: 46160 | AC46: =IF(Y46="","-",TEXT(Y46,"mmmmyy")) -> May26 | AD46: BOE Received and Paid | AE46: Paid | AF46: Received | AG46: 46168 | AH46: Closed | AJ46: 43749450461 | AL46: 46112 | AM46: 46133 | AP46: EVA FILM
B47: 5600000383 | C47: 0692626IM0Y00043 | D47: 46066 | E47: SBI | F47: 0.1 | G47: FIRST MATERIAL SCIENCE (THAILAND) CO LTD | H47: USD | I47: 0 | J47: 0 | K47: =J47+I47 -> 0 | L47: 95.12 | M47: =K47*L47 -> 0 | N47: Raw Material | O47: 60 | P47: YES | Q47: MSBT250645-3 | R47: 46116 | S47: 46120 | T47: 46099 | U47: 155041.86 | V47: =K47-U47 -> -155041.86 | W47: =U47*L47 -> 14747582 | Y47: 46160 | AC47: =IF(Y47="","-",TEXT(Y47,"mmmmyy")) -> May26 | AD47: BOE Received and Paid | AE47: Paid | AF47: Received | AG47: 46168 | AH47: Closed | AJ47: 43749450461 | AL47: 46112 | AM47: 46133 | AP47: EVA FILM
B48: 5600000383 | C48: 0692626IM0Y00043 | D48: 46066 | E48: SBI | F48: 0.1 | G48: FIRST MATERIAL SCIENCE (THAILAND) CO LTD | H48: USD | I48: 0 | J48: 0 | K48: =J48+I48 -> 0 | L48: 95.12 | M48: =K48*L48 -> 0 | N48: Raw Material | O48: 60 | P48: YES | Q48: MSBT250645-1 | R48: 46118 | S48: 46122 | T48: 46097 | U48: 155041.86 | V48: =K48-U48 -> -155041.86 | W48: =U48*L48 -> 14747582 | Y48: =T48+O48 -> 46157 | AC48: =IF(Y48="","-",TEXT(Y48,"mmmmyy")) -> May26 | AD48: BOE Received and Paid | AE48: Paid | AF48: Received | AG48: 46168 | AH48: Closed | AJ48: 43749450461 | AL48: 46112 | AM48: 46133 | AP48: EVA FILM
B49: 5600000383 | C49: 0692626IM0Y00043 | D49: 46066 | E49: SBI | F49: 0.1 | G49: FIRST MATERIAL SCIENCE (THAILAND) CO LTD | H49: USD | I49: 0 | J49: 0 | K49: =J49+I49 -> 0 | L49: 95.12 | M49: =K49*L49 -> 0 | N49: Raw Material | O49: 60 | P49: YES | Q49: MSBT250645-5 | R49: 46132 | S49: 46135 | T49: 46107 | U49: 310083.72 | V49: =K49-U49 -> -310083.72 | W49: =U49*L49 -> 29495163 | Y49: 46168 | Z49: =Y49+2 -> 46170 | AA49: =M45 -> 88485491 | AC49: =IF(Y49="","-",TEXT(Y49,"mmmmyy")) -> May26 | AD49: BOE Received and Paid | AE49: Paid | AF49: Received | AG49: 46168 | AH49: Closed | AJ49: 44485511084 | AK49: 3505000 | AL49: 46112 | AM49: 46133 | AP49: EVA FILM
A50: 239 | B50: 5600000387 | C50: 0692626IM0Y00044 | D50: 46066 | E50: SBI | F50: 0.1 | G50: FUTURE ALUMINUM NEW MATERIALS SDN BHD | H50: USD | I50: 588000 | J50: 0 | K50: =J50+I50 -> 588000 | L50: 95.12 | M50: =K50*L50 -> 55930560 | N50: Raw Material | O50: 60 | P50: YES | Q50: FA-GREW2026-02-26 | R50: 46086 | S50: 46094 | T50: 46079 | U50: 588000 | V50: =K50-U50 -> 0 | W50: =U50*L50 -> 55930560 | Y50: 46139 | Z50: =Y50+2 -> 46141 | AA50: =M50 -> 55930560 | AC50: =IF(Y50="","-",TEXT(Y50,"mmmmyy")) -> April26 | AD50: BOE Received and Paid | AE50: Paid | AF50: Received | AG50: 46139 | AH50: Closed | AJ50: 44450034472 | AL50: 46081 | AM50: 46102 | AN50: 7931820 | AO50: 46139 | AP50: AL FRAME
A51: 240 | B51: 5600000371 | C51: 0692626IM0Y00047 | D51: 46069 | E51: SBI | F51: 0.1 | G51: PT GREEN SOLAR ENERGY TUNAS | H51: USD | I51: 310356.25 | J51: 0 | K51: =J51+I51 -> 310356.25 | L51: 95.12 | M51: =K51*L51 -> 29521086 | N51: Raw Material | O51: 60 | P51: YES | Q51: SNP20260210 | R51: 46114 | S51: 46119 | T51: 46093 | U51: 310356.25 | V51: =K51-U51 -> 0 | W51: =U51*L51 -> 29521086 | Y51: 46153 | Z51: =Y51+2 -> 46155 | AA51: =M51 -> 29521086 | AC51: =IF(Y51="","-",TEXT(Y51,"mmmmyy")) -> May26 | AD51: BOE Received and Paid | AE51: Paid | AF51: Received | AG51: 46153 | AH51: Closed | AJ51: 44450034472 | AK51: 2842000 | AL51: 46101 | AM51: 46122 | AP51: SOLAR CELLS
A52: 241 | B52: 5600000413 | C52: 0692626IM0Y00050 | D52: 46070 | E52: SBI | F52: 0.1 | G52: JIETAI NEW ENERGY TECHNOLOGY (HK) LIMITED | H52: USD | I52: 3039498 | J52: 0 | K52: =J52+I52 -> 3039498 | L52: 96 | M52: =K52*L52 -> 291791808 | N52: Raw Material | O52: 60 | P52: YES | Q52: HKJTGREW20260226-3/4 | R52: 46129 | S52: 46133 | T52: 46112 | U52: 2992494 | V52: =K52-U52 -> 47003.98 | W52: =U52*L52 -> 2.8727943e+08 | X52: =V52*L52 -> 4512382.1 | Y52: 46174 | Z52: =Y52+2 -> 46176 | AA52: =M52 -> 291791808 | AC52: =IF(Y52="","-",TEXT(Y52,"mmmmyy")) -> June26 | AD52: BOE Received and Paid | AE52: Paid | AF52: Received | AG52: 46174 | AH52: Closed | AJ52: 43792161126 | AK52: 3381000 | AL52: 46127 | AM52: 46152 | AP52: SOLAR CELLS
B53: 5600000413 | C53: 0692626IM0Y00050 | D53: 46070 | E53: SBI | F53: 0.1 | G53: JIETAI NEW ENERGY TECHNOLOGY (HK) LIMITED | H53: USD | I53: 0 | J53: 0 | K53: =J53+I53 -> 0 | L53: 96 | M53: =K53*L53 -> 0 | N53: Raw Material | O53: 60 | P53: CANCELLED | U53: 47003.98 | V53: =K53-U53 -> -47003.98 | W53: =U53*L53 -> 4512382.1 | X53: =V53*L53 -> -4512382.1 | Y53: 46174 | AA53: =M53 -> 0 | AC53: =IF(Y53="","-",TEXT(Y53,"mmmmyy")) -> June26 | AD53: LC Cancelled | AE53: Paid | AF53: Cancelled | AG53: 46174 | AH53: Closed | AJ53: 44450034472 | AK53: 5390000 | AL53: 46127 | AM53: 46152 | AP53: SOLAR CELLS
B54: 5600000413 | C54: 0692626IM0Y00050 | D54: 46070 | E54: SBI | F54: 0.1 | G54: JIETAI NEW ENERGY TECHNOLOGY (HK) LIMITED | H54: USD | I54: 0 | J54: 0 | K54: =J54+I54 -> 0 | L54: 96 | M54: =K54*L54 -> 0 | N54: Raw Material | O54: 60 | P54: CANCELLED | U54: 0 | V54: =K54-U54 -> 0 | W54: =U54*L54 -> 0 | X54: =V54*L54 -> 0 | Y54: 46174 | AA54: =M54 -> 0 | AC54: =IF(Y54="","-",TEXT(Y54,"mmmmyy")) -> June26 | AD54: LC Cancelled | AE54: Paid | AF54: Cancelled | AG54: 46174 | AH54: Closed | AJ54: 44803304283 | AK54: 19049000 | AL54: 46127 | AM54: 46152 | AP54: SOLAR CELLS
A55: 242 | B55: 5600000414 | C55: 0692626IM0Y00049 | D55: 46070 | E55: SBI | F55: 0.1 | G55: JIETAI NEW ENERGY TECHNOLOGY (HK) LIMITED | H55: USD | I55: 3039498 | J55: 0 | K55: =J55+I55 -> 3039498 | L55: 96 | M55: =K55*L55 -> 291791808 | N55: Raw Material | O55: 60 | P55: YES | Q55: HKJTGREW20260226-5/6 | R55: 46132 | S55: 46135 | T55: 46112 | U55: 2989373.6 | V55: =K55-U55 -> 50124.37 | W55: =U55*L55 -> 2.8697987e+08 | X55: =V55*L55 -> 4811939.5 | Y55: 46174 | Z55: =Y55+2 -> 46176 | AA55: =M55 -> 291791808 | AC55: =IF(Y55="","-",TEXT(Y55,"mmmmyy")) -> June26 | AD55: BOE Received and Paid | AE55: Paid | AF55: Received | AG55: 46174 | AH55: Closed | AJ55: 43607525170 | AK55: 7264000 | AL55: 46127 | AM55: 46152 | AP55: SOLAR CELLS
B56: 5600000414 | C56: 0692626IM0Y00049 | D56: 46070 | E56: SBI | F56: 0.1 | G56: JIETAI NEW ENERGY TECHNOLOGY (HK) LIMITED | H56: USD | I56: 0 | J56: 0 | K56: =J56+I56 -> 0 | L56: 96 | M56: =K56*L56 -> 0 | N56: Raw Material | O56: 60 | P56: CANCELLED | U56: 50124.37 | V56: =K56-U56 -> -50124.37 | W56: =U56*L56 -> 4811939.5 | X56: =V56*L56 -> -4811939.5 | Y56: 46174 | AA56: =M56 -> 0 | AC56: =IF(Y56="","-",TEXT(Y56,"mmmmyy")) -> June26 | AD56: LC Cancelled | AE56: Paid | AF56: Cancelled | AG56: 46174 | AH56: Closed | AJ56: 44325393960 | AK56: 10778000 | AL56: 46127 | AM56: 46152 | AP56: SOLAR CELLS
B57: 5600000414 | C57: 0692626IM0Y00049 | D57: 46070 | E57: SBI | F57: 0.1 | G57: JIETAI NEW ENERGY TECHNOLOGY (HK) LIMITED | H57: USD | I57: 0 | J57: 0 | K57: =J57+I57 -> 0 | L57: 96 | M57: =K57*L57 -> 0 | N57: Raw Material | O57: 60 | P57: CANCELLED | U57: 0 | V57: =K57-U57 -> 0 | W57: =U57*L57 -> 0 | X57: =V57*L57 -> 0 | Y57: 46174 | AA57: =M57 -> 0 | AC57: =IF(Y57="","-",TEXT(Y57,"mmmmyy")) -> June26 | AD57: LC Cancelled | AE57: Paid | AF57: Cancelled | AG57: 46174 | AH57: Closed | AJ57: 44803304283 | AK57: 9778000 | AL57: 46127 | AM57: 46152 | AP57: SOLAR CELLS
A58: 244 | B58: 5600000422 | C58: 0692626IM0Y00053 | D58: 46076 | E58: SBI | F58: 0.1 | G58: PT BINTAN CELLULAR INDONESIA | H58: USD | I58: 6450000 | J58: 0 | K58: =J58+I58 -> 6450000 | L58: 95.12 | M58: =K58*L58 -> 613524000 | N58: Raw Material | O58: 60 | P58: YES | Q58: BCI26022411 | R58: 46101 | S58: 46101 | T58: 46081 | U58: 477999.98 | V58: =K58-U58 -> 5972000 | W58: =U58*L58 -> 45467358 | Y58: 46141 | Z58: =Y58+2 -> 46143 | AA58: =M58 -> 613524000 | AB58: 46093 | AC58: =IF(Y58="","-",TEXT(Y58,"mmmmyy")) -> April26 | AD58: BOE Received and Paid | AE58: Paid | AF58: Received | AG58: 46141 | AH58: Closed | AL58: 46112 | AM58: 46133 | AN58: 7998661 | AO58: 46141 | AP58: SOLAR CELLS
B59: 5600000422 | C59: 0692626IM0Y00053 | D59: 46076 | E59: SBI | F59: 0.1 | G59: PT BINTAN CELLULAR INDONESIA | H59: USD | J59: 0 | K59: =J59+I59 -> 0 | L59: 95.12 | M59: =K59*L59 -> 0 | N59: Raw Material | O59: 60 | P59: YES | Q59: BC126022406 | R59: 46101 | S59: 46105 | T59: 46081 | U59: 746591.73 | V59: =K59-U59 -> -746591.73 | W59: =U59*L59 -> 71015805 | Y59: 46141 | AA59: =M59 -> 0 | AB59: 46093 | AC59: =IF(Y59="","-",TEXT(Y59,"mmmmyy")) -> April26 | AD59: BOE Received and Paid | AE59: Paid | AF59: Received | AG59: 46141 | AH59: Closed | AL59: 46112 | AM59: 46133 | AN59: 7998664 | AO59: 46141 | AP59: SOLAR CELLS
B60: 5600000422 | C60: 0692626IM0Y00053 | D60: 46076 | E60: SBI | F60: 0.1 | G60: PT BINTAN CELLULAR INDONESIA | H60: USD | J60: 0 | K60: =J60+I60 -> 0 | L60: 95.12 | M60: =K60*L60 -> 0 | N60: Raw Material | O60: 60 | P60: YES | Q60: BCI26022410 | R60: 46101 | S60: 46105 | T60: 46081 | U60: 746349.01 | V60: =K60-U60 -> -746349.01 | W60: =U60*L60 -> 70992718 | Y60: 46141 | AA60: =M60 -> 0 | AB60: 46093 | AC60: =IF(Y60="","-",TEXT(Y60,"mmmmyy")) -> April26 | AD60: BOE Received and Paid | AE60: Paid | AF60: Received | AG60: 46141 | AH60: Closed | AL60: 46112 | AM60: 46133 | AN60: 8027729 | AO60: 46141 | AP60: SOLAR CELLS
B61: 5600000422 | C61: 0692626IM0Y00053 | D61: 46076 | E61: SBI | F61: 0.1 | G61: PT BINTAN CELLULAR INDONESIA | H61: USD | J61: 0 | K61: =J61+I61 -> 0 | L61: 95.12 | M61: =K61*L61 -> 0 | N61: Raw Material | O61: 60 | P61: YES | Q61: BCI26022408 | R61: 46101 | S61: 46105 | T61: 46081 | U61: 746591.73 | V61: =K61-U61 -> -746591.73 | W61: =U61*L61 -> 71015805 | Y61: 46141 | AA61: =M61 -> 0 | AB61: 46093 | AC61: =IF(Y61="","-",TEXT(Y61,"mmmmyy")) -> April26 | AD61: BOE Received and Paid | AE61: Paid | AF61: Received | AG61: 46141 | AH61: Closed | AL61: 46112 | AM61: 46133 | AN61: 7967766 | AO61: 46141 | AP61: SOLAR CELLS
B62: 5600000422 | C62: 0692626IM0Y00053 | D62: 46076 | E62: SBI | F62: 0.1 | G62: PT BINTAN CELLULAR INDONESIA | H62: USD | J62: 0 | K62: =J62+I62 -> 0 | L62: 95.12 | M62: =K62*L62 -> 0 | N62: Raw Material | O62: 60 | P62: YES | Q62: BCI26022403 | R62: 46101 | S62: 46101 | T62: 46081 | U62: 746071.61 | V62: =K62-U62 -> -746071.61 | W62: =U62*L62 -> 70966332 | Y62: 46140 | AA62: =M62 -> 0 | AB62: 46095 | AC62: =IF(Y62="","-",TEXT(Y62,"mmmmyy")) -> April26 | AD62: BOE Received and Paid | AE62: Paid | AF62: Received | AG62: 46141 | AH62: Closed | AL62: 46112 | AM62: 46133 | AN62: 7886048 | AO62: 46140 | AP62: SOLAR CELLS
B63: 5600000422 | C63: 0692626IM0Y00053 | D63: 46076 | E63: SBI | F63: 0.1 | G63: PT BINTAN CELLULAR INDONESIA | H63: USD | J63: 0 | K63: =J63+I63 -> 0 | L63: 95.12 | M63: =K63*L63 -> 0 | N63: Raw Material | O63: 60 | P63: YES | Q63: BCI26022407 | R63: 46101 | S63: 46105 | T63: 46081 | U63: 746591.73 | V63: =K63-U63 -> -746591.73 | W63: =U63*L63 -> 71015805 | Y63: 46141 | AA63: =M63 -> 0 | AB63: 46100 | AC63: =IF(Y63="","-",TEXT(Y63,"mmmmyy")) -> April26 | AD63: BOE Received and Paid | AE63: Paid | AF63: Received | AG63: 46141 | AH63: Closed | AL63: 46112 | AM63: 46133 | AN63: 7967237 | AO63: 46141 | AP63: SOLAR CELLS
B64: 5600000422 | C64: 0692626IM0Y00053 | D64: 46076 | E64: SBI | F64: 0.1 | G64: PT BINTAN CELLULAR INDONESIA | H64: USD | J64: 0 | K64: =J64+I64 -> 0 | L64: 95.12 | M64: =K64*L64 -> 0 | N64: Raw Material | O64: 60 | P64: YES | Q64: BCI26022409 | R64: 46101 | S64: 46105 | T64: 46081 | U64: 746591.73 | V64: =K64-U64 -> -746591.73 | W64: =U64*L64 -> 71015805 | Y64: 46141 | AA64: =M64 -> 0 | AB64: 46100 | AC64: =IF(Y64="","-",TEXT(Y64,"mmmmyy")) -> April26 | AD64: BOE Received and Paid | AE64: Paid | AF64: Received | AG64: 46141 | AH64: Closed | AL64: 46112 | AM64: 46133 | AN64: 7931077 | AO64: 46141 | AP64: SOLAR CELLS
B65: 5600000422 | C65: 0692626IM0Y00053 | D65: 46076 | E65: SBI | F65: 0.1 | G65: PT BINTAN CELLULAR INDONESIA | H65: USD | J65: 0 | K65: =J65+I65 -> 0 | L65: 95.12 | M65: =K65*L65 -> 0 | N65: Raw Material | O65: 60 | P65: YES | Q65: BCI26022404 | R65: 46101 | S65: 46101 | T65: 46081 | U65: 746591.73 | V65: =K65-U65 -> -746591.73 | W65: =U65*L65 -> 71015805 | Y65: 46140 | AA65: =M65 -> 0 | AB65: 46097 | AC65: =IF(Y65="","-",TEXT(Y65,"mmmmyy")) -> April26 | AD65: BOE Received and Paid | AE65: Paid | AF65: Received | AG65: 46141 | AH65: Closed | AL65: 46112 | AM65: 46133 | AN65: 7917366 | AO65: 46140 | AP65: SOLAR CELLS
B66: 5600000422 | C66: 0692626IM0Y00053 | D66: 46076 | E66: SBI | F66: 0.1 | G66: PT BINTAN CELLULAR INDONESIA | H66: USD | J66: 0 | K66: =J66+I66 -> 0 | L66: 95.12 | M66: =K66*L66 -> 0 | N66: Raw Material | O66: 60 | P66: YES | Q66: BCI26022405 | R66: 46101 | S66: 46101 | T66: 46081 | U66: 746591.73 | V66: =K66-U66 -> -746591.73 | W66: =U66*L66 -> 71015805 | Y66: 46140 | AB66: 46089 | AC66: =IF(Y66="","-",TEXT(Y66,"mmmmyy")) -> April26 | AD66: BOE Received and Paid | AE66: Paid | AF66: Received | AG66: 46141 | AH66: Closed | AL66: 46112 | AM66: 46133 | AN66: 7915721 | AO66: 46140 | AP66: SOLAR CELLS
A67: 245 | B67: 5600000390 | C67: 0692626IM0Y00054 | D67: 46076 | E67: SBI | F67: 0.1 | G67: ARVEE INTERNATIONAL PTE LTD | H67: USD | I67: 2020311.9 | J67: 0 | K67: =J67+I67 -> 2020311.9 | L67: 95.12 | M67: =K67*L67 -> 1.9217207e+08 | N67: Raw Material | O67: 55 | P67: YES | Q67: IDA20260108A | R67: 46097 | S67: 46106 | T67: 46063 | U67: 2011633.6 | V67: =K67-U67 -> 8678.32 | W67: =U67*L67 -> 1.9134659e+08 | Y67: =T67+O67 -> 46118 | Z67: =Y67+2 -> 46120 | AA67: =M67 -> 1.9217207e+08 | AB67: 46087 | AC67: =IF(Y67="","-",TEXT(Y67,"mmmmyy")) -> April26 | AD67: BOE Received and Paid | AE67: Paid | AF67: Received | AG67: 46118 | AH67: Closed | AL67: 46112 | AM67: 46133 | AN67: 7830736 | AO67: 46118 | AP67: SOLAR CELLS
B68: 5600000390 | C68: 0692626IM0Y00054 | D68: 46076 | E68: SBI | F68: 0.1 | G68: ARVEE INTERNATIONAL PTE LTD | H68: USD | I68: 0 | J68: 0 | K68: =J68+I68 -> 0 | L68: 95.12 | M68: =K68*L68 -> 0 | N68: Raw Material | O68: 55 | P68: CANCELLED | U68: 8678.32 | V68: =K68-U68 -> -8678.32 | W68: =U68*L68 -> 825481.8 | Y68: 46118 | Z68: - | AA68: =M68 -> 0 | AC68: =IF(Y68="","-",TEXT(Y68,"mmmmyy")) -> April26 | AD68: LC Cancelled | AE68: Paid | AF68: Cancelled | AG68: 46118 | AH68: Closed | AL68: 46112 | AM68: 46133 | AP68: SOLAR CELLS
A69: 246 | B69: 5600000387 | C69: 0692626IM0Y00052 | D69: 46078 | E69: SBI | F69: 0.1 | G69: FUTURE ALUMINUM NEW MATERIALS SDN BHD | H69: USD | I69: 588000 | J69: 0 | K69: =J69+I69 -> 588000 | L69: 95.12 | M69: =K69*L69 -> 55930560 | N69: Raw Material | O69: 60 | P69: YES | Q69: FA-GREW2026-03-03 | R69: 46097 | S69: 46101 | T69: 46085 | U69: 588000 | V69: =K69-U69 -> 0 | W69: =U69*L69 -> 55930560 | Y69: 46146 | Z69: =Y69+2 -> 46148 | AA69: =M69 -> 55930560 | AC69: =IF(Y69="","-",TEXT(Y69,"mmmmyy")) -> May26 | AD69: BOE Received and Paid | AE69: Paid | AF69: Received | AG69: 46146 | AH69: Closed | AL69: 46101 | AM69: 46122 | AN69: 8060758 | AO69: 46146 | AP69: AL FRAME
A70: 247 | B70: 5600000407 | C70: 0692626IM0Y00057 | D70: 46078 | E70: SBI | F70: 0.1 | G70: FIRST MATERIAL SCIENCE (THAILAND) CO LTD | H70: USD | I70: 894998.94 | J70: 0 | K70: =J70+I70 -> 894998.94 | L70: 95.12 | M70: =K70*L70 -> 85132299 | N70: Raw Material | O70: 60 | P70: YES | Q70: MSBT260063-1 | R70: 46114 | S70: 46119 | T70: 46099 | U70: 357999.57 | V70: =K70-U70 -> 536999.37 | W70: =U70*L70 -> 34052919 | Y70: 46160 | AC70: =IF(Y70="","-",TEXT(Y70,"mmmmyy")) -> May26 | AD70: BOE Received and Paid | AE70: Paid | AF70: Received | AG70: 46168 | AH70: Closed | AJ70: 44028685576 | AK70: 8225000 | AL70: 46112 | AM70: 46133 | AP70: EVA FILM
B71: 5600000407 | C71: 0692626IM0Y00057 | D71: 46078 | E71: SBI | F71: 0.1 | G71: FIRST MATERIAL SCIENCE (THAILAND) CO LTD | H71: USD | I71: 0 | J71: 0 | K71: =J71+I71 -> 0 | L71: 95.12 | M71: =K71*L71 -> 0 | N71: Raw Material | O71: 60 | P71: YES | Q71: MSBT260063-3 | R71: 46136 | S71: 46147 | T71: 46105 | U71: 387832.87 | V71: =K71-U71 -> -387832.87 | W71: =U71*L71 -> 36890663 | Y71: 46168 | AC71: =IF(Y71="","-",TEXT(Y71,"mmmmyy")) -> May26 | AD71: BOE Received and Paid | AE71: Paid | AF71: Received | AG71: 46168 | AH71: Closed | AL71: 46112 | AM71: 46133 | AP71: EVA FILM
B72: 5600000407 | C72: 0692626IM0Y00057 | D72: 46078 | E72: SBI | F72: 0.1 | G72: FIRST MATERIAL SCIENCE (THAILAND) CO LTD | H72: USD | I72: 0 | J72: 0 | K72: =J72+I72 -> 0 | L72: 95.12 | M72: =K72*L72 -> 0 | N72: Raw Material | O72: 60 | P72: YES | Q72: MSBT260063-2 | R72: 46122 | S72: 46133 | T72: 46105 | U72: 149166.49 | V72: =K72-U72 -> -149166.49 | W72: =U72*L72 -> 14188717 | Y72: 46168 | Z72: =Y72+2 -> 46170 | AA72: =M70 -> 85132299 | AC72: =IF(Y72="","-",TEXT(Y72,"mmmmyy")) -> May26 | AD72: BOE Received and Paid | AE72: Paid | AF72: Received | AG72: 46168 | AH72: Closed | AL72: 46112 | AM72: 46133 | AP72: EVA FILM
A73: 248 | B73: 5600000427 | C73: 0692626IM0Y00058 | D73: 46083 | E73: SBI | F73: 0.1 | G73: JIETAI NEW ENERGY TECHNOLOGY (HK) LIMITED | H73: USD | I73: 3441715.2 | J73: =I73*1% -> 34417.152 | K73: =J73+I73 -> 3476132.4 | L73: 96 | M73: =K73*L73 -> 3.3370871e+08 | N73: Raw Material | O73: 60 | P73: YES | Q73: HKJTGREW20260310-4 | R73: 46132 | S73: 46135 | T73: 46126 | U73: 2068376.1 | V73: =K73-U73 -> 1407756.3 | W73: =U73*L73 -> 1.985641e+08 | X73: =V73*L73 -> 1.351446e+08 | Y73: 46188 | AC73: =IF(Y73="","-",TEXT(Y73,"mmmmyy")) -> June26 | AD73: Part/Full BOE received & Unpaid | AE73: Unpaid | AF73: Received | AH73: Open | AJ73: 44707855866 | AK73: 30000000 | AL73: 46132 | AM73: 46157 | AP73: SOLAR CELLS
B74: 5600000427 | C74: 0692626IM0Y00058 | D74: 46083 | E74: SBI | F74: 0.1 | G74: JIETAI NEW ENERGY TECHNOLOGY (HK) LIMITED | H74: USD | I74: 0 | J74: =I74*1% -> 0 | K74: =J74+I74 -> 0 | L74: 96 | M74: =K74*L74 -> 0 | N74: Raw Material | O74: 60 | P74: YES | Q74: HKJTGREW20260310-5 | R74: 46140 | S74: 46147 | T74: 46130 | U74: 1384612.2 | V74: =K74-U74 -> -1384612.2 | W74: =U74*L74 -> 1.3292277e+08 | X74: =V74*L74 -> -1.3292277e+08 | Y74: 46190 | AC74: =IF(Y74="","-",TEXT(Y74,"mmmmyy")) -> June26 | AD74: Part/Full BOE received & Unpaid | AE74: Unpaid | AF74: Received | AH74: Open | AJ74: 42814707478 | AK74: 1760000 | AL74: 46132 | AM74: 46157 | AP74: SOLAR CELLS
B75: 5600000427 | C75: 0692626IM0Y00058 | D75: 46083 | E75: SBI | F75: 0.1 | G75: JIETAI NEW ENERGY TECHNOLOGY (HK) LIMITED | H75: USD | I75: 0 | J75: =I75*1% -> 0 | K75: =J75+I75 -> 0 | L75: 96 | M75: =K75*L75 -> 0 | N75: Raw Material | O75: 60 | P75: CANCELLED | U75: 23144.08 | V75: =K75-U75 -> -23144.08 | W75: =U75*L75 -> 2221831.7 | X75: =V75*L75 -> -2221831.7 | Y75: 46190 | Z75: =Y75+2 -> 46192 | AA75: =M73 -> 3.3370871e+08 | AC75: =IF(Y75="","-",TEXT(Y75,"mmmmyy")) -> June26 | AD75: BOE not received | AE75: Cancelled | AF75: Cancelled | AH75: Open | AJ75: 42840339454 | AK75: 892000 | AL75: 46132 | AM75: 46157 | AP75: SOLAR CELLS
A76: 249 | B76: 5600000426 | C76: 0692626IM0Y00059 | D76: 46083 | E76: SBI | F76: 0.1 | G76: JIETAI NEW ENERGY TECHNOLOGY (HK) LIMITED | H76: USD | I76: 3441715.2 | J76: =I76*1% -> 34417.152 | K76: =J76+I76 -> 3476132.4 | L76: 96 | M76: =K76*L76 -> 3.3370871e+08 | N76: Raw Material | O76: 60 | P76: YES | Q76: HKJTGREW20260310-1/2 | R76: 46132 | S76: 46135 | T76: 46116 | U76: 2764823.9 | V76: =K76-U76 -> 711308.5 | W76: =U76*L76 -> 2.6542309e+08 | X76: =V76*L76 -> 68285616 | Y76: 46176 | AC76: =IF(Y76="","-",TEXT(Y76,"mmmmyy")) -> June26 | AD76: Part/Full BOE received & Unpaid | AE76: Paid | AF76: Received | AH76: Open | AJ76: 43607525170 | AK76: 1148000 | AL76: 46132 | AM76: 46157 | AP76: SOLAR CELLS
B77: 5600000426 | C77: 0692626IM0Y00059 | D77: 46083 | E77: SBI | F77: 0.1 | G77: JIETAI NEW ENERGY TECHNOLOGY (HK) LIMITED | H77: USD | I77: 0 | J77: =I77*1% -> 0 | K77: =J77+I77 -> 0 | L77: 96 | M77: =K77*L77 -> 0 | N77: Raw Material | O77: 60 | P77: YES | Q77: HKJTGREW20260310-3 | R77: 46132 | S77: 46135 | T77: 46127 | U77: 688293.85 | V77: =K77-U77 -> -688293.85 | W77: =U77*L77 -> 66076210 | X77: =V77*L77 -> -66076210 | Y77: 46188 | Z77: =Y77+2 -> 46190 | AA77: =M76 -> 3.3370871e+08 | AC77: =IF(Y77="","-",TEXT(Y77,"mmmmyy")) -> June26 | AD77: Part/Full BOE received & Unpaid | AE77: Unpaid | AF77: Received | AH77: Open | AJ77: 43792161126 | AK77: 6996000 | AL77: 46132 | AM77: 46157 | AP77: SOLAR CELLS
B78: 5600000426 | C78: 0692626IM0Y00059 | D78: 46083 | E78: SBI | F78: 0.1 | G78: JIETAI NEW ENERGY TECHNOLOGY (HK) LIMITED | H78: USD | I78: 0 | J78: =I78*1% -> 0 | K78: =J78+I78 -> 0 | L78: 96 | M78: =K78*L78 -> 0 | N78: Raw Material | O78: 60 | P78: CANCELLED | U78: 23014.65 | V78: =K78-U78 -> -23014.65 | W78: =U78*L78 -> 2209406.4 | X78: =V78*L78 -> -2209406.4 | Y78: 46188 | AA78: =M77 -> 0 | AC78: =IF(Y78="","-",TEXT(Y78,"mmmmyy")) -> June26 | AD78: BOE not received | AE78: Cancelled | AF78: Cancelled | AH78: Open | AJ78: 44803304283 | AK78: 2316000 | AL78: 46132 | AM78: 46157 | AP78: SOLAR CELLS
A79: 254 | B79: 5600000391 | C79: 0692626IM0Y00063 | D79: 46091 | E79: SBI | F79: 0.1 | G79: ARVEE INTERNATIONAL PTE LTD | H79: USD | I79: 669762.42 | J79: 0 | K79: =J79+I79 -> 669762.42 | L79: 95.12 | M79: =K79*L79 -> 63707801 | N79: Raw Material | O79: 55 | P79: YES | Q79: ID20260108B | R79: 46111 | S79: 46118 | T79: 46081 | U79: 669655.96 | V79: =K79-U79 -> 106.46 | W79: =U79*L79 -> 63697675 | Y79: 46136 | Z79: =Y79+2 -> 46138 | AA79: =M79 -> 63707801 | AC79: =IF(Y79="","-",TEXT(Y79,"mmmmyy")) -> April26 | AD79: BOE Received and Paid | AE79: Paid | AF79: Received | AG79: 46136 | AH79: Closed | AL79: 46096 | AM79: 46117 | AN79: 8248503 | AO79: 46136 | AP79: SOLAR CELLS
B80: 5600000391 | C80: 0692626IM0Y00063 | D80: 46091 | E80: SBI | F80: 0.1 | G80: ARVEE INTERNATIONAL PTE LTD | H80: USD | I80: 0 | J80: 0 | K80: =J80+I80 -> 0 | L80: 95.12 | M80: =K80*L80 -> 0 | N80: Raw Material | O80: 55 | P80: CANCELLED | U80: 106.46 | V80: =K80-U80 -> -106.46 | W80: =U80*L80 -> 10126.475 | Y80: 46136 | AA80: =M80 -> 0 | AC80: =IF(Y80="","-",TEXT(Y80,"mmmmyy")) -> April26 | AD80: LC Cancelled | AE80: Paid | AF80: Cancelled | AG80: 46136 | AH80: Closed | AL80: 46096 | AM80: 46117 | AP80: SOLAR CELLS
A81: 255 | B81: 5600000390 | C81: 0692626IM0Y00064 | D81: 46094 | E81: SBI | F81: 0.1 | G81: ARVEE INTERNATIONAL PTE LTD | H81: USD | I81: 1344018.8 | J81: 0 | K81: =J81+I81 -> 1344018.8 | L81: 95.12 | M81: =K81*L81 -> 1.2784307e+08 | N81: Raw Material | O81: 55 | P81: YES | Q81: ID20260115B-1 | R81: 46118 | S81: 46120 | T81: 46081 | U81: 1344065.6 | V81: =K81-U81 -> -46.78 | W81: =U81*L81 -> 1.2784752e+08 | Y81: 46136 | Z81: =Y81+2 -> 46138 | AA81: =M81 -> 1.2784307e+08 | AB81: 46101 | AC81: =IF(Y81="","-",TEXT(Y81,"mmmmyy")) -> April26 | AD81: BOE Received and Paid | AE81: Paid | AF81: Received | AG81: 46136 | AH81: Closed | AL81: 46096 | AM81: 46117 | AN81: 8112424 | AO81: 46136 | AP81: SOLAR CELLS
A82: 256 | B82: 5600000406 | C82: 0692626IM0Y00066 | D82: 46094 | E82: SBI | F82: 0.1 | G82: TAICANG JUREN INTERNATIONAL TRADE CO LTD | H82: USD | I82: 804980 | J82: 0 | K82: =J82+I82 -> 804980 | L82: 94.9205 | M82: =K82*L82 -> 76409104 | N82: Raw Material | O82: 60 | P82: YES | Q82: JRIT20260318001 | R82: 46118 | S82: 46122 | T82: 46107 | U82: 804980 | V82: =K82-U82 -> 0 | W82: =U82*L82 -> 76409104 | Y82: 46168 | Z82: =Y82+2 -> 46170 | AA82: =M82 -> 76409104 | AC82: =IF(Y82="","-",TEXT(Y82,"mmmmyy")) -> May26 | AD82: BOE Received and Paid | AE82: Paid | AF82: Received | AG82: 46168 | AH82: Closed | AJ82: 42371819184 | AK82: 7505000 | AL82: 46122 | AM82: 46143 | AP82: PV RIBBON BUS BAR
A83: 258 | B83: 5600000412 | C83: 0692626IM0Y00068 | D83: 46097 | E83: SBI | F83: 0.1 | G83: FLAT HONG KONG CO LTD | H83: USD | I83: 1307700 | J83: 0 | K83: =J83+I83 -> 1307700 | L83: 94.9205 | M83: =K83*L83 -> 1.2412754e+08 | N83: Raw Material | O83: 45 | P83: YES | Q83: 81005224 /5420/5600/5667/5683 | R83: 46118 | S83: 46122 | T83: 46104 | U83: 1307700 | V83: =K83-U83 -> 0 | W83: =U83*L83 -> 1.2412754e+08 | Y83: 46149 | Z83: =Y83+2 -> 46151 | AA83: =M83 -> 1.2412754e+08 | AC83: =IF(Y83="","-",TEXT(Y83,"mmmmyy")) -> May26 | AD83: BOE Received and Paid | AE83: Paid | AF83: Received | AG83: 46149 | AH83: Closed | AL83: 46127 | AM83: 46148 | AP83: GLASS
A84: 259 | B84: 5600000412 | C84: 0692626IM0Y00067 | D84: 46097 | E84: SBI | F84: 0.1 | G84: FLAT HONG KONG CO LTD | H84: USD | I84: 1307700 | J84: 0 | K84: =J84+I84 -> 1307700 | L84: 95.12 | M84: =K84*L84 -> 124388424 | N84: Raw Material | O84: 45 | P84: YES | Q84: 81003332/3737/3329/3831/3836 | R84: 46116 | S84: 46120 | T84: 46100 | U84: 1307700 | V84: =K84-U84 -> 0 | W84: =U84*L84 -> 124388424 | Y84: 46146 | Z84: =Y84+2 -> 46148 | AA84: =M84 -> 124388424 | AC84: =IF(Y84="","-",TEXT(Y84,"mmmmyy")) -> May26 | AD84: BOE Received and Paid | AE84: Paid | AF84: Received | AG84: 46146 | AH84: Closed | AL84: 46127 | AM84: 46148 | AN84: 8849791 / 8849792 /8850556 /8847569 /8850714 | AO84: 46146 | AP84: GLASS
A85: 260 | B85: 5600000412 | C85: 0692626IM0Y00069 | D85: 46099 | E85: SBI | F85: 0.1 | G85: FLAT HONG KONG CO LTD | H85: USD | I85: 1307700 | J85: 0 | K85: =J85+I85 -> 1307700 | L85: 96 | M85: =K85*L85 -> 125539200 | N85: Raw Material | O85: 45 | P85: YES | Q85: 81015302/4671/5417/5804/5806 | R85: 46147 | S85: 46154 | T85: 46137 | U85: 1307700 | V85: =K85-U85 -> 0 | W85: =U85*L85 -> 125539200 | Y85: 46182 | Z85: =Y85+2 -> 46184 | AA85: =M85 -> 125539200 | AC85: =IF(Y85="","-",TEXT(Y85,"mmmmyy")) -> June26 | AD85: Part/Full BOE received & Unpaid | AE85: Unpaid | AF85: Received | AH85: Open | AJ85: 44730457174 | AK85: 12197000 | AL85: 46157 | AM85: 46178 | AP85: GLASS
A86: 261 | B86: 5600000444 | C86: 0692626IM0Y00070 | D86: 46099 | E86: SBI | F86: 0.1 | G86: PT BINTAN CELLULAR INDONESIA | H86: USD | I86: 3203988.5 | J86: 0 | K86: =J86+I86 -> 3203988.5 | L86: 96 | M86: =K86*L86 -> 3.0758289e+08 | N86: Raw Material | O86: 60 | P86: YES | Q86: BCI26032308 | R86: 46134 | S86: 46139 | T86: 46113 | U86: 361972.8 | V86: =K86-U86 -> 2842015.7 | W86: =U86*L86 -> 34749389 | Y86: 46175 | Z86: =Y86+2 -> 46177 | AA86: =M86 -> 3.0758289e+08 | AC86: =IF(Y86="","-",TEXT(Y86,"mmmmyy")) -> June26 | AD86: BOE Received and Paid | AE86: Paid | AF86: Received | AG86: 46175 | AH86: Closed | AJ86: 42815340031 | AK86: 300000 | AL86: 46127 | AM86: 46148 | AP86: SOLAR CELLS
B87: 5600000444 | C87: 0692626IM0Y00070 | D87: 46099 | E87: SBI | F87: 0.1 | G87: PT BINTAN CELLULAR INDONESIA | H87: USD | I87: 0 | J87: 0 | K87: =J87+I87 -> 0 | L87: 96 | M87: =K87*L87 -> 0 | N87: Raw Material | O87: 60 | P87: YES | Q87: BCI26032303 | R87: 46134 | S87: 46139 | T87: 46111 | U87: 433266.62 | V87: =K87-U87 -> -433266.62 | W87: =U87*L87 -> 41593596 | Y87: 46171 | AC87: =IF(Y87="","-",TEXT(Y87,"mmmmyy")) -> May26 | AD87: BOE Received and Paid | AE87: Paid | AF87: Received | AG87: 46175 | AH87: Closed | AL87: 46127 | AM87: 46148 | AP87: SOLAR CELLS
B88: 5600000444 | C88: 0692626IM0Y00070 | D88: 46099 | E88: SBI | F88: 0.1 | G88: PT BINTAN CELLULAR INDONESIA | H88: USD | I88: 0 | J88: 0 | K88: =J88+I88 -> 0 | L88: 96 | M88: =K88*L88 -> 0 | N88: Raw Material | O88: 60 | P88: YES | Q88: BCI26032302 | R88: 46134 | S88: 46139 | T88: 46107 | U88: 361972.8 | V88: =K88-U88 -> -361972.8 | W88: =U88*L88 -> 34749389 | Y88: 46168 | AC88: =IF(Y88="","-",TEXT(Y88,"mmmmyy")) -> May26 | AD88: BOE Received and Paid | AE88: Paid | AF88: Received | AG88: 46175 | AH88: Closed | AL88: 46127 | AM88: 46148 | AP88: SOLAR CELLS
B89: 5600000444 | C89: 0692626IM0Y00070 | D89: 46099 | E89: SBI | F89: 0.1 | G89: PT BINTAN CELLULAR INDONESIA | H89: USD | I89: 0 | J89: 0 | K89: =J89+I89 -> 0 | L89: 96 | M89: =K89*L89 -> 0 | N89: Raw Material | O89: 60 | P89: YES | Q89: BCI26032301 | R89: 46134 | S89: 46141 | T89: 46107 | U89: 433266.62 | V89: =K89-U89 -> -433266.62 | W89: =U89*L89 -> 41593596 | Y89: 46168 | AC89: =IF(Y89="","-",TEXT(Y89,"mmmmyy")) -> May26 | AD89: BOE Received and Paid | AE89: Paid | AF89: Received | AG89: 46175 | AH89: Closed | AL89: 46127 | AM89: 46148 | AP89: SOLAR CELLS
B90: 5600000444 | C90: 0692626IM0Y00070 | D90: 46099 | E90: SBI | F90: 0.1 | G90: PT BINTAN CELLULAR INDONESIA | H90: USD | I90: 0 | J90: 0 | K90: =J90+I90 -> 0 | L90: 96 | M90: =K90*L90 -> 0 | N90: Raw Material | O90: 60 | P90: YES | Q90: BCI26032304 | R90: 46134 | S90: 46141 | T90: 46107 | U90: 361972.8 | V90: =K90-U90 -> -361972.8 | W90: =U90*L90 -> 34749389 | Y90: 46168 | AC90: =IF(Y90="","-",TEXT(Y90,"mmmmyy")) -> May26 | AD90: BOE Received and Paid | AE90: Paid | AF90: Received | AG90: 46175 | AH90: Closed | AL90: 46127 | AM90: 46148 | AP90: SOLAR CELLS
B91: 5600000444 | C91: 0692626IM0Y00070 | D91: 46099 | E91: SBI | F91: 0.1 | G91: PT BINTAN CELLULAR INDONESIA | H91: USD | I91: 0 | J91: 0 | K91: =J91+I91 -> 0 | L91: 96 | M91: =K91*L91 -> 0 | N91: Raw Material | O91: 60 | P91: YES | Q91: BCI26032305 | R91: 46134 | S91: 46141 | T91: 46113 | U91: 433266.62 | V91: =K91-U91 -> -433266.62 | W91: =U91*L91 -> 41593596 | Y91: 46174 | AC91: =IF(Y91="","-",TEXT(Y91,"mmmmyy")) -> June26 | AD91: BOE Received and Paid | AE91: Paid | AF91: Received | AG91: 46175 | AH91: Closed | AI91: Yes-SBI | AL91: 46127 | AM91: 46148 | AP91: SOLAR CELLS
B92: 5600000444 | C92: 0692626IM0Y00070 | D92: 46099 | E92: SBI | F92: 0.1 | G92: PT BINTAN CELLULAR INDONESIA | H92: USD | I92: 0 | J92: 0 | K92: =J92+I92 -> 0 | L92: 96 | M92: =K92*L92 -> 0 | N92: Raw Material | O92: 60 | P92: YES | Q92: BCI26032307 | R92: 46134 | S92: 46141 | T92: 46113 | U92: 433266.62 | V92: =K92-U92 -> -433266.62 | W92: =U92*L92 -> 41593596 | Y92: 46174 | AC92: =IF(Y92="","-",TEXT(Y92,"mmmmyy")) -> June26 | AD92: BOE Received and Paid | AE92: Paid | AF92: Received | AG92: 46175 | AH92: Closed | AI92: Yes-SBI | AL92: 46127 | AM92: 46148 | AP92: SOLAR CELLS
B93: 5600000444 | C93: 0692626IM0Y00070 | D93: 46099 | E93: SBI | F93: 0.1 | G93: PT BINTAN CELLULAR INDONESIA | H93: USD | I93: 0 | J93: 0 | K93: =J93+I93 -> 0 | L93: 96 | M93: =K93*L93 -> 0 | N93: Raw Material | O93: 60 | P93: YES | Q93: BCI26032306 | R93: 46134 | S93: 46141 | T93: 46113 | U93: 361972.8 | V93: =K93-U93 -> -361972.8 | W93: =U93*L93 -> 34749389 | Y93: 46174 | AC93: =IF(Y93="","-",TEXT(Y93,"mmmmyy")) -> June26 | AD93: BOE Received and Paid | AE93: Paid | AF93: Received | AG93: 46175 | AH93: Closed | AI93: Yes-SBI | AL93: 46127 | AM93: 46148 | AP93: SOLAR CELLS
B94: 5600000444 | C94: 0692626IM0Y00070 | D94: 46099 | E94: SBI | F94: 0.1 | G94: PT BINTAN CELLULAR INDONESIA | H94: USD | I94: 0 | J94: 0 | K94: =J94+I94 -> 0 | L94: 96 | M94: =K94*L94 -> 0 | N94: Raw Material | O94: 60 | P94: CANCELLED | U94: 23030.8 | V94: =K94-U94 -> -23030.8 | W94: =U94*L94 -> 2210956.8 | Y94: 46175 | AC94: =IF(Y94="","-",TEXT(Y94,"mmmmyy")) -> June26 | AD94: LC Cancelled | AE94: Paid | AF94: Cancelled | AG94: 46175 | AH94: Closed | AL94: 46127 | AM94: 46148 | AP94: SOLAR CELLS
A95: 270 | B95: 5600000446 | C95: 0692626IM0Y00074 | D95: 46101 | E95: SBI | F95: 0.1 | G95: FLAT HONG KONG CO LTD | H95: USD | I95: 1307700 | J95: 0 | K95: =J95+I95 -> 1307700 | L95: 94.9205 | M95: =K95*L95 -> 1.2412754e+08 | N95: Raw Material | O95: 45 | P95: YES | Q95: 81007400 /7403/7405/7674/7678 | R95: 46119 | S95: 46122 | T95: 46107 | U95: 1307700 | V95: =K95-U95 -> 0 | W95: =U95*L95 -> 1.2412754e+08 | Y95: 46153 | Z95: =Y95+2 -> 46155 | AA95: =M95 -> 1.2412754e+08 | AC95: =IF(Y95="","-",TEXT(Y95,"mmmmyy")) -> May26 | AD95: BOE Received and Paid | AE95: Paid | AF95: Received | AG95: 46153 | AH95: Closed | AI95: Yes-SBI | AL95: 46127 | AM95: 46148 | AP95: GLASS
A96: 271 | B96: 5600000446 | C96: 0692626IM0Y00075 | D96: 46101 | E96: SBI | F96: 0.1 | G96: FLAT HONG KONG CO LTD | H96: USD | I96: 1307700 | J96: 0 | K96: =J96+I96 -> 1307700 | L96: 96 | M96: =K96*L96 -> 125539200 | N96: Raw Material | O96: 45 | P96: YES | Q96: 81006010/81013207/81010631 | R96: 46133 | S96: 46135 | T96: 46122 | U96: 652950 | V96: =K96-U96 -> 654750 | W96: =U96*L96 -> 62683200 | Y96: 46171 | AC96: =IF(Y96="","-",TEXT(Y96,"mmmmyy")) -> May26 | AD96: Part/Full BOE received & Unpaid | AE96: Paid | AF96: Received | AH96: Open | AJ96: 4281470748 | AK96: 2151000 | AL96: 46142 | AM96: 46163 | AP96: GLASS
B97: 5600000446 | C97: 0692626IM0Y00075 | D97: 46101 | E97: SBI | F97: 0.1 | G97: FLAT HONG KONG CO LTD | H97: USD | I97: 0 | J97: 0 | K97: =J97+I97 -> 0 | L97: 96 | M97: =K97*L97 -> 0 | N97: Raw Material | O97: 45 | P97: YES | Q97: 81013533 | R97: 46144 | S97: 46149 | T97: 46133 | U97: 130770 | V97: =K97-U97 -> -130770 | W97: =U97*L97 -> 12553920 | Y97: 46178 | AC97: =IF(Y97="","-",TEXT(Y97,"mmmmyy")) -> June26 | AD97: Part/Full BOE received & Unpaid | AE97: Unpaid | AF97: Received | AH97: Open | AJ97: 44674538206 | AK97: 10179000 | AL97: 46142 | AM97: 46163 | AP97: GLASS
B98: 5600000446 | C98: 0692626IM0Y00075 | D98: 46101 | E98: SBI | F98: 0.1 | G98: FLAT HONG KONG CO LTD | H98: USD | I98: 0 | J98: 0 | K98: =J98+I98 -> 0 | L98: 96 | M98: =K98*L98 -> 0 | N98: Raw Material | O98: 45 | P98: YES | Q98: 81013211/81010648 | R98: 46154 | S98: 46158 | T98: 46140 | U98: 523980 | V98: =K98-U98 -> -523980 | W98: =U98*L98 -> 50302080 | Y98: 46185 | Z98: =Y98+2 -> 46187 | AA98: =M96 -> 125539200 | AC98: =IF(Y98="","-",TEXT(Y98,"mmmmyy")) -> June26 | AD98: Part/Full BOE received & Unpaid | AE98: Unpaid | AF98: Received | AH98: Open | AL98: 46142 | AM98: 46163 | AP98: GLASS
A99: 272 | B99: 5600000446 | C99: 0692626IM0Y00076 | D99: 46101 | E99: SBI | F99: 0.1 | G99: FLAT HONG KONG CO LTD | H99: USD | I99: 1307700 | J99: 0 | K99: =J99+I99 -> 1307700 | L99: 96 | M99: =K99*L99 -> 125539200 | N99: Raw Material | O99: 45 | P99: YES | Q99: 81012295 | R99: 46144 | S99: 46149 | T99: 46133 | U99: 262440 | V99: =K99-U99 -> 1045260 | W99: =U99*L99 -> 25194240 | Y99: 46178 | AC99: =IF(Y99="","-",TEXT(Y99,"mmmmyy")) -> June26 | AD99: Part/Full BOE received & Unpaid | AE99: Unpaid | AF99: Received | AH99: Open | AJ99: 43792161126 | AK99: 2293000 | AL99: 46142 | AM99: 46163 | AP99: GLASS
B100: 5600000446 | C100: 0692626IM0Y00076 | D100: 46101 | E100: SBI | F100: 0.1 | G100: FLAT HONG KONG CO LTD | H100: USD | I100: 0 | J100: 0 | K100: =J100+I100 -> 0 | L100: 96 | M100: =K100*L100 -> 0 | N100: Raw Material | O100: 45 | P100: YES | Q100: 81012449/4293/3478/3458 | R100: 46155 | S100: 46158 | T100: 46140 | U100: 1045260 | V100: =K100-U100 -> -1045260 | W100: =U100*L100 -> 100344960 | Y100: 46185 | Z100: =Y100+2 -> 46187 | AA100: =M99 -> 125539200 | AC100: =IF(Y100="","-",TEXT(Y100,"mmmmyy")) -> June26 | AD100: Part/Full BOE received & Unpaid | AE100: Unpaid | AF100: Received | AH100: Open | AJ100: 42815340031 | AK100: 67000 | AL100: 46142 | AM100: 46163 | AP100: GLASS
...

Sheet Due Import Payment list rate
B2: Confirmed Lc Payment List
B4: LC no. | C4: LC Op. Date | D4: BENEFICIARY NAME | E4: CURRENCY | F4: BILL AMT | G4: DISCREPANCY AMT | H4: FINAL PAYMENT AMT IN FC | I4: LC Payment Due Date | J4: REF NO | K4: BOE NO | L4: INV NO
B5: 0692626IM0Y00075 | C5: 46101 | D5: FLAT HONG KONG CO LTD | E5: USD | F5: 130770 | G5: 0 | H5: =F5-G5 -> 130770 | I5: 46177 | J5: 0692626US0B00282 | K5: 9246588 | L5: 81013533
B6: 0692626IM0Y00076 | C6: 46101 | D6: FLAT HONG KONG CO LTD | E6: USD | F6: 262440 | G6: 118 | H6: =F6-G6 -> 262322 | I6: 46177 | J6: 0692626US0B00283 | K6: 9151803 | L6: 81012295
B7: 0692626IM0Y00097 | C7: 46127 | D7: ANHUI CSG NEW ENERGY MATERIAL TECHNOLOGY CO LTD | E7: USD | F7: 274950 | G7: 0 | H7: =F7-G7 -> 274950 | I7: 46177 | J7: 0692626US0B00297 | K7: 9543987 | L7: SFG2604015-2
B8: 0692626IM0Y00097 | C8: 46127 | D8: ANHUI CSG NEW ENERGY MATERIAL TECHNOLOGY CO LTD | E8: USD | F8: 412425 | G8: 0 | H8: =F8-G8 -> 412425 | I8: 46177 | J8: 0692626US0B00296 | K8: TRACKING DETAILS | L8: SFG2604015-1
D12: LC AMT IN FC | F12: =SUBTOTAL(9,F5:F11) -> 1080585 | H12: =SUBTOTAL(9,H5:H11) -> 1080467

Sheet LC BG in Process
A1: Type | B1: Bank Name | C1: MRGIN | D1: PO | E1: Party Name | F1: Amt in FC | G1: CURRENCY | H1: AMT IN INR | I1: MARGIN | J1: Name of Material | K1: STATUS
A2: LC | B2: SBI | C2: 0.1 | D2: 5600000456 | E2: ZHEJIANG ZHONGHUAN SUNTER PV TECHNOLOGY | F2: 801024 | G2: 95 | H2: =F2*G2 -> 76097280 | I2: =H2*100% -> 76097280 | J2: JUNCTION BOX | K2: HOLD
A3: LC | B3: SBI | C3: 0.1 | D3: 5600000450 | E3: JIANGYIN HAIHONG NEW ENERGY TECHNOLOGY CO LTD | F3: 482500 | G3: 95 | H3: =F3*G3 -> 45837500 | I3: =H3*100% -> 45837500 | J3: FRAME | K3: DOC SUBMITTED TO BANK
A4: LC | B4: SBI | C4: 0.1 | D4: 5600000455 | E4: ZHEJIANG ZHONGHUAN SUNTER PV TECHNOLOGY | F4: 801024 | G4: 95 | H4: =F4*G4 -> 76097280 | I4: =H4*100% -> 76097280 | J4: JUNCTION BOX | K4: HOLD
A5: LC | B5: SBI | C5: 0.1 | D5: 5600000451 | E5: FUTURE ALUMINUM NEW MATERIALS SDN BHD | F5: 1089760 | G5: 95 | H5: =F5*G5 -> 103527200 | I5: =H5*100% -> 103527200 | J5: FRAME | K5: HOLD
A6: LC | B6: SBI | C6: 0.1 | D6: 5600000449 | E6: FUTURE ALUMINUM NEW MATERIALS SDN BHD | F6: 1107400 | G6: 95 | H6: =F6*G6 -> 105203000 | I6: =H6*100% -> 105203000 | J6: FRAME | K6: HOLD
A7: LC | B7: SBI | C7: 0.1 | E7: PT DUOMAX SOLAR INDONESIA | F7: 575815.68 | G7: 95 | H7: =F7*G7 -> 54702490 | I7: =H7*100% -> 54702490 | J7: CELL | K7: LC DRAFT CONFRIMATION PENDING
E10: Total | H10: =SUM(H2:H9) -> 4.6146475e+08

Sheet supplier Bank Guarantee
A1: Sr.no | B1: Supplier | C1: Type | D1: Bank | E1: Amt. | F1: Date of opening | G1: Date of expiry | H1: PO NO
A2: 1 | B2: Swati Switchgears (India) Pvt Ltd | C2: CORPORATE BG | D2: - | E2: 288545 | F2: 45268 | G2: 46252 | H2: 1100000132
A3: 2 | B3: Swati Switchgears (India) Pvt Ltd | C3: CORPORATE BG | D3: - | E3: 932896 | F3: 45268 | G3: 46360 | H3: 1100000275
A4: 3 | B4: Swati Switchgears (India) Pvt Ltd | C4: CORPORATE BG | D4: - | E4: 1872150 | F4: 45268 | G4: 46313 | H4: 1100000133
A5: 4 | B5: Riello Power India Pvt Ltd | C5: BANK GUARANTEE | D5: Punjab National Bank | E5: 1010000 | F5: 45271 | G5: 45619 | H5: 1100000209
A6: 7 | B6: Rostfrei Steels Pvt Ltd | C6: BANK GUARANTEE | D6: ICICI Bank Ltd | E6: 207500 | F6: 45350 | G6: 45636 | H6: 1100000214
A7: 8 | B7: Kirby Building Systems & Structures Indai Pvt Ltd | C7: BANK GUARANTEE | D7: ICICI Bank Ltd | E7: 35200000 | F7: 45428 | G7: 45519 | H7: P2/11000000010
A8: 10 | B8: Kirby Building Systems & Structures Indai Pvt Ltd | C8: BANK GUARANTEE | D8: ICICI Bank Ltd | E8: 8800000 | F8: 45510 | G8: 46086 | H8: P2/11000000010
A9: 11 | B9: Swati Switchgears (India) Pvt Ltd | C9: CORPORATE BG | D9: - | E9: 2840000 | F9: 45637 | G9: 46665 | H9: P2/11000000069
A10: 12 | B10: Rostfrei Steels Pvt Ltd | C10: BANK GUARANTEE | D10: ICICI Bank Ltd | E10: 184000 | F10: 45674 | G10: 46002 | H10: P2/1100000022
A11: 13 | B11: EPACK PREFAB TECHNOLOGIES LTD | C11: BANK GUARANTEE | D11: ICICI Bank Ltd | E11: 34398745 | F11: 45735 | G11: 45930 | H11: P4/1400000065
A12: 14 | B12: AVANT GARDE CLEANROOM &ENGG | C12: BANK GUARANTEE | D12: ICICI Bank Ltd | E12: 109815000 | F12: 45775 | G12: 46112 | H12: 1400000138
A13: 15 | B13: GARDNER DENVER ENGINEERED PRODUCTS INDIA PVT LTD | C13: BANK GUARANTEE | D13: BANK OF AMERICA | E13: 2210000 | F13: 45777 | G13: 45882 | H13: P4/1400000075
A14: 16 | B14: MEMBRANE GROUP INDIA PVT LTD | C14: BANK GUARANTEE | D14: Punjab National Bank | E14: 42375730 | F14: 45791 | G14: 45960 | H14: GEPL/2025/577
A15: 17 | B15: AGNICE FIRE PROTECTION PVT LTD | C15: BANK GUARANTEE | D15: AXIS BANK | E15: 3000000 | F15: 45793 | G15: 46101 | H15: 1400000183
A16: 18 | B16: AGNICE FIRE PROTECTION PVT LTD | C16: BANK GUARANTEE | D16: AXIS BANK | E16: 11510000 | F16: 45793 | G16: 46101 | H16: 1400000181
A17: 19 | B17: Kirby Building Systems & Structures Indai Pvt Ltd | C17: BANK GUARANTEE | D17: AXIS BANK | E17: 27734400 | F17: 45806 | G17: 45896 | H17: 1400000134
... A54: 58 | B54: Kirby Building Systems & Structures Indai Pvt Ltd | C54: BANK GUARANTEE | D54: YES BANK | E54: 2441968 | F54: 46142 | G54: 46679 | H54: 1400000153
D57: Total | E57: =SUM(E2:E56) -> 600681046
A60: CLOSED
A62: Sr.no | B62: Supplier | C62: Type | D62: Bank | E62: Amt. | F62: Date of opening | G62: Date of expiry | H62: PO NO
A63: 6 | B63: MS Gandhi Automations Pvt Ltd | C63: BANK GUARANTEE | D63: Axis Bank Ltd | E63: 910068 | F63: 45289 | G63: 45593 | H63: 1100000173 | I63: Handover to Sh. Harimohan sir and received by beneficiary also
A64: 5 | B64: Skai Air Control Pvt Ltd | C64: BANK GUARANTEE | D64: IDBI Bank Ltd | E64: 12290888 | F64: 45274 | G64: 45641 | H64: 1100000143,142,212,242,319,260,350,379 | I64: Handover to Sh. Harimohan sir on 04-04-2025
A65: 9 | B65: Sudhir Power Ltd | C65: BANK GUARANTEE | D65: ICICI Bank Ltd | E65: 1976000 | F65: 45449 | G65: 45838 | H65: - | I65: Handover to Kishan sir on 06-09-2025
A66: 35 | B66: NAY ENTERPRISE | C66: BANK GUARANTEE | D66: YES BANK | E66: 14750000 | F66: 45919 | G66: 45991 | H66: 1400000208 | I66: handover to Meet sir on 30-09-2025 due to assign clause issue as per their request to return back
A67: 34 | B67: GNBS ECO CO LTD | C67: BANK GUARANTEE | D67: HANA BANK | E67: 140000 | F67: 45916 | G67: 46173 | H67: 1400000398 [USD BG ASSIGNABLE CLUASE PENDING] | I67: SUBMITTED IN SBI BANK ON 28-11-2025 FOR CANCELLATION AS IT IS FOREIGN BG
A68: 27 | B68: Raychem RPG PVT LTD | C68: BANK GUARANTEE | D68: ICICI Bank Ltd | E68: 7649999 | F68: 45848 | G68: 46053 | H68: 1400000252 | I68: Handover to Meet sir on 16-05-2026
A69: 48 | B69: SHIV SHAKTI ENGINEERS | C69: BANK GUARANTEE | D69: SBI | E69: 14200000 | F69: 46052 | G69: 46112 | H69: 1400000469 | I69: Handover to Meet sir on 27-05-2026
A70: 38 | B70: SHIV SHAKTI ENGINEERS | C70: BANK GUARANTEE | D70: KOTAK | E70: 7100000 | F70: 45947 | G70: 46053 | H70: 1400000469 | I70: Handover to Meet sir on 27-05-2026
A73: supplier BG details
A75: Party Name | B75: PO No/LOI NO | C75: BG Amt | D75: mail dtd | E75: Product | F75: First time Draft confirm date by Finance | G75: Original BG Received | H75: Remarks
A76: Gardner Denver Engineered Products India Pvt Ltd | B76: P4/1400000075 | C76: 2210000 | D76: 45745 | E76: MODULE | F76: 45748 | G76: YES
A77: Permionics Membranes Pvt. Ltd | B77: GEPL/2025/581 | C77: 2,29,72,980.00 | D77: 45757 | E77: cell | F77: 45763 | G77: YES
A78: Avant Garde Cleanroom & Engg. Solutions Pvt. Ltd | B78: 1400000138 | C78: 10,98,15,000.00 | D78: 45757 | E78: cell | F78: 45761 | G78: YES | H78: -
A79: Membrane Group India Pvt Ltd | B79: GEPL/2025/577 | C79: 4,23,75,730.00 | D79: 45763 | E79: cell | F79: 45763 | G79: YES | H79: -
A80: Trane Technologies Pvt Ltd | B80: 1400000114 | C80: 1,18,63,789.00 | D80: 45771 | E80: cell | F80: 45772 | G80: YES
A81: Skai Air Control Private Limited | B81: 1100000045/1100000045/1100000056/1100000116 | C81: 1,49,46,077.00 | D81: 45784 | E81: MODULE | F81: - | G81: YES | H81: -
A82: Agnice Fire Protection Pvt. Ltd | B82: 1400000183 | C82: 3000000 | D82: 45792 | E82: cell | F82: 45792 | G82: YES | H82: -
A83: Agnice Fire Protection Pvt. Ltd | B83: 1400000181 | C83: 11510000 | D83: 45792 | E83: cell | F83: 45792 | G83: YES | H83: -
A84: Air Gas Electronic Material Enterprises Co., Ltd | B84: 1400000139 | C84: $ 212900 | D84: 45819 | E84: GAS | F84: 45821 | G84: NO | H84: -
A85: Air Gas Electronic Material Enterprises Co., Ltd | B85: 1400000141 | C85: $ 114300 | D85: 45819 | E85: GAS | F85: 45821 | G85: NO | H85: -
A86: Raychem RPG PVT LTD | B86: 1400000252 | C86: 7650000 | D86: 45825 | E86: CELL | F86: 45826 | G86: YES | H86: -
A87: Nay Enterprise | B87: 1400000208 and 1400000210 | C87: 17850713 | D87: 45845 | E87: CELL | F87: 45846 | G87: NO | H87: -
A88: EPACK PREFAB TECHNOLOGIES LIMITED | B88: P4/1400000291 | C88: 1863401 | D88: 45849 | E88: CELL | F88: 45852 | G88: YES | H88: -

Sheet Bank Guarantee
A1: Sr.no | B1: Bank Name | C1: Supplier | D1: BG no. | E1: Type | F1: Amt. | G1: Tag | H1: Date of opening | I1: Date of expiry | J1: FD No | K1: FD Lien Amt | L1: FD Amt | M1: status
A2: 1 | B2: SBI BG 100% | C2: THE PRESIDENT OF INDIA | D2: 0692623BG0000159 | E2: EPCG | F2: 22734500 | G2: Module Line | H2: 45107 | I2: 47299 | J2: 42815340031 | K2: 7224000 | L2: 19980054 | M2: ACTIVE
B3: SBI BG 100% | C3: THE PRESIDENT OF INDIA | D3: 0692623BG0000159 | E3: EPCG | F3: 0 | G3: Module Line | H3: 45107 | I3: 47299 | J3: 42456259384 | K3: 7564000 | L3: 13071236 | M3: ACTIVE
B4: SBI BG 100% | C4: THE PRESIDENT OF INDIA | D4: 0692623BG0000159 | E4: EPCG | F4: 0 | G4: Module Line | H4: 45107 | I4: 47299 | J4: 42561333063 | K4: 4450000 | L4: 6801318 | M4: ACTIVE
B5: SBI BG 100% | C5: THE PRESIDENT OF INDIA | D5: 0692623BG0000159 | E5: EPCG | F5: 0 | G5: Module Line | H5: 45107 | I5: 47299 | J5: 42371819184 | K5: 3496500 | L5: 4144466 | M5: ACTIVE
A6: =A2+1 -> 2 | B6: SBI BG 100% | C6: THE PRESIDENT OF INDIA | D6: 0692623BG0000161 | E6: EPCG | F6: 14767500 | G6: Stringer | H6: 45110 | I6: 47330 | J6: 42042836045 | K6: 14767500 | L6: 14767500 | M6: ACTIVE
A7: =A6+1 -> 3 | B7: SBI BG 100% | C7: THE PRESIDENT OF INDIA | D7: 0692623BG0000222 | E7: EPCG | F7: 1229500 | G7: Vacuum Pump | H7: 45159 | I7: 47351 | J7: 42194876674 | K7: 1229500 | L7: 1229500 | M7: ACTIVE
A8: =A7+1 -> 4 | B8: SBI BG 100% | C8: THE PRESIDENT OF INDIA | D8: 0692623BG0000262 | E8: IGCR | F8: 13125000 | G8: Solar Glass | H8: 45199 | I8: 46295 | J8: 42311730454 | K8: 13125000 | L8: 13125000 | M8: ACTIVE
A9: =A8+1 -> 5 | B9: SBI BG 100% | C9: THE PRESIDENT OF INDIA | D9: 0692623BG0000308 | E9: EPCG | F9: 1425000 | G9: Sum Simulator | H9: 45240 | I9: 47432 | J9: 42426399021 | K9: 1425000 | L9: 1425000 | M9: ACTIVE
A10: =A9+1 -> 6 | B10: SBI BG 100% | C10: THE PRESIDENT OF INDIA | D10: 0692623BG0000309 | E10: EPCG | F10: 498800 | G10: PDI Line | H10: 45240 | I10: 47432 | J10: 42426333831 | K10: 498800 | L10: 498800 | M10: ACTIVE
A11: =A10+1 -> 7 | B11: SBI BG 100% | C11: THE PRESIDENT OF INDIA | D11: 0692623BG0000307 | E11: EPCG | F11: 22734500 | G11: Module Line | H11: 45240 | I11: 47432 | J11: 42426400640 | K11: 22734500 | L11: 22734500 | M11: ACTIVE
A12: =A11+1 -> 8 | B12: SBI BG 100% | C12: THE PRESIDENT OF INDIA | D12: 0692623BG0000322 | E12: EPCG | F12: 4254045 | G12: Lab Testing Machine - ZWT / CG Goods | H12: 45275 | I12: 47467 | J12: 42525986027 | K12: 4254045 | L12: 4254045 | M12: ACTIVE
A13: 9 | B13: SBI-BG 10% | C13: SOLAR ENERGY CORPORATION OF INDIA LTD | D13: 0692624BG0000093 | E13: PLI | F13: 180000000 | G13: PLI | H13: 45379 | I13: 47968 | J13: 42830614684 | K13: 18000000 | L13: 18000000 | M13: ACTIVE
A14: 10 | B14: SBI BG 100% | C14: THE PRESIDENT OF INDIA | D14: 0692624BG0000126 | E14: BG | F14: 4672540 | G14: AGAINST BOE NO 3305878 SOLAR SPACE LC | H14: 45439 | I14: 46195 | J14: 43254910895 | K14: 1700000 | L14: 1806609 | M14: ACTIVE
B15: SBI BG 100% | C15: THE PRESIDENT OF INDIA | D15: 0692624BG0000126 | E15: BG | G15: AGAINST BOE NO 3305878 SOLAR SPACE LC | H15: 45439 | I15: 46195 | J15: 42352342044 | K15: 1368730 | L15: 1368730 | M15: ACTIVE
B16: SBI BG 100% | C16: THE PRESIDENT OF INDIA | D16: 0692624BG0000126 | E16: BG | G16: AGAINST BOE NO 3305878 SOLAR SPACE LC | H16: 45439 | I16: 46195 | J16: 42318765196 | K16: 1594009 | L16: 1594009 | M16: ACTIVE
B17: SBI BG 100% | C17: THE PRESIDENT OF INDIA | D17: 0692624BG0000126 | E17: BG | G17: AGAINST BOE NO 3305878 SOLAR SPACE LC | H17: 45439 | I17: 46195 | J17: 42319489577 | K17: 9801 | L17: 318801 | M17: ACTIVE
A18: =A14+1 -> 11 | B18: SBI BG 100% | C18: THE PRESIDENT OF INDIA | D18: 0692624BG0000127 | E18: BG | F18: 4669484 | G18: AGAINST BOE NO 3324460 SOLAR SPACE LC | H18: 45439 | I18: 46195 | J18: 42309489089 | K18: 3188000 | L18: 3188034 | M18: ACTIVE
B19: SBI BG 100% | C19: THE PRESIDENT OF INDIA | D19: 0692624BG0000127 | E19: BG | G19: AGAINST BOE NO 3324460 SOLAR SPACE LC | H19: 45439 | I19: 46195 | J19: 42896923356 | K19: 1048000 | L19: 10893478 | M19: ACTIVE
B20: SBI BG 100% | C20: THE PRESIDENT OF INDIA | D20: 0692624BG0000127 | E20: BG | G20: AGAINST BOE NO 3324460 SOLAR SPACE LC | H20: 45439 | I20: 46195 | J20: 42377916078 | K20: 433484 | L20: 4888352 | M20: ACTIVE
A21: =A18+1 -> 12 | B21: SBI BG 100% | C21: THE PRESIDENT OF INDIA | D21: 0692624BG0000128 | E21: BG | F21: 4672251 | G21: AGAINST BOE NO 3305835 SOLAR SPACE LC | H21: 45439 | I21: 46195 | J21: 42377916078 | K21: 4014275 | L21: 0 | M21: ACTIVE
B22: SBI BG 100% | C22: THE PRESIDENT OF INDIA | D22: 0692624BG0000128 | E22: BG | F22: 0 | G22: AGAINST BOE NO 3305835 SOLAR SPACE LC | H22: 45439 | I22: 46195 | J22: 42597394309 | K22: 657976 | L22: 820000 | M22: ACTIVE
A23: 19 | B23: IDBI -BG | C23: Sunsure Energy Pvt Ltd | D23: 26001IBGA00021 | E23: ABG | F23: 70250120 | G23: 50 MW Mundsar Solar | H23: 46076 | I23: 46112 | M23: ACTIVE
A24: 20 | B24: IDBI -BG | C24: Sunsure Energy Pvt Ltd | D24: 26001IBGA00033 | E24: ABG | F24: 87561900 | G24: 60.180 MW | H24: 46090 | I24: 46119 | J24: 1001105000022030 | K24: 8757000 | M24: ACTIVE
A25: 22 | B25: SBI-BG 10% | C25: SUNBREEZE RENEWABLES NINE PVT LTD | D25: 0692626BG0Y00022 | E25: ABG | F25: 904400000 | G25: MW is 360 MW | H25: 46093 | I25: 46173 | J25: 44995227852 | K25: 90000000 | M25: ACTIVE
B26: SBI-BG 10% | C26: SUNBREEZE RENEWABLES NINE PVT LTD | D26: 0692626BG0Y00022 | E26: ABG | F26: 0 | G26: MW is 360 MW | H26: 46093 | I26: 46173 | J26: 44994834618 | K26: 40980678 | M26: ACTIVE
B27: SBI-BG 10% | C27: SUNBREEZE RENEWABLES NINE PVT LTD | D27: 0692626BG0Y00022 | E27: ABG | F27: 0 | G27: MW is 360 MW | H27: 46093 | I27: 46173 | J27: 43286332815 | K27: 4680000 | M27: ACTIVE
A28: 23 | B28: SBI-BG 10% | C28: HINDUJA RENEWABLES ENERGY PVT LTD | D28: 0692626BG0Y00024 | E28: ABG | F28: 358647023 | G28: 196.78908 MW | H28: 46111 | I28: 46223 | J28: 45039415633 | K28: 53798000 | M28: ACTIVE
A29: 24 | B29: SBI-BG 10% | C29: HINDUJA RENEWABLES ENERGY PVT LTD | D29: 0692626BG0Y00025 | E29: ABG | F29: 51239569 | G29: 196.78908 MW | H29: 46111 | I29: 46223 | J29: 45039415633 | K29: 7686000 | M29: ACTIVE
A30: 25 | B30: SBI-BG 10% | C30: HINDUJA RENEWABLES ENERGY PVT LTD | D30: 0692626BG0Y00026 | E30: ABG | F30: 307409604 | G30: 196.78908 MW | H30: 46111 | I30: 46223 | J30: 45039415633 | K30: 46112000 | M30: ACTIVE
D32: TOTAL | F32: =SUBTOTAL(9,F2:F31) -> 2054291336 | K32: =SUBTOTAL(9,K2:K31) -> 364796798 | L32: =SUBTOTAL(9,L2:L31) -> 144909432
C34: CLOSED BG
A36: Sr.no | B36: Bank Name | C36: Supplier | D36: BG no. | E36: Type | F36: Amt. | H36: Date of opening | I36: Date of expiry | J36: FD No | K36: FD Lien Amt | L36: FD Amt | M36: status | N36: closed date
A37: =A12+1 -> 9 | B37: SBI | C37: SOLAR ENERGY CORPORATION OF INDIA LTD | D37: 0692623BG0000326 | E37: EMD | F37: 54000000 | G37: 200Mwp | H37: 45281 | I37: 45540 | J37: 42278070682, 42318765196 , 42475014793 , 42334957015 | L37: - | M37: CLOSED | N37: 45508
A38: =A13+1 -> 10 | B38: SBI | C38: SOLAR ENERGY CORPORATION OF INDIA LTD | D38: 0692624BG0000072 | E38: EMD | F38: 75000000 | G38: 900Mwp | H38: 45372 | I38: 45632 | J38: 42814707478 | L38: 7500000 | M38: CLOSED | N38: 45503
A39: 1 | B39: BANDHAN | C39: SOLAR ENERGY CORPORATION OF INDIA LTD | D39: 2023PBG017240189 | E39: PLI | F39: 180000000 | G39: PLI | H39: 45026 | I39: 47968 | J39: 23001563112 | L39: 180000000 | M39: CLOSED | N39: 45418
A40: 17 | B40: SBI | C40: Acme Cleantech Solutions Private Limited | D40: 0692624BG0000148 | E40: BG | F40: 167500000 | G40: Bikaner Project | H40: 45492 | I40: 45595 | J40: 42319489577 , 42855164420, 42561333063 , 42815340031 , 42840339454 | L40: 16800000 | M40: CLOSED | N40: 45611
A41: 23 | B41: SBI | C41: AMBUJA CEMENT LTD/ADANI | D41: 0692624BG0Y00190 | E41: ABG | F41: 119832166 | H41: 45617 | I41: 45688 | J41: 43549245722 | K41: 119832166 | L41: 119832166 | M41: CLOSED | N41: 45661
A42: 19 | B42: SBI | C42: AMBUJA CEMENT LTD/ADANI | D42: 0692624BG0000161 | E42: ABG | F42: 56468122 | G42: 35 Mwp | H42: 45527 | I42: 45626 | J42: 42814707478 | K42: 5646813 | L42: 7773717 | M42: CLOSED | N42: 45673
A43: 23 | B43: SBI | C43: ADANI GREEN ENERGY LTD | D43: 0692625BG0Y00009 | E43: ABG | F43: 139236457 | G43: SOLAR PV MODULE OF 82.20 WP | H43: 45681 | I43: 45731 | J43: 43749543130 | K43: 139236457 | L43: 139236457 | M43: CLOSED | N43: 45749
A44: 20 | B44: SBI | C44: AMBUJA CEMENT LTD/ADANI | D44: 0692624BG0Y00173 | E44: ABG | F44: 124338817 | G44: 80 Mwp | H44: 45561 | I44: 45716 | J44: 42814707478 | K44: 1800000 | L44: 0 | M44: CLOSED | N44: 45754
B45: SBI | C45: AMBUJA CEMENT LTD/ADANI | D45: 0692624BG0Y00173 | E45: ABG | F45: 0 | G45: 80 Mwp | H45: 45561 | I45: 45716 | J45: 43381644996 | K45: 2500000 | L45: 2500000 | M45: CLOSED
B46: SBI | C46: AMBUJA CEMENT LTD/ADANI | D46: 0692624BG0Y00173 | E46: ABG | F46: 0 | G46: 80 Mwp | H46: 45561 | I46: 45716 | J46: 42461935379 | K46: 3560000 | L46: 3783224 | M46: CLOSED
B47: SBI | C47: AMBUJA CEMENT LTD/ADANI | D47: 0692624BG0Y00173 | E47: ABG | F47: 0 | G47: 80 Mwp | H47: 45561 | I47: 45716 | J47: 43183927865 | K47: 4700000 | L47: 4700000 | M47: CLOSED
A48: 18 | B48: SBI | C48: Solarcraft Power India 5 Private Limited | D48: 0692624BG0000152 | E48: ABG | F48: 188198146 | G48: TOPCON MSA | H48: 45497 | I48: 45808 | J48: 43183923893 | K48: 18900000 | L48: 18900000 | M48: CLOSED | N48: 45847
A49: 23 | B49: SBI | C49: DYNASPEDE RENEWABLE ENERGY PVT LTD/SUNSTREAM | D49: 0692625BG0Y00032 | E49: ABG | F49: 69804000 | G49: Module WP 580-585 WP | H49: 45751 | I49: 45838 | J49: 42456259384 | K49: 5500000 | L49: 0 | M49: CLOSED | N49: 45861
B50: SBI | C50: DYNASPEDE RENEWABLE ENERGY PVT LTD/SUNSTREAM | D50: 0692625BG0Y00032 | E50: ABG | F50: 0 | H50: 45751 | I50: 45838 | J50: 42561333063 | K50: 1481000 | L50: 0 | M50: CLOSED | N50: 45861
A51: 25 | B51: SBI | C51: SOLAR ENERGY CORPORATION OF INDIA LTD | D51: 0692625BG0Y00063 | E51: EMD | F51: 56000000 | G51: modules for a 260 MW | H51: 45796 | I51: 46011 | J51: 43286332815 | K51: 5600000 | L51: 0 | M51: CLOSED | N51: 45888
A52: 21 | B52: SBI | C52: SUNBREEZE RENEWABLES NINE PVT LTD | D52: 0692624BG0Y00183 | E52: ABG | F52: 112753571 | G52: SOLAR PV MODULE OF 580 WP | H52: 45583 | I52: 45900 | J52: 42039487699 | K52: 800000 | L52: 29100000 | M52: CLOSED | N52: 45890
B53: SBI | C53: SUNBREEZE RENEWABLES NINE PVT LTD | D53: 0692624BG0Y00183 | E53: ABG | F53: 0 | G53: SOLAR PV MODULE OF 580 WP | H53: 45583 | I53: 45900 | J53: 42461936258 | K53: 10000000 | L53: 22734500 | M53: CLOSED
B54: SBI | C54: SUNBREEZE RENEWABLES NINE PVT LTD | D54: 0692624BG0Y00183 | E54: ABG | F54: 0 | G54: SOLAR PV MODULE OF 580 WP | H54: 45583 | I54: 45900 | J54: 43286332815 | K54: 531000 | L54: 10627033 | M54: CLOSED
A55: 22 | B55: SBI | C55: SUNBREEZE RENEWABLES NINE PVT LTD | D55: 0692624BG0Y00191 | E55: ABG | F55: 156200000 | G55: SOLAR PV MODULE OF 580 WP | H55: 45617 | I55: 45900 | J55: 42840339454 | K55: 2020000 | L55: 3480084 | M55: CLOSED | N55: 45890
B56: SBI | C56: SUNBREEZE RENEWABLES NINE PVT LTD | D56: 0692624BG0Y00191 | E56: ABG | F56: 0 | H56: 45617 | I56: 45900 | J56: 42855164420 | K56: 3600000 | L56: 3600000 | M56: CLOSED
B57: SBI | C57: SUNBREEZE RENEWABLES NINE PVT LTD | D57: 0692624BG0Y00191 | E57: ABG | F57: 0 | H57: 45617 | I57: 45900 | J57: 43549278543 | K57: 10000000 | L57: 10000000 | M57: CLOSED
A58: 15 | B58: SBI | C58: Purvah Green Power Private Limited /RPSG | D58: 0692625BG0Y00111 | E58: ABG | F58: 106061378 | G58: RPSG 210 MW | H58: 45881 | I58: 46053 | J58: 44361399732 | K58: 10606200 | L58: 71500000 | M58: CLOSED | N58: 45933
A59: 14 | B59: SBI | C59: SUNBREEZE RENEWABLES NINE PVT LTD | D59: 0692625BG0Y00054 | E59: ABG | F59: 419109538 | G59: Module WP 460 WP | H59: 45791 | I59: 45930 | J59: 44085316349 | K59: 50000000 | L59: 124315000 | M59: CLOSED | N59: 46108
A60: 13 | B60: SBI BG 100% | C60: THE PRESIDENT OF INDIA | D60: 0692624BG0000136 | E60: BG | F60: 10218189 | G60: AGAINST BOE NO 3490798 & 3408215 release of jolywood material | H60: 45463 | I60: 46021 | J60: 43074817405 | K60: 10218189 | L60: 10913952 | M60: CLOSED | N60: 46108
B61: SBI-BG 10% | C61: NTPC RAJASTHAN GREEN ENERGY LIMITED | D61: 0692625BG0Y00133 | E61: EMD | F61: 200000000 | G61: BIKANER 787.8 Mwp | H61: 45894 | I61: 46070 | J61: 42461936258 | K61: 10000000 | L61: 10627033 | M61: CLOSED
B62: SBI-BG 10% | C62: NTPC RAJASTHAN GREEN ENERGY LIMITED | D62: 0692625BG0Y00133 | E62: EMD | F62: 0 | G62: BIKANER 787.8 Mwp | H62: 45894 | I62: 46070 | J62: 43549278543 | K62: 10000000 | L62: 10000000 | M62: CLOSED
A63: 18 | B63: SBI-BG 10% | C63: NTPC Renewable energy Limited | D63: 0692625BG0Y00135 | E63: EMD | F63: 200000000 | G63: KHAVDA | H63: 45895 | I63: 46073 | J63: 43286332815 | K63: 8867000 | L63: 22848391 | M63: CLOSED | N63: 46114
B64: SBI-BG 10% | C64: NTPC Renewable energy Limited | D64: 0692625BG0Y00135 | E64: EMD | F64: 0 | G64: KHAVDA | H64: 45895 | I64: 46073 | J64: 42896923356 | K64: 9845000 | M64: CLOSED | N64: 46114
B65: SBI-BG 10% | C65: NTPC Renewable energy Limited | D65: 0692625BG0Y00135 | E65: EMD | F65: 0 | G65: KHAVDA | H65: 45895 | I65: 46073 | J65: 44361399732 | K65: 1288000 | L65: 0 | M65: CLOSED | N65: 46114
A66: 17 | B66: SBI-BG 10% | C66: NTPC Renewable energy Limited | D66: 0692625BG0Y00125 | E66: EMD | F66: 200000000 | G66: Lalitpur-1 + Lalitpur-2 878.7 MWP | H66: 45888 | I66: 46173 | J66: 44085316349 | K66: 20000000 | L66: 200000000 | M66: CLOSED | N66: 46121 | O66: Invoke on 09-04-2026
A67: 16 | B67: SBI-BG 10% | C67: Purvah Green Power Private Limited /RPSG | D67: 0692625BG0Y00112 | E67: ABG | F67: 2426631 | G67: RPSG 210 MW | H67: 45881 | I67: 46053 | K67: 365000 | L67: 30924792 | M67: CLOSED | N67: 46144
A68: 21 | B68: SBI-BG 10% | C68: SUNBREEZE RENEWABLES NINE PVT LTD | D68: 0692626BG0Y00021 | E68: ABG | F68: 910000000 | G68: MW is 360 MW | H68: 46093 | I68: 46173 | J68: 44361399732 | K68: 59584437 | M68: CLOSED | N68: 46164
B69: SBI-BG 10% | C69: SUNBREEZE RENEWABLES NINE PVT LTD | D69: 0692626BG0Y00021 | E69: ABG | G69: MW is 360 MW | H69: 46093 | I69: 46173 | J69: 42039487699 | K69: 21900000 | M69: CLOSED | N69: 46164
B70: SBI-BG 10% | C70: SUNBREEZE RENEWABLES NINE PVT LTD | D70: 0692626BG0Y00021 | E70: ABG | G70: MW is 360 MW | H70: 46093 | I70: 46173 | J70: 43199860436 | K70: 30996241 | M70: CLOSED | N70: 46164
B71: SBI-BG 10% | C71: SUNBREEZE RENEWABLES NINE PVT LTD | D71: 0692626BG0Y00021 | E71: ABG | G71: MW is 360 MW | H71: 46093 | I71: 46173 | J71: 44994834618 | K71: 24019322 | M71: CLOSED | N71: 46164

Sheet FDR List
A1: SR NO | B1: Bank Name | C1: Opening date | D1: FD Account Number | E1: LC/BG/COLLETRAL | F1: MARGIN | G1: PARTY NAME | H1: TYPE | I1: DESCRIPTION | J1: Original Principal Rate | K1: OLD MATURITY AMT | L1: FD LIEN AMT for LC/BG | M1: New Prin. Amt | N1: Int. Amt | O1: New Maturity Amt. | P1: Maturity Period | Q1: Maturity Date | R1: New Deposit Value | S1: New Maturity Value | T1: New Maturity Date | U1: New Interest Rates | V1: FINAL FD AMT | W1: STATUS | X1: Account Type
A2: =A203+1 -> 2 | B2: SBI | C2: 45108 | D2: 42042836045 | E2: BG 100% | F2: 1 | G2: THE PRESIDENT OF INDIA | H2: EPCG | I2: STRINGER | J2: 0.065 | K2: 14767500 | L2: 14767500 | M2: 14767500 | N2: 6975546 | O2: 21743046 | P2: 6 Y | Q2: 47300 | R2: - | S2: - | T2: - | U2: - | V2: =M2 -> 14767500 | W2: ACTIVE | X2: CA
A3: =A2+1 -> 3 | B3: SBI | C3: 45079 | D3: 41965814780 | E3: COLLETRAL | F3: COLLETRAL | G3: GREW ENERGY PVT LTD | H3: COLLETRAL | I3: - | J3: 0.071 | K3: 14600000 | L3: 14600000 | M3: 15650791 | N3: =O3-L3 -> 2306258 | O3: 16906258 | P3: 400D | Q3: 45479 | R3: 16778862 | S3: 17959368 | T3: 46279 | U3: 0.0625 | V3: =R3 -> 16778862 | W3: ACTIVE | X3: -
A4: =A3+1 -> 4 | B4: SBI | C4: 45159 | D4: 42194876674 | E4: BG 100% | F4: 1 | G4: THE PRESIDENT OF INDIA | H4: EPCG | I4: VACCUM PUMP | J4: 0.065 | K4: 1229500 | L4: 1229500 | M4: 1229500 | N4: 580764 | O4: 1810264 | P4: 6 Y | Q4: 47351 | R4: - | S4: - | T4: - | U4: - | V4: =M4 -> 1229500 | W4: ACTIVE | X4: CA
A5: =A127+1 -> 8 | B5: SBI | C5: 45199 | D5: 42311730454 | E5: BG 100% | F5: 1 | G5: THE PRESIDENT OF INDIA | H5: IGCR | I5: SOLAR GLASS | J5: 0.07 | K5: 13125000 | L5: 13125000 | M5: 13125000 | N5: 2040830 | O5: 15165830 | P5: 2 Y 1M | Q5: 45960 | R5: 14953460 | S5: 17088006 | T5: 46721 | U5: 6.45 | V5: =M5 -> 13125000 | W5: ACTIVE | X5: CA
A6: =A5+1 -> 9 | B6: SBI | C6: 45199 | D6: 42309489089 | E6: BG 100% | F6: 1 | G6: THE PRESIDENT OF INDIA | H6: CUSTOM DEPT | I6: AGAINST BOE NO 3324460 SOLAR SPACE LC | J6: 0.068 | K6: 3000000 | L6: 3188034 | M6: 3188034 | N6: =O6-M6 -> 222377 | O6: 3410411 | P6: 1 Y | Q6: 45565 | R6: 3387854 | S6: 3604609 | T6: 46295 | U6: 0.0625 | V6: =R6 -> 3387854 | W6: ACTIVE | X6: CA
A7: =A6+1 -> 10 | B7: SBI | C7: 45202 | D7: 42319489577 | E7: BG 100% | F7: 1 | G7: THE PRESIDENT OF INDIA | H7: CUSTOM DEPT | I7: AGAINST BOE NO 3305878 SOLAR SPACE LC | J7: 0.068 | K7: 300000 | L7: 9801 | M7: 318801 | N7: =O7-M7 -> 22238 | O7: 341039 | P7: 1 Y | Q7: 45568 | R7: 338780 | S7: 360455 | T7: 46298 | U7: 0.0625 | V7: =R7 -> 338780 | W7: ACTIVE | X7: CA
B8: SBI | C8: 45202 | D8: 42319489577 | E8: CAPEX 100% | F8: 1 | J8: 0.068 | K8: - | L8: 328979 | M8: - | N8: - | O8: - | P8: 1 Y | Q8: 45568 | R8: - | S8: - | T8: 46298 | U8: 0.0625 | V8: - | W8: ACTIVE | X8: CA
A9: =A134+1 -> 13 | B9: SBI | C9: 45212 | D9: 42352342044 | E9: BG 100% | F9: 1 | G9: THE PRESIDENT OF INDIA | H9: CUSTOM DEPT | I9: AGAINST BOE NO 3305878 SOLAR SPACE LC | J9: 0.068 | K9: 1288000 | L9: 1368730 | M9: 1368730 | N9: =O9-M9 -> 95474 | O9: 1464204 | P9: 1 Y | Q9: 45578 | R9: 1454521 | S9: 1547581 | T9: 46308 | U9: 0.0625 | V9: =R9 -> 1454521 | W9: ACTIVE | X9: CA
A10: =A149+1 -> 16 | B10: SBI | C10: 45219 | D10: 42371819184 | E10: BG 100% | F10: 1 | G10: THE PRESIDENT OF INDIA | H10: EPCG | I10: Module Line | J10: 0.068 | K10: 3900000 | L10: 3496500 | M10: 4144466 | N10: =O10-M10 -> 289092 | O10: 4433558 | P10: 1 Y | Q10: 45585 | R10: 4404256 | S10: 4686041 | T10: 46315 | U10: 0.0625 | V10: =R10 -> 4404256 | W10: ACTIVE | X10: CA
B11: SBI | C11: 45219 | D11: 42371819184 | E11: LC - 10% | F11: 0.1 | J11: 0.068 | K11: 0 | L11: 103500 | M11: 0 | N11: 0 | O11: 0 | P11: 1 Y | Q11: 45585 | R11: - | S11: - | T11: 46315 | U11: 0.0625 | V11: - | W11: ACTIVE | X11: CA
B12: SBI | C12: 45219 | D12: 42371819184 | E12: LC - 10% | F12: 0.1 | J12: 0.068 | K12: 0 | L12: 300000 | M12: 0 | N12: 0 | O12: 0 | P12: 1 Y | Q12: 45585 | R12: - | S12: - | T12: 46315 | U12: 0.0625 | V12: - | W12: ACTIVE | X12: CA
A13: =A143+1 -> 18 | B13: SBI | C13: 45251 | D13: 42456259384 | E13: BG 100% | F13: 1 | G13: THE PRESIDENT OF INDIA | H13: EPCG | I13: Module Line | J13: 0.068 | K13: 12300000 | L13: 7564000 | M13: 13071236 | N13: =O13-M13 -> 911768 | O13: 13983004 | P13: 1 Y | Q13: 45617 | R13: 13890835 | S13: 14779573 | T13: 46347 | U13: 0.0625 | V13: =R13 -> 13890835 | W13: ACTIVE | X13: CC
B14: SBI | C14: 45251 | D14: 42456259384 | E14: LC - 10% | F14: 0.1 | J14: 0.068 | L14: 6326835 | M14: - | N14: 0 | O14: - | P14: 1 Y | Q14: 45617 | R14: - | S14: - | T14: 46347 | U14: 0.0625 | V14: - | W14: ACTIVE | X14: CC
A15: =A162+1 -> 20 | B15: SBI | C15: 45253 | D15: 42461936258 | E15: FREE AGAINST BG | F15: 0.1 | J15: 0.068 | K15: 10000000 | L15: 10000000 | M15: 10000000 | N15: =O15-M15 -> 1368308 | O15: 11368308 | P15: 1 Y | Q15: 45619 | R15: 11293386 | S15: 12015939 | T15: 46349 | U15: 0.0625 | V15: =R15 -> 11293386 | W15: ACTIVE | X15: CA
B16: SBI | C16: 45253 | D16: 42461936258 | E16: FREE AGAINST BG | F16: 0.1 | J16: 0.068 | K16: - | L16: 1293386 | M16: - | N16: 0 | O16: - | P16: 1 Y | Q16: 45619 | R16: - | S16: - | T16: 46349 | U16: 0.0625 | V16: - | W16: ACTIVE | X16: CA
A17: =A151+1 -> 24 | B17: SBI | C17: 45289 | D17: 42561333063 | E17: BG 100% | F17: 1 | G17: THE PRESIDENT OF INDIA | H17: EPCG | I17: Module Line | J17: 0.068 | K17: 6400000 | L17: 4450000 | M17: 6801318 | N17: =O17-M17 -> 45106 | O17: 6846424 | P17: 1 Y | Q17: 45655 | R17: 7227800 | S17: 7690236 | T17: 46385 | U17: 0.0625 | V17: =R17 -> 7227800 | W17: ACTIVE | X17: CC
B18: SBI | C18: 45289 | D18: 42561333063 | E18: LC - 10% | F18: 0.1 | J18: 0.068 | K18: - | L18: 1907482 | M18: 0 | N18: 0 | O18: - | P18: 1 Y | Q18: 45655 | R18: - | S18: - | T18: 46385 | U18: 0.0625 | V18: - | W18: ACTIVE | X18: CC
B19: SBI | C19: 45289 | D19: 42561333063 | E19: SBLC | F19: 0.1 | J19: 0.068 | K19: - | L19: 870318 | M19: 0 | N19: 0 | O19: - | P19: 1 Y | Q19: 45655 | R19: - | S19: - | T19: 46385 | U19: 0.0625 | V19: - | W19: ACTIVE | X19: CC
A20: =A132+1 -> 27 | B20: SBI | C20: 45202 | D20: 42318765196 | E20: BG 100% | F20: 1 | G20: THE PRESIDENT OF INDIA | H20: CUSTOM DEPT | I20: AGAINST BOE NO 3305878 SOLAR SPACE LC | J20: 0.068 | K20: 1500000 | L20: 1594009 | M20: 1594009 | N20: =O20-M20 -> 111188 | O20: 1705197 | P20: 1 Y | Q20: 45568 | R20: 1693911 | S20: 1802288 | T20: 46298 | U20: 0.0625 | V20: =R20 -> 1693911 | W20: ACTIVE | X20: CA
A21: =A20+1 -> 28 | B21: SBI | C21: 45239 | D21: 42426399021 | E21: BG 100% | F21: 1 | G21: THE PRESIDENT OF INDIA | H21: EPCG | I21: Sum Simulator | J21: 0.065 | K21: 1425000 | L21: 1425000 | M21: 1425000 | N21: 673110 | O21: 2098110 | P21: 6 Y | Q21: 47431 | R21: - | S21: - | T21: - | U21: - | V21: =M21 -> 1425000 | W21: ACTIVE | X21: CC
A22: =A21+1 -> 29 | B22: SBI | C22: 45239 | D22: 42426333831 | E22: BG 100% | F22: 1 | G22: THE PRESIDENT OF INDIA | H22: EPCG | I22: PDI Line | J22: 0.065 | K22: 498800 | L22: 498800 | M22: 498800 | N22: 235612 | O22: 734412 | P22: 6 Y | Q22: 47431 | R22: - | S22: - | T22: - | U22: - | V22: =M22 -> 498800 | W22: ACTIVE | X22: CC
A23: =A22+1 -> 30 | B23: SBI | C23: 45239 | D23: 42426400640 | E23: BG 100% | F23: 1 | G23: THE PRESIDENT OF INDIA | H23: EPCG | I23: Module Line | J23: 0.06 | K23: 22734500 | L23: 22734500 | M23: 22734500 | N23: 9764532 | O23: 32499032 | P23: 6 Y | Q23: 47431 | R23: - | S23: - | T23: - | U23: - | V23: =M23 -> 22734500 | W23: ACTIVE | X23: CC
A24: =A23+1 -> 31 | B24: SBI | C24: 45275 | D24: 42525986027 | E24: BG 100% | F24: 1 | G24: THE PRESIDENT OF INDIA | H24: EPCG | I24: Lab Testing Machine - ZWT / CG Goods | J24: 0.065 | K24: 4254045 | L24: 4254045 | M24: 4254045 | N24: 2009432 | O24: 6263477 | P24: 6 Y | Q24: 47467 | R24: - | S24: - | T24: - | U24: - | V24: =M24 -> 4254045 | W24: ACTIVE | X24: CC
A25: =A24+1 -> 32 | B25: SBI | C25: 45222 | D25: 42377916078 | E25: BG 100% | F25: 1 | G25: THE PRESIDENT OF INDIA | H25: CUSTOM DEPT | I25: AGAINST BOE NO 3305835 SOLAR SPACE LC | J25: 0.068 | K25: 4600000 | L25: 4014275 | M25: 4888352 | N25: =O25-M25 -> 340981 | O25: 5229333 | P25: 1 Y | Q25: 45588 | R25: 5194781 | S25: 5527144 | T25: 46318 | U25: 0.0625 | V25: =R25 -> 5194781 | W25: ACTIVE | X25: CA
B26: SBI | C26: 45222 | D26: 42377916078 | E26: BG 100% | F26: 1 | G26: THE PRESIDENT OF INDIA | H26: CUSTOM DEPT | I26: AGAINST BOE NO 3324460 SOLAR SPACE LC | J26: 0.068 | K26: 0 | L26: 433484 | M26: 0 | N26: 0 | O26: 0 | P26: 1 Y | Q26: 45588 | R26: 0 | S26: 0 | T26: 46318 | U26: 0.0625 | V26: - | W26: ACTIVE | X26: CA
B27: SBI | C27: 45222 | D27: 42377916078 | E27: FREE AGAINST BG | F27: 1 | J27: 0.068 | K27: 0 | L27: 152241 | M27: 0 | N27: 0 | O27: 0 | P27: 1 Y | Q27: 45588 | R27: 0 | S27: 0 | T27: 46318 | U27: 0.0625 | V27: - | W27: ACTIVE | X27: CA
A28: =A25+1 -> 33 | B28: SBI | C28: 45299 | D28: 42597394309 | E28: BG 100% | F28: 1 | G28: THE PRESIDENT OF INDIA | H28: CUSTOM DEPT | I28: AGAINST BOE NO 3305835 SOLAR SPACE LC | J28: 0.068 | K28: 820000 | L28: 657976 | M28: 820000 | N28: 57198 | O28: 877198 | P28: 1 Y | Q28: 45665 | R28: 926058 | S28: 985307 | T28: 46395 | U28: 0.0625 | V28: =R28 -> 926058 | W28: ACTIVE | X28: CC
B29: SBI | C29: 45299 | D29: 42597394309 | E29: LC - 10% | F29: 0.1 | J29: 0.068 | K29: - | L29: 268082 | M29: 0 | N29: 0 | O29: 0 | P29: 1 Y | Q29: 45665 | R29: - | S29: - | T29: 46395 | U29: 0.0625 | W29: ACTIVE | X29: CC
A30: =A28+1 -> 34 | B30: SBI | C30: 45372 | D30: 42814707478 | E30: LC - 10% | F30: 0.1 | J30: 0.06 | K30: 7500000 | L30: 8075822 | M30: 7773717 | N30: =O30-L30 -> 39806 | O30: 8115628 | P30: 8M | Q30: 45617 | R30: 8368822 | S30: 8702494 | T30: 46347 | U30: 0.059 | V30: =R30 -> 8368822 | W30: ACTIVE | X30: CC
B31: SBI | C31: 45372 | D31: 42814707478 | E31: LC - 10% | F31: 0.1 | J31: 0.06 | K31: 0 | L31: 293000 | M31: 0 | N31: 0 | O31: 0 | P31: 8M | Q31: 45617 | R31: 0 | S31: 0 | T31: 46347 | U31: 0.059 | V31: 0 | W31: ACTIVE | X31: CC
A32: =A30+1 -> 35 | B32: SBI | C32: 45372 | D32: 42815340031 | E32: BG 100% | F32: 1 | G32: THE PRESIDENT OF INDIA | H32: EPCG | I32: Module Line | J32: 0.068 | K32: 18800000 | L32: 7224000 | M32: 18800000 | N32: =O32-L32 -> 12887370 | O32: 20111370 | P32: 1 Y | Q32: 45737 | R32: 21234178 | S32: 22592744 | T32: 46467 | U32: 0.0625 | V32: =R32 -> 21234178 | W32: ACTIVE | X32: CC
B33: SBI | C33: 45372 | D33: 42815340031 | E33: LC - 10% | F33: 0.1 | J33: 0.068 | K33: - | L33: 12606054 | P33: 1 Y | Q33: 45737 | R33: - | S33: - | T33: - | U33: - | V33: - | W33: ACTIVE | X33: CC
B34: SBI | C34: 45372 | D34: 42815340031 | E34: LC - 10% | F34: 0.1 | J34: 0.068 | K34: - | L34: 150000 | P34: 1 Y | Q34: 45737 | R34: - | S34: - | T34: - | U34: - | V34: - | W34: ACTIVE | X34: CC
A35: =A32+1 -> 36 | B35: SBI | C35: 45378 | D35: 42830614684 | E35: BG 10% | F35: 0.1 | G35: SOLAR ENERGY CORPORATION OF INDIA LTD | H35: PLI | I35: PLI | J35: 0.065 | K35: 18000000 | L35: 18000000 | M35: 18000000 | N35: =O35-L35 -> 12477735 | O35: 30477735 | P35: 8 Y 2M | Q35: 48361 | R35: - | S35: - | T35: - | U35: - | V35: =M35 -> 18000000 | W35: ACTIVE | X35: CC
B36: SBI | C36: 45381 | D36: 42840339454 | E36: LC - 10% | F36: 0.1 | J36: 0.068 | K36: 3200000 | L36: 3400884 | M36: - | N36: 0 | O36: 0 | P36: 1 Y | Q36: 45746 | R36: 3614378 | S36: 3845628 | T36: 46476 | U36: 0.0625 | V36: =R36 -> 3614378 | W36: ACTIVE | X36: CC
A37: 37 | B37: SBI | C37: 45386 | D37: 42855164420 | E37: LC - 10% | F37: 0.1 | J37: 0.068 | K37: 3600000 | L37: 3600000 | M37: 3600000 | N37: =O37-L37 -> 251113 | O37: 3851113 | P37: 1 Y | Q37: 45751 | R37: 4046190 | S37: 4326345 | T37: 46481 | U37: 0.0625 | V37: =R37 -> 4046190 | W37: ACTIVE | X37: CC
A38: 38 | B38: SBI | C38: 45401 | D38: 42896923356 | E38: BG 100% | F38: 1 | G38: THE PRESIDENT OF INDIA | H38: CUSTOM DEPT | I38: AGAINST BOE NO 3324460 SOLAR SPACE LC | J38: 0.068 | K38: 10250000 | L38: 1048000 | M38: 10250000 | N38: =O38-L38 -> 9916976 | O38: 10964976 | P38: 1 Y | Q38: 45766 | R38: 10893478 | S38: 11641884 | T38: 46131 | U38: 0.067 | V38: =R38 -> 10893478 | W38: ACTIVE | X38: CC
B39: SBI | C39: 45401 | D39: 42896923356 | E39: FREE AGAINST BG | F39: 0.1 | J39: 0.068 | K39: 0 | L39: 9845000 | M39: 0 | N39: 0 | O39: 0 | P39: 1 Y | Q39: 45766 | R39: - | S39: - | T39: - | U39: - | V39: - | W39: ACTIVE | X39: CC
A40: =A38+1 -> 39 | B40: SBI | C40: 45463 | D40: 43074817405 | E40: SBLC | F40: 1 | J40: 0.068 | K40: 10218189 | L40: 10218189 | M40: 10218189 | N40: =O40-L40 -> 773850 | O40: 10992039 | P40: 1 Y | Q40: 45858 | R40: 10913952 | S40: 11673869 | T40: 46254 | U40: 0.0625 | V40: =R40 -> 10913952 | W40: ACTIVE | X40: CC
A41: =A40+1 -> 40 | B41: SBI | C41: 45497 | D41: 43183923893 | E41: LC - 10% | F41: 0.1 | J41: 0.0725 | K41: 18900000 | L41: 14031238 | M41: 18900000 | N41: =O41-L41 -> 6595386.2 | O41: 20626624 | P41: 444D | Q41: 45941 | R41: 20451027 | S41: 22146476 | T41: 46385 | U41: 6.6 | V41: =M41 -> 18900000 | W41: ACTIVE | X41: CA
B42: SBI | C42: 45497 | D42: 43183923893 | E42: SBLC | F42: 0.1 | J42: 0.0725 | K42: 0 | L42: 6419789.2 | M42: 0 | N42: 0 | O42: 0 | P42: 444D | Q42: 45941 | R42: 20451027 | S42: 22146476 | T42: 46385 | U42: 6.6 | V42: =M42 -> 0 | W42: ACTIVE | X42: CA
A43: =A205+1 -> 42 | B43: SBI | C43: 45518 | D43: 43254910895 | E43: BG 100% | F43: 1 | G43: THE PRESIDENT OF INDIA | H43: CUSTOM DEPT | I43: AGAINST BOE NO 3305878 SOLAR SPACE LC | J43: 0.068 | K43: 1700000 | L43: 1700000 | M43: 1700000 | N43: =O43-L43 -> 118581 | O43: 1818581 | P43: 1 Y | Q43: 45883 | R43: 1806609 | S43: 1922196 | T43: 46248 | U43: 0.0625 | V43: =R43 -> 1806609 | W43: ACTIVE | X43: CA
A44: 43 | B44: SBI | C44: 45532 | D44: 43286332815 | E44: BG 10% | F44: 0.1 | G44: SUNBREEZE RENEWABLES NINE PVT LTD | H44: ABG | I44: MW is 360 MW | J44: 0.068 | K44: 21500000 | L44: 4680000 | M44: 21500000 | N44: =O44-L44 -> 18319705 | O44: 22999705 | P44: 1 Y | Q44: 45896 | R44: 22848391 | S44: 24310235 | T44: 46261 | U44: 0.0625 | V44: =R44 -> 22848391 | W44: ACTIVE | X44: CC
B45: SBI | C45: 45532 | D45: 43286332815 | E45: SBLC | F45: 0.1 | J45: 0.068 | K45: 0 | L45: 18168391 | M45: 0 | N45: 0 | O45: 0 | P45: 1 Y | Q45: 45896 | R45: 0 | S45: 0 | T45: 46261 | U45: 0.0625 | V45: 0 | W45: ACTIVE | X45: CC
A46: 44 | B46: SBI | C46: 45617 | D46: 43549278543 | E46: FREE AGAINST BG | F46: 0.1 | J46: 0.0725 | K46: 10000000 | L46: 10000000 | M46: 10000000 | N46: =O46-L46 -> 913558 | O46: 10913558 | P46: 444D | Q46: 46061 | R46: - | S46: - | T46: - | U46: - | V46: =M46 -> 10000000 | W46: ACTIVE | X46: CC
A47: 45 | B47: SBI | C47: 45635 | D47: 43607525170 | E47: LC - 10% | F47: 0.1 | J47: 0.07 | K47: 50000000 | L47: =K47-L48 -> 48372095 | M47: 50000000 | N47: =O47-L47 -> 6032826 | O47: 54404921 | P47: 444D | Q47: 46079 | R47: - | S47: - | T47: - | U47: - | V47: =M47 -> 50000000 | W47: ACTIVE | X47: CC
B48: SBI | C48: 45635 | D48: 43607525170 | E48: SBLC | F48: 0.1 | J48: 0.07 | K48: 0 | L48: =1627905 -> 1627905 | M48: 0 | N48: 0 | O48: 0 | P48: 444D | Q48: 46079 | R48: - | S48: - | T48: - | U48: - | V48: =M48 -> 0 | W48: ACTIVE | X48: CC
A49: 46 | B49: SBI | C49: 45643 | D49: 43630359430 | E49: LC - 10% | F49: 0.1 | J49: 0.07 | K49: 100000000 | L49: 78433188 | M49: 100000000 | N49: =O49-L49 -> 30376655 | O49: 108809843 | P49: 444D | Q49: 46087 | R49: - | S49: - | T49: - | U49: - | V49: =M49 -> 100000000 | W49: ACTIVE | X49: CC
B50: SBI | C50: 45643 | D50: 43630359430 | E50: SBLC | F50: 0.1 | J50: 0.07 | K50: 0 | L50: 30376655 | M50: 0 | N50: 0 | O50: 0 | P50: 444D | Q50: 46087 | R50: - | S50: - | T50: - | U50: - | V50: =M50 -> 0 | W50: ACTIVE | X50: CC
A51: 47 | B51: SBI | C51: 45650 | D51: 43649959856 | E51: LC - 10% | F51: 0.1 | J51: 0.0725 | K51: 25000000 | L51: 25000000 | M51: 25000000 | N51: 453125 | O51: 25000000 | P51: 444D | Q51: 46094 | R51: - | S51: - | T51: - | U51: - | V51: =M51 -> 25000000 | W51: ACTIVE | X51: CC
A52: 48 | B52: SBI | C52: 45650 | D52: 43650012802 | E52: LC - 10% | F52: 0.1 | J52: 0.0725 | K52: 25000000 | L52: 25000000 | M52: 25000000 | N52: 453125 | O52: 25000000 | P52: 444D | Q52: 46094 | R52: - | S52: - | T52: - | U52: - | V52: =M52 -> 25000000 | W52: ACTIVE | X52: CC
